Workbook

Sheet Model>>>
C4: Norwegian Cruise Line Holdings
C5: Ticker: NCLH (NYSE)
C6: Date: 10/2/2026
C7: Recommendation: Short, 6-12 months
C9: Key outputs (selected case, DCF!C9)
C10: Current price | I10: =DCF!I2 -> 15.05
C11: Value per share, EV / EBITDA | I11: =DCF!L34 -> 10.833978
C12: Probability-weighted value | I12: =DCF!G44 -> 11.964428
C13: Return to probability-weighted value | I13: =DCF!G45 -> -0.20502142
C14: DCF cross-check value | I14: =DCF!L46 -> 8.1076995
C15: FY2027E net yield growth | I15: ='Operating Model'!I32 -> -0.0072773132
C16: FY2027E Adjusted EBITDA ($mm) | I16: ='Operating Model'!I52 -> 2472.3891
C17: Street-implied FY2027E EBITDA ($mm) | I17: =Consensus!C57 -> 2693.22
C18: FY2027E Adjusted EPS | I18: ='Operating Model'!I63 -> 0.95137614
C19: Consensus FY2027E EPS (Zacks / Yahoo) | I19: =Consensus!D8 -> 1.46
I20: =Consensus!D7 -> 1.67
C21: Price-implied steady-state EBITDA at 9% ($mm) | I21: =DCF!E31 -> 3038.9729
C22: EBITDA the average target requires ($mm) | I22: =Consensus!C67 -> 2912.6059
C23: Sept 30 deposits forecast ($mm) | I23: =Deposits!C70 -> 2940.2197
C24: KPI 1: 1H27 ticket price y/y, consensus case / ours | H24: =AVERAGE('Net Yield Build'!N24:O24) -> -0.0108108 | I24: =AVERAGE('Net Yield Build'!N51:O51) -> -0.026071794
C25: KPI 2: 2027 occupancy, consensus case / ours | H25: ='Net Yield Build'!U20 -> 1.0306424 | I25: ='Net Yield Build'!U47 -> 1.0206424
C27: Formatting
C28: Blue: hard-coded data from filings and public sources
C29: Blue on gray: forecast assumptions and drivers
C30: Black: formulas
C31: Green: links to other sheets
C33: Sheets
C34: Thesis to KPIs | E34: Start here: data -> KPI -> model -> consensus, with dated checks
C35: DCF | E35: Valuation: case switch (C9), WACC, reverse DCF, EV/EBITDA, DCF cross-check, scenarios, sensitivity
C36: Model vs Consensus / Bridge Build | E36: Model vs. consensus; live 2027 EBITDA bridge, one step per KPI
C37: Operating Model | E37: Annual model FY2024A-FY2030E: capacity, net yield, revenue, costs, P&L, cash flow, ROIC
C38: Net Yield Build | E38: Quarterly net yield for the three cases; KPI rows 24 / 51 / 78 (price) and 13 / 40 / 67 (occupancy)
C39: KPI 1 Price Build | E39: Thesis 1: fare cuts on unsold cabins by brand and region -> ticket price per passenger day
C40: KPI 2 Booking Build | E40: Thesis 2: booking shortfall from deposits -> occupancy and late discounts; price-guarantee claims
C41: Fleet Build / Fleet Qtr Build | E41: Ship-level berths; ship x quarter capacity days (504 rows) for quarterly capacity growth
C42: Consensus | E42: Annual and quarterly consensus, ratings, targets, guidance, decoding the target
C43: Quarterly (A) / Income / Cash Flow / Balance | E43: Historical results: 8-K releases and SEC XBRL
C44: Fare Panel / Deposits | E44: Raw fare panel (4,783 itineraries, summarized) and the deposit indicator (back-test, peers, Nov 4 forecast)
C45: Factor & Positioning / Multiple vs Net Yield | E45: Return decomposition, news days, oil test, short interest; multiple vs. net yield
C46: Exhibit Data | E46: Data behind the memo charts

Sheet Thesis to KPIs
B2: Thesis to KPIs: what the alternative data shows, which model inputs it moves, and where we differ from consensus
B3: Net yield = occupancy x net revenue per passenger day. Our base case differs from the consensus case on two KPIs: ticket price per passenger day (KPI 1) and occupancy (KPI 2). Onboard spend, unit costs and fuel also differ; they are listed separately.
B5: A. FY2027: consensus case vs. our base case | C5: Consensus case | D5: Base case | E5: Difference
B6: Occupancy | C6: ='Net Yield Build'!U20 -> 1.0306424 | D6: ='Net Yield Build'!U47 -> 1.0206424 | E6: =(D6-C6)*100 -> -1
B7: KPI 1 input: ticket revenue per passenger day ($) | C7: ='Net Yield Build'!U25 -> 248.40382 | D7: ='Net Yield Build'!U52 -> 243.98634 | E7: =D7/C7-1 -> -0.017783446
B8: Onboard revenue per passenger day ($) | C8: ='Net Yield Build'!U26 -> 131.44647 | D8: ='Net Yield Build'!U53 -> 129.54003 | E8: =D8/C8-1 -> -0.014503524
B9: Net revenue per passenger day ($) | C9: ='Net Yield Build'!U29 -> 283.89472 | D9: ='Net Yield Build'!U56 -> 279.17896 | E9: =D9/C9-1 -> -0.016610973
B10: Net yield ($ per capacity day) | C10: ='Net Yield Build'!U30 -> 292.59394 | D10: ='Net Yield Build'!U57 -> 284.94188 | E10: =D10/C10-1 -> -0.026152488
B11: Net yield growth y/y | C11: ='Net Yield Build'!U31 -> 0.015702552 | D11: ='Net Yield Build'!U58 -> -0.0072773132 | E11: =(D11-C11)*100 -> -2.2979866
B12: Adjusted EBITDA ($mm) | C12: =DCF!E41 -> 2787.034 | D12: =DCF!E42 -> 2472.3891 | E12: =D12/C12-1 -> -0.11289598
B14: B. The two KPIs by quarter | C14: 3Q26E | D14: 4Q26E | E14: 1Q27E | F14: 2Q27E | G14: 3Q27E | H14: 4Q27E
B15: KPI 1: like-for-like ticket price y/y, consensus case | C15: ='Net Yield Build'!L24 -> -0.0995 | D15: ='Net Yield Build'!M24 -> -0.0603 | E15: ='Net Yield Build'!N24 -> -0.013559834 | F15: ='Net Yield Build'!O24 -> -0.0080617665 | G15: ='Net Yield Build'!P24 -> 0.0039092903 | H15: ='Net Yield Build'!Q24 -> 0.0029699256
B16: KPI 1: ours | C16: ='Net Yield Build'!L51 -> -0.1055 | D16: ='Net Yield Build'!M51 -> -0.0762 | E16: ='Net Yield Build'!N51 -> -0.028407702 | F16: ='Net Yield Build'!O51 -> -0.023735886 | G16: ='Net Yield Build'!P51 -> -0.0044150741 | H16: ='Net Yield Build'!Q51 -> -0.0076694521
B17: of which Thesis 1 (fare cuts on unsold cabins) | C17: ='Net Yield Build'!L42 -> 0 | D17: ='Net Yield Build'!M42 -> -0.032896144 | E17: ='Net Yield Build'!N42 -> -0.033407702 | F17: ='Net Yield Build'!O42 -> -0.028735886 | G17: ='Net Yield Build'!P42 -> -0.0028358453 | H17: ='Net Yield Build'!Q42 -> -0.0060902232
B18: of which Thesis 2 (late discounts on the shortfall) | C18: ='Net Yield Build'!L44 -> 0 | D18: ='Net Yield Build'!M44 -> 0 | E18: ='Net Yield Build'!N44 -> 0 | F18: ='Net Yield Build'!O44 -> 0 | G18: ='Net Yield Build'!P44 -> -0.0065792288 | H18: ='Net Yield Build'!Q44 -> -0.0065792288
B19: KPI 2: occupancy change y/y (pts), consensus case | C19: ='Net Yield Build'!L13 -> -2.4 | D19: ='Net Yield Build'!M13 -> -2.8 | E19: ='Net Yield Build'!N13 -> -1 | F19: ='Net Yield Build'!O13 -> 0.5 | G19: ='Net Yield Build'!P13 -> 1.5 | H19: ='Net Yield Build'!Q13 -> 2
B20: KPI 2: ours | C20: ='Net Yield Build'!L40 -> -2.4 | D20: ='Net Yield Build'!M40 -> -2.8 | E20: ='Net Yield Build'!N40 -> -2 | F20: ='Net Yield Build'!O40 -> -0.5 | G20: ='Net Yield Build'!P40 -> 0.5 | H20: ='Net Yield Build'!Q40 -> 1
B21: Net yield y/y, consensus case | C21: ='Net Yield Build'!L31 -> -0.079971158 | D21: ='Net Yield Build'!M31 -> -0.059984861 | E21: ='Net Yield Build'!N31 -> -0.010613405 | F21: ='Net Yield Build'!O31 -> 0.007404509 | G21: ='Net Yield Build'!P31 -> 0.028777065 | H21: ='Net Yield Build'!Q31 -> 0.037263476
B22: Net yield y/y, ours | C22: ='Net Yield Build'!L58 -> -0.084022341 | D22: ='Net Yield Build'!M58 -> -0.070006965 | E22: ='Net Yield Build'!N58 -> -0.034691082 | F22: ='Net Yield Build'!O58 -> -0.017589168 | G22: ='Net Yield Build'!P58 -> 0.0085040694 | H22: ='Net Yield Build'!Q58 -> 0.014772734
B24: C. Each thesis, from the data to the model
B25: Thesis | C25: What the data shows | D25: What it implies | E25: KPI it moves | F25: Consensus case | G25: Ours | H25: 2027 EBITDA ($mm)
B26: Thesis 1: NCL is cutting price to fill Caribbean ships because it is losing share there | C26: ="1H27 Caribbean fares "&TEXT('KPI 1 Price Build'!F16,"0.0%")&" vs. peers "&TEXT('KPI 1 Price Build'!F19,"0.0%")&"; NCL elsewhere "&TEXT('KPI 1 Price Build'!F17,"0.0%") -> 1H27 Caribbean fares -14.5% vs. peers -0.5%; NCL elsewhere -2.8% | D26: Cuts hit the cabins NCL still has to sell for 1H27 | E26: KPI 1: 1H27 ticket price | F26: =AVERAGE('Net Yield Build'!N24:O24) -> -0.0108108 | G26: =AVERAGE('Net Yield Build'!N51:O51) -> -0.026071794 | H26: ='Model vs Consensus'!C26 -> -43.523693
B27: Thesis 2: the price guarantee keeps guests from booking early | C27: ="Deposits per future berth-day "&TEXT(Deposits!F26,"0.0%")&" y/y; 7th straight decline" -> Deposits per future berth-day -8.3% y/y; 7th straight decline | D27: A booking shortfall NCL fills late at a discount | E27: KPI 1: 2H27 ticket price | F27: =AVERAGE('Net Yield Build'!P24:Q24) -> 0.0034396079 | G27: =AVERAGE('Net Yield Build'!P51:Q51) -> -0.0060422631 | H27: ='Model vs Consensus'!C27 -> -17.090892
B28: Thesis 2 (continued) | C28: ="Occupancy fell "&TEXT(-'KPI 2 Booking Build'!D17,"0.0")&" pts in 2Q26 with the indicator at "&TEXT('KPI 2 Booking Build'!D18,"0.0%") -> Occupancy fell 1.5 pts in 2Q26 with the indicator at -6.1% | D28: Part of the shortfall sails empty | E28: KPI 2: 2027 occupancy | F28: ='Net Yield Build'!U20 -> 1.0306424 | G28: ='Net Yield Build'!U47 -> 1.0206424 | H28: ='Model vs Consensus'!C28 -> -76.058523
B30: Other differences (not part of either thesis)
B31: Onboard spend growth per passenger day, 2027 | C31: 2025: -0.3%; 1H26: +1.0% (Quarterly (A)) | F31: ='Net Yield Build'!N18 -> 0.035 | G31: ='Net Yield Build'!N45 -> 0.02 | H31: ='Model vs Consensus'!C29 -> -41.546117
B32: Unit costs ex fuel per capacity day, 2027 y/y | C32: 1H26 about flat; 3Q26 guide -0.9%; $225M savings plan | F32: ='Operating Model'!I11 -> -0.005 | G32: ='Operating Model'!I12 -> 0.01 | H32: ='Model vs Consensus'!C30 -> -107.10628
B33: Fuel price per ton, net of hedges ($) | C33: 2026 guide $780; Brent +63% y/y | F33: ='Operating Model'!I16 -> 760 | G33: ='Operating Model'!I17 -> 800
B34: Unit costs and fuel share one bridge step (Model vs Consensus row 30).
B36: D. What each KPI is worth (base case, 2027)
B37: 1 pt of ticket price per passenger day: EBITDA ($mm) | C37: ='Net Yield Build'!U59*(1-'Net Yield Build'!U54)*0.01 -> 49.066202 | D37: per share: | E37: =C37*$C$39 -> 0.88788621
B38: 1 pt of occupancy: EBITDA ($mm) | C38: ='Net Yield Build'!U46*0.01*'Net Yield Build'!U56 -> 75.71873 | D38: per share: | E38: =C38*$C$39 -> 1.3701818
B39: Value per share of $1M of 2027 EBITDA (at today's multiple) | C39: =DCF!F25/DCF!L33 -> 0.018095678
B40: Value per share on the two theses alone (consensus-case onboard, costs and fuel) | C40: =((DCF!E42-'Model vs Consensus'!C29-'Model vs Consensus'!C30)*DCF!F25-DCF!F22)/DCF!L33 -> 13.523944 | D40: =C40/DCF!I2-1 -> -0.1013991
B42: E. Dated checks: when each KPI gets tested
B43: Nov 4, 2026: 3Q26 10-Q | C43: Sept 30 advance ticket sales vs. our $2.94B (KPI 2 shortfall) | G43: ="Below "&TEXT('KPI 2 Booking Build'!D58,"$#,##0")&"M supports; at or above "&TEXT('KPI 2 Booking Build'!D59,"$#,##0")&"M we cover" -> Below $2,970M supports; at or above $3,110M we cover
B44: Late Feb 2027: first 2027 guide | C44: Net yield guide vs. the consensus case (KPI 1 and KPI 2) | G44: ="At or below flat supports; consensus case "&TEXT('Net Yield Build'!U31,"+0.0%") -> At or below flat supports; consensus case +1.6%
B45: Monthly: fare panel re-run | C45: 1H27 Caribbean cuts on unsold cabins (KPI 1) | G45: Cuts back near peers would undo Thesis 1
B46: May 2027: 1Q27 results | C46: Reported ticket revenue per passenger day and occupancy | G46: ="Ours: occupancy "&TEXT('Net Yield Build'!N47,"0.0%")&", ticket price "&TEXT('Net Yield Build'!N51,"0.0%") -> Ours: occupancy 101.8%, ticket price -2.8%
B48: Green = links; black = formulas. Every number on this sheet comes from the KPI builds, the Net Yield Build or the DCF.

Sheet DCF
B2: Norwegian Cruise Line Holdings | G2: Current Price | I2: 15.05
B4: Valuation
B5: $mm except per-share data
B7: Case Selection
B9: Selected Case | C9: 2
B11: Bull case (Street-like) | C11: 1
B12: Base case (our view) | C12: 2
B13: Bear case | C13: 3
B15: Market data | H15: WACC
B16: Share price | F16: =I2 -> 15.05 | H16: Risk-free rate (10-year Treasury) | L16: 0.042
B17: Basic shares outstanding (M) | F17: 459.19 | H17: Beta (levered) | L17: 1.8
B18: Market capitalization | F18: =F16*F17 -> 6910.8095 | H18: Equity risk premium | L18: 0.05
B19: Net debt (Jun 30, 2026) | F19: ='Quarterly (A)'!J40 -> 14800 | H19: Cost of equity | L19: =L16+L17*L18 -> 0.132
B20: Enterprise value | F20: =F18+F19 -> 21710.809 | H20: Pre-tax cost of debt | L20: 0.0725
B21: Net debt at YE2026E (model, selected case) | F21: ='Operating Model'!H88 -> 15883.244 | H21: Tax rate | L21: 0.02
B22: Net debt at YE2026E used in valuation | F22: 15800 | H22: Equity weight | L22: =F18/(F18+F19) -> 0.31831192
B23: Forward EV (market cap + YE2026E net debt) | F23: =F18+F22 -> 22710.809 | H23: Debt weight | L23: =1-L22 -> 0.68168808
B24: Street-implied FY2027E EBITDA | F24: =Consensus!C57 -> 2693.22 | H24: WACC | L24: =L19*L22+L20*(1-L21)*L23 -> 0.090451112
B25: Market EV / FY2027E EBITDA (Street) | F25: =F23/F24 -> 8.4325861
B27: Price-implied expectations (reverse DCF) | H27: Primary valuation: EV / FY2027E EBITDA
B28: Cost of capital | C28: 0.08 | D28: 0.085 | E28: 0.09 | F28: =L24 -> 0.090451112 | H28: FY2027E Adjusted EBITDA (selected case) | L28: ='Operating Model'!I52 -> 2472.3891
B29: Enterprise value (today) | C29: =$F$20 -> 21710.809 | D29: =$F$20 -> 21710.809 | E29: =$F$20 -> 21710.809 | F29: =$F$20 -> 21710.809 | H29: Target EV / EBITDA | L29: =CHOOSE($C$9,$L$36,$F$25,$F$25) -> 8.4325861
B30: (+) Steady-state D&A (2026E guide) | C30: ='Operating Model'!$H$54 -> 1085 | D30: ='Operating Model'!$H$54 -> 1085 | E30: ='Operating Model'!$H$54 -> 1085 | F30: ='Operating Model'!$H$54 -> 1085 | H30: Implied enterprise value | L30: =L28*L29 -> 20848.634
B31: Implied steady-state EBITDA | C31: =C29*C28+C30 -> 2821.8648 | D31: =D29*D28+D30 -> 2930.4188 | E31: =E29*E28+E30 -> 3038.9729 | F31: =F29*F28+F30 -> 3048.7669 | H31: (-) Net debt at YE2026E | L31: =$F$22 -> 15800
B32: 2026E EBITDA (model) | C32: ='Operating Model'!$H$52 -> 2471.989 | D32: ='Operating Model'!$H$52 -> 2471.989 | E32: ='Operating Model'!$H$52 -> 2471.989 | F32: ='Operating Model'!$H$52 -> 2471.989 | H32: Equity value | L32: =L30-L31 -> 5048.6336
B33: Implied EBITDA vs 2026E | C33: =C31/C32-1 -> 0.14153615 | D33: =D31/D32-1 -> 0.1854498 | E33: =E31/E32-1 -> 0.22936344 | F33: =F31/F32-1 -> 0.23332543 | H33: Diluted shares (M) | L33: ='Operating Model'!I62 -> 466
B34: Implied net yield rebuild vs 2026E (constant unit costs) | C34: =(C31-C32)/'Operating Model'!$H$33 -> 0.04643638 | D34: =(D31-D32)/'Operating Model'!$H$33 -> 0.060843941 | E34: =(E31-E32)/'Operating Model'!$H$33 -> 0.075251502 | F34: =(F31-F32)/'Operating Model'!$H$33 -> 0.076551386 | H34: Implied value per share | L34: =L32/L33 -> 10.833978
B35: Implied net yield vs 2025A peak | C35: =('Operating Model'!$H$31/'Operating Model'!$G$31)*(1+C34)-1 -> -0.0024471849 | D35: =('Operating Model'!$H$31/'Operating Model'!$G$31)*(1+D34)-1 -> 0.011287337 | E35: =('Operating Model'!$H$31/'Operating Model'!$G$31)*(1+E34)-1 -> 0.025021858 | F35: =('Operating Model'!$H$31/'Operating Model'!$G$31)*(1+F34)-1 -> 0.026261019 | H35: Return vs current price | L35: =L34/$I$2-1 -> -0.28013437
B36: Memo: March 2026 company guide for 2026 EBITDA | C36: =Consensus!C44 -> 2950 | H36: Bull-case EV / EBITDA (re-rating) | L36: 9
H38: DCF cross-check (value at YE2026)
B39: Scenario summary (all cases live) | H39: PV of unlevered FCF, 2027E-2030E | L39: =SUM('Operating Model'!I107:L107) -> 850.73285
B40: Case | C40: Prob. | D40: FY27 net yield | E40: FY27 EBITDA | F40: EV/EBITDA | G40: Value | H40: 2030E EBITDA | L40: ='Operating Model'!L52 -> 3154.0527
B41: Bull | C41: 0.25 | D41: ='Net Yield Build'!U31 -> 0.015702552 | E41: ='Net Yield Build'!U37-'Operating Model'!$G$45*(1+'Operating Model'!$H$11)*(1+'Operating Model'!$I$11)*'Net Yield Build'!U19-'Operating Model'!$H$47*('Net Yield Build'!U19/'Net Yield Build'!T19)*0.99*'Operating Model'!$I$16/1000 -> 2787.034 | F41: =$L$36 -> 9 | G41: =(E41*F41-$F$22)/$L$33 -> 19.921257 | H41: Exit EV / EBITDA (today's market multiple) | L41: =$F$25 -> 8.4325861
B42: Base | C42: 0.5 | D42: ='Net Yield Build'!U58 -> -0.0072773132 | E42: ='Net Yield Build'!U64-'Operating Model'!$G$45*(1+'Operating Model'!$H$12)*(1+'Operating Model'!$I$12)*'Net Yield Build'!U46-'Operating Model'!$H$47*('Net Yield Build'!U46/'Net Yield Build'!T46)*0.99*'Operating Model'!$I$17/1000 -> 2472.3891 | F42: =$F$25 -> 8.4325861 | G42: =(E42*F42-$F$22)/$L$33 -> 10.833978 | H42: Terminal value | L42: =L40*L41 -> 26596.821
B43: Bear | C43: 0.25 | D43: ='Net Yield Build'!U85 -> -0.026430387 | E43: ='Net Yield Build'!U91-'Operating Model'!$G$45*(1+'Operating Model'!$H$13)*(1+'Operating Model'!$I$13)*'Net Yield Build'!U73-'Operating Model'!$H$47*('Net Yield Build'!U73/'Net Yield Build'!T73)*0.99*'Operating Model'!$I$18/1000 -> 2220.0924 | F43: =$F$25 -> 8.4325861 | G43: =(E43*F43-$F$22)/$L$33 -> 6.2684978 | H43: PV of terminal value | L43: =L42/(1+$L$24)^4 -> 18810.699
B44: Probability-weighted | C44: =SUM(C41:C43) -> 1 | G44: =C41*G41+C42*G42+C43*G43 -> 11.964428 | H44: Enterprise value | L44: =L39+L43 -> 19661.432
B45: Return vs current price | G45: =G44/$I$2-1 -> -0.20502142 | H45: (-) Net debt at YE2026E | L45: =$F$21 -> 15883.244
H46: Value per share (floored at zero) | L46: =MAX(0,(L44-L45)/L33) -> 8.1076995
H47: Return vs current price | L47: =L46/$I$2-1 -> -0.46128243
B49: Sensitivity: value per share vs FY2027E net yield growth and EV/EBITDA (selected-case costs)
B50: Net yield growth \ multiple | C50: 7.5 | D50: 8 | E50: =$F$25 -> 8.4325861 | F50: 9 | G50: 9.5
B51: -0.04 | C51: =((('Operating Model'!$H$31*(1+$B51)*'Operating Model'!$I$27)-'Operating Model'!$I$46-'Operating Model'!$I$49)*C$50-$F$22)/$L$33 -> 1.7861899 | D51: =((('Operating Model'!$H$31*(1+$B51)*'Operating Model'!$I$27)-'Operating Model'!$I$46-'Operating Model'!$I$49)*D$50-$F$22)/$L$33 -> 4.1656412 | E51: =((('Operating Model'!$H$31*(1+$B51)*'Operating Model'!$I$27)-'Operating Model'!$I$46-'Operating Model'!$I$49)*E$50-$F$22)/$L$33 -> 6.2242762 | F51: =((('Operating Model'!$H$31*(1+$B51)*'Operating Model'!$I$27)-'Operating Model'!$I$46-'Operating Model'!$I$49)*F$50-$F$22)/$L$33 -> 8.9245438 | G51: =((('Operating Model'!$H$31*(1+$B51)*'Operating Model'!$I$27)-'Operating Model'!$I$46-'Operating Model'!$I$49)*G$50-$F$22)/$L$33 -> 11.303995
B52: -0.03 | C52: =((('Operating Model'!$H$31*(1+$B52)*'Operating Model'!$I$27)-'Operating Model'!$I$46-'Operating Model'!$I$49)*C$50-$F$22)/$L$33 -> 3.0391127 | D52: =((('Operating Model'!$H$31*(1+$B52)*'Operating Model'!$I$27)-'Operating Model'!$I$46-'Operating Model'!$I$49)*D$50-$F$22)/$L$33 -> 5.5020922 | E52: =((('Operating Model'!$H$31*(1+$B52)*'Operating Model'!$I$27)-'Operating Model'!$I$46-'Operating Model'!$I$49)*E$50-$F$22)/$L$33 -> 7.6329935 | F52: =((('Operating Model'!$H$31*(1+$B52)*'Operating Model'!$I$27)-'Operating Model'!$I$46-'Operating Model'!$I$49)*F$50-$F$22)/$L$33 -> 10.428051 | G52: =((('Operating Model'!$H$31*(1+$B52)*'Operating Model'!$I$27)-'Operating Model'!$I$46-'Operating Model'!$I$49)*G$50-$F$22)/$L$33 -> 12.891031
B53: -0.02 | C53: =((('Operating Model'!$H$31*(1+$B53)*'Operating Model'!$I$27)-'Operating Model'!$I$46-'Operating Model'!$I$49)*C$50-$F$22)/$L$33 -> 4.2920356 | D53: =((('Operating Model'!$H$31*(1+$B53)*'Operating Model'!$I$27)-'Operating Model'!$I$46-'Operating Model'!$I$49)*D$50-$F$22)/$L$33 -> 6.8385432 | E53: =((('Operating Model'!$H$31*(1+$B53)*'Operating Model'!$I$27)-'Operating Model'!$I$46-'Operating Model'!$I$49)*E$50-$F$22)/$L$33 -> 9.0417108 | F53: =((('Operating Model'!$H$31*(1+$B53)*'Operating Model'!$I$27)-'Operating Model'!$I$46-'Operating Model'!$I$49)*F$50-$F$22)/$L$33 -> 11.931559 | G53: =((('Operating Model'!$H$31*(1+$B53)*'Operating Model'!$I$27)-'Operating Model'!$I$46-'Operating Model'!$I$49)*G$50-$F$22)/$L$33 -> 14.478066
B54: -0.01 | C54: =((('Operating Model'!$H$31*(1+$B54)*'Operating Model'!$I$27)-'Operating Model'!$I$46-'Operating Model'!$I$49)*C$50-$F$22)/$L$33 -> 5.5449584 | D54: =((('Operating Model'!$H$31*(1+$B54)*'Operating Model'!$I$27)-'Operating Model'!$I$46-'Operating Model'!$I$49)*D$50-$F$22)/$L$33 -> 8.1749943 | E54: =((('Operating Model'!$H$31*(1+$B54)*'Operating Model'!$I$27)-'Operating Model'!$I$46-'Operating Model'!$I$49)*E$50-$F$22)/$L$33 -> 10.450428 | F54: =((('Operating Model'!$H$31*(1+$B54)*'Operating Model'!$I$27)-'Operating Model'!$I$46-'Operating Model'!$I$49)*F$50-$F$22)/$L$33 -> 13.435066 | G54: =((('Operating Model'!$H$31*(1+$B54)*'Operating Model'!$I$27)-'Operating Model'!$I$46-'Operating Model'!$I$49)*G$50-$F$22)/$L$33 -> 16.065102
B55: 0 | C55: =((('Operating Model'!$H$31*(1+$B55)*'Operating Model'!$I$27)-'Operating Model'!$I$46-'Operating Model'!$I$49)*C$50-$F$22)/$L$33 -> 6.7978812 | D55: =((('Operating Model'!$H$31*(1+$B55)*'Operating Model'!$I$27)-'Operating Model'!$I$46-'Operating Model'!$I$49)*D$50-$F$22)/$L$33 -> 9.5114453 | E55: =((('Operating Model'!$H$31*(1+$B55)*'Operating Model'!$I$27)-'Operating Model'!$I$46-'Operating Model'!$I$49)*E$50-$F$22)/$L$33 -> 11.859145 | F55: =((('Operating Model'!$H$31*(1+$B55)*'Operating Model'!$I$27)-'Operating Model'!$I$46-'Operating Model'!$I$49)*F$50-$F$22)/$L$33 -> 14.938573 | G55: =((('Operating Model'!$H$31*(1+$B55)*'Operating Model'!$I$27)-'Operating Model'!$I$46-'Operating Model'!$I$49)*G$50-$F$22)/$L$33 -> 17.652137
B56: 0.01 | C56: =((('Operating Model'!$H$31*(1+$B56)*'Operating Model'!$I$27)-'Operating Model'!$I$46-'Operating Model'!$I$49)*C$50-$F$22)/$L$33 -> 8.0508041 | D56: =((('Operating Model'!$H$31*(1+$B56)*'Operating Model'!$I$27)-'Operating Model'!$I$46-'Operating Model'!$I$49)*D$50-$F$22)/$L$33 -> 10.847896 | E56: =((('Operating Model'!$H$31*(1+$B56)*'Operating Model'!$I$27)-'Operating Model'!$I$46-'Operating Model'!$I$49)*E$50-$F$22)/$L$33 -> 13.267863 | F56: =((('Operating Model'!$H$31*(1+$B56)*'Operating Model'!$I$27)-'Operating Model'!$I$46-'Operating Model'!$I$49)*F$50-$F$22)/$L$33 -> 16.442081 | G56: =((('Operating Model'!$H$31*(1+$B56)*'Operating Model'!$I$27)-'Operating Model'!$I$46-'Operating Model'!$I$49)*G$50-$F$22)/$L$33 -> 19.239173
B57: 0.02 | C57: =((('Operating Model'!$H$31*(1+$B57)*'Operating Model'!$I$27)-'Operating Model'!$I$46-'Operating Model'!$I$49)*C$50-$F$22)/$L$33 -> 9.3037269 | D57: =((('Operating Model'!$H$31*(1+$B57)*'Operating Model'!$I$27)-'Operating Model'!$I$46-'Operating Model'!$I$49)*D$50-$F$22)/$L$33 -> 12.184347 | E57: =((('Operating Model'!$H$31*(1+$B57)*'Operating Model'!$I$27)-'Operating Model'!$I$46-'Operating Model'!$I$49)*E$50-$F$22)/$L$33 -> 14.67658 | F57: =((('Operating Model'!$H$31*(1+$B57)*'Operating Model'!$I$27)-'Operating Model'!$I$46-'Operating Model'!$I$49)*F$50-$F$22)/$L$33 -> 17.945588 | G57: =((('Operating Model'!$H$31*(1+$B57)*'Operating Model'!$I$27)-'Operating Model'!$I$46-'Operating Model'!$I$49)*G$50-$F$22)/$L$33 -> 20.826209
B58: 0.03 | C58: =((('Operating Model'!$H$31*(1+$B58)*'Operating Model'!$I$27)-'Operating Model'!$I$46-'Operating Model'!$I$49)*C$50-$F$22)/$L$33 -> 10.55665 | D58: =((('Operating Model'!$H$31*(1+$B58)*'Operating Model'!$I$27)-'Operating Model'!$I$46-'Operating Model'!$I$49)*D$50-$F$22)/$L$33 -> 13.520798 | E58: =((('Operating Model'!$H$31*(1+$B58)*'Operating Model'!$I$27)-'Operating Model'!$I$46-'Operating Model'!$I$49)*E$50-$F$22)/$L$33 -> 16.085297 | F58: =((('Operating Model'!$H$31*(1+$B58)*'Operating Model'!$I$27)-'Operating Model'!$I$46-'Operating Model'!$I$49)*F$50-$F$22)/$L$33 -> 19.449096 | G58: =((('Operating Model'!$H$31*(1+$B58)*'Operating Model'!$I$27)-'Operating Model'!$I$46-'Operating Model'!$I$49)*G$50-$F$22)/$L$33 -> 22.413244

Sheet Model vs Consensus
B2: Model vs. consensus (selected case, DCF!C9)
C4: Model | D4: Consensus | E4: Difference | F4: Difference (%)
B5: FY2026E revenue ($mm) | C5: ='Operating Model'!H38 -> 10006.098 | D5: =Consensus!C6 -> 10030 | E5: =C5-D5 -> -23.901594 | F5: =C5/D5-1 -> -0.0023830104
B6: FY2027E revenue ($mm) | C6: ='Operating Model'!I38 -> 10339.88 | D6: =Consensus!D6 -> 10570 | E6: =C6-D6 -> -230.11953 | F6: =C6/D6-1 -> -0.021771005
B7: FY2027E Adjusted EBITDA ($mm) | C7: ='Operating Model'!I52 -> 2472.3891 | D7: =Consensus!C57 -> 2693.22 | E7: =C7-D7 -> -220.83094 | F7: =C7/D7-1 -> -0.081995135
B8: FY2026E Adjusted EPS (vs. Zacks) | C8: ='Operating Model'!H63 -> 1.4404077 | D8: =Consensus!C8 -> 1.36 | E8: =C8-D8 -> 0.080407713 | F8: =C8/D8-1 -> 0.059123318
B9: FY2027E Adjusted EPS (vs. Zacks) | C9: ='Operating Model'!I63 -> 0.95137614 | D9: =Consensus!D8 -> 1.46 | E9: =C9-D9 -> -0.50862386 | F9: =C9/D9-1 -> -0.34837251
B10: FY2027E Adjusted EPS (vs. Yahoo) | C10: ='Operating Model'!I63 -> 0.95137614 | D10: =Consensus!D7 -> 1.67 | E10: =C10-D10 -> -0.71862386 | F10: =C10/D10-1 -> -0.43031369
B11: FY2027E net yield growth (vs. consensus case) | C11: ='Operating Model'!I32 -> -0.0072773132 | D11: ='Net Yield Build'!U31 -> 0.015702552 | E11: =C11-D11 -> -0.022979866 | F11: =C11-D11 -> -0.022979866
B13: Adjusted EPS by quarter: model vs. Nasdaq/Zacks consensus
B14: Quarter | C14: Model | D14: Consensus | E14: Difference
B15: 3Q26 | C15: ='Net Yield Build'!L125 -> 0.8975119 | D15: =Consensus!C12 -> 0.83 | E15: =C15-D15 -> 0.067511904
B16: 4Q26 | C16: ='Net Yield Build'!M125 -> -0.15327803 | D16: =Consensus!D12 -> -0.1 | E16: =C16-D16 -> -0.053278028
B17: 1Q27 | C17: ='Net Yield Build'!N125 -> -0.11869737 | D17: =Consensus!E12 -> -0.04 | E17: =C17-D17 -> -0.078697365
B18: 2Q27 | C18: ='Net Yield Build'!O125 -> 0.28160162 | D18: =Consensus!F12 -> 0.37 | E18: =C18-D18 -> -0.088398384
B19: 3Q27 | C19: ='Net Yield Build'!P125 -> 0.88003919 | D19: =Consensus!G12 -> 0.97 | E19: =C19-D19 -> -0.089960806
B20: 4Q27 | C20: ='Net Yield Build'!Q125 -> -0.091567307 | D20: =Consensus!H12 -> 0.16 | E20: =C20-D20 -> -0.25156731
B22: 2027 Adjusted EBITDA bridge: consensus case to model base case (Bridge Build)
B23: Step | C23: $mm
B24: Consensus case (bull inputs) | C24: ='Bridge Build'!D6 -> 2787.034
B25: 2H26 exit rate | C25: ='Bridge Build'!E7 -> -29.319419
B26: Thesis 1 -> KPI 1: fare cuts on unsold cabins (1H27) | C26: ='Bridge Build'!E8 -> -43.523693
B27: Thesis 2 -> KPI 1: late discounts on the booking shortfall (2H27) | C27: ='Bridge Build'!E9 -> -17.090892
B28: Thesis 2 -> KPI 2: occupancy | C28: ='Bridge Build'!E10 -> -76.058523
B29: Other: onboard spend growth | C29: ='Bridge Build'!E11 -> -41.546117
B30: Other: unit costs and fuel | C30: ='Bridge Build'!E12 -> -107.10628
B31: Model base case | C31: =DCF!E42 -> 2472.3891
B32: Check: steps sum to the difference | C32: =C24+SUM(C25:C30)-C31 -> 0

Sheet Bridge Build
B2: Bridge Build: 2027 EBITDA from the consensus case to our base case, one KPI at a time
B3: Each block reruns the quarterly net yield with one more group of base-case inputs switched on, in order. The change between blocks is the EBITDA attributable to that group. The last step must equal DCF!E42 (checks in row 13).
B5: Step | D5: 2027 EBITDA | E5: Change
B6: Consensus case (bull inputs) | D6: =J21 -> 2787.034
B7: 2H26 exit (3Q-4Q26 inputs) | D7: =J30 -> 2757.7146 | E7: =D7-D6 -> -29.319419
B8: Thesis 1 -> KPI 1: fare cuts on unsold cabins | D8: =J39 -> 2714.1909 | E8: =D8-D7 -> -43.523693
B9: Thesis 2 -> KPI 1: late discounts on the shortfall | D9: =J48 -> 2697.1 | E9: =D9-D8 -> -17.090892
B10: Thesis 2 -> KPI 2: occupancy | D10: =J57 -> 2621.0415 | E10: =D10-D9 -> -76.058523
B11: Other: onboard spend growth | D11: =J66 -> 2579.4953 | E11: =D11-D10 -> -41.546117
B12: Other: unit costs and fuel | D12: =J65-'Operating Model'!$G$45*(1+'Operating Model'!$H$12)*(1+'Operating Model'!$I$12)*'Net Yield Build'!$U$19-'Operating Model'!$H$47*('Net Yield Build'!$U$19/'Net Yield Build'!$T$19)*0.99*'Operating Model'!$I$17/1000 -> 2472.3891 | E12: =D12-D11 -> -107.10628
B13: Checks: block 0 = DCF!E41, final = DCF!E42 (both should be 0) | D13: =D6-DCF!E41 -> 0 | E13: =D12-DCF!E42 -> 0
B14: Block 0: Consensus case (bull inputs) | D14: 3Q26E | E14: 4Q26E | F14: 1Q27E | G14: 2Q27E | H14: 3Q27E | I14: 4Q27E | J14: FY2027E
B15: Occupancy change y/y (pts) | D15: ='Net Yield Build'!L13 -> -2.4 | E15: ='Net Yield Build'!M13 -> -2.8 | F15: ='Net Yield Build'!N13 -> -1 | G15: ='Net Yield Build'!O13 -> 0.5 | H15: ='Net Yield Build'!P13 -> 1.5 | I15: ='Net Yield Build'!Q13 -> 2
B16: Occupancy | D16: ='Net Yield Build'!H20+D15/100 -> 1.0399959 | E16: ='Net Yield Build'!I20+E15/100 -> 0.98972285 | F16: ='Net Yield Build'!J20+F15/100 -> 1.0277757 | G16: ='Net Yield Build'!K20+G15/100 -> 1.0287188 | H16: =D16+H15/100 -> 1.0549959 | I16: =E16+I15/100 -> 1.0097229
B17: Like-for-like ticket price change + mix | D17: ='Net Yield Build'!L14+'Net Yield Build'!L15+'Net Yield Build'!L17+'Net Yield Build'!L16 -> -0.0945 | E17: ='Net Yield Build'!M14+'Net Yield Build'!M15+'Net Yield Build'!M17+'Net Yield Build'!M16 -> -0.0553 | F17: ='Net Yield Build'!N14+'Net Yield Build'!N15+'Net Yield Build'!N17+'Net Yield Build'!N16 -> -0.0035598342 | G17: ='Net Yield Build'!O14+'Net Yield Build'!O15+'Net Yield Build'!O17+'Net Yield Build'!O16 -> 0.0019382335 | H17: ='Net Yield Build'!P14+'Net Yield Build'!P15+'Net Yield Build'!P17+'Net Yield Build'!P16 -> 0.01390929 | I17: ='Net Yield Build'!Q14+'Net Yield Build'!Q15+'Net Yield Build'!Q17+'Net Yield Build'!Q16 -> 0.012969926
B18: Ticket revenue per passenger day ($) | D18: ='Net Yield Build'!H25*(1+D17) -> 271.8448 | E18: ='Net Yield Build'!I25*(1+E17) -> 223.80161 | F18: ='Net Yield Build'!J25*(1+F17) -> 231.64226 | G18: ='Net Yield Build'!K25*(1+G17) -> 256.92126 | H18: =D18*(1+H17) -> 275.62597 | I18: =E18*(1+I17) -> 226.7043
B19: Onboard revenue per passenger day ($) | D19: ='Net Yield Build'!H26*(1+'Net Yield Build'!L18) -> 135.27676 | E19: ='Net Yield Build'!I26*(1+'Net Yield Build'!M18) -> 118.66645 | F19: ='Net Yield Build'!J26*(1+'Net Yield Build'!N18) -> 123.07054 | G19: ='Net Yield Build'!K26*(1+'Net Yield Build'!O18) -> 139.04939 | H19: =D19*(1+'Net Yield Build'!P18) -> 140.01145 | I19: =E19*(1+'Net Yield Build'!Q18) -> 122.81978
B20: Adjusted gross margin ($mm) | D20: ='Net Yield Build'!L19*D16*(D18*(1-'Net Yield Build'!L54)+D19*(1-'Net Yield Build'!L55)) -> 2138.9429 | E20: ='Net Yield Build'!M19*E16*(E18*(1-'Net Yield Build'!M54)+E19*(1-'Net Yield Build'!M55)) -> 1676.6932 | F20: ='Net Yield Build'!N19*F16*(F18*(1-'Net Yield Build'!N54)+F19*(1-'Net Yield Build'!N55)) -> 1821.7515 | G20: ='Net Yield Build'!O19*G16*(G18*(1-'Net Yield Build'!O54)+G19*(1-'Net Yield Build'!O55)) -> 1980.551 | H20: ='Net Yield Build'!P19*H16*(H18*(1-'Net Yield Build'!P54)+H19*(1-'Net Yield Build'!P55)) -> 2307.5726 | I20: ='Net Yield Build'!Q19*I16*(I18*(1-'Net Yield Build'!Q54)+I19*(1-'Net Yield Build'!Q55)) -> 1825.8382 | J20: =SUM(F20:I20) -> 7935.7132
B21: Adjusted EBITDA ($mm) | J21: =J20-'Operating Model'!$G$45*(1+'Operating Model'!$H$11)*(1+'Operating Model'!$I$11)*'Net Yield Build'!$U$19-'Operating Model'!$H$47*('Net Yield Build'!$U$19/'Net Yield Build'!$T$19)*0.99*'Operating Model'!$I$16/1000 -> 2787.034
B23: Block 1: 2H26 exit (3Q-4Q26 inputs) | D23: 3Q26E | E23: 4Q26E | F23: 1Q27E | G23: 2Q27E | H23: 3Q27E | I23: 4Q27E | J23: FY2027E
B24: Occupancy change y/y (pts) | D24: ='Net Yield Build'!L40 -> -2.4 | E24: ='Net Yield Build'!M40 -> -2.8 | F24: ='Net Yield Build'!N13 -> -1 | G24: ='Net Yield Build'!O13 -> 0.5 | H24: ='Net Yield Build'!P13 -> 1.5 | I24: ='Net Yield Build'!Q13 -> 2
B25: Occupancy | D25: ='Net Yield Build'!H20+D24/100 -> 1.0399959 | E25: ='Net Yield Build'!I20+E24/100 -> 0.98972285 | F25: ='Net Yield Build'!J20+F24/100 -> 1.0277757 | G25: ='Net Yield Build'!K20+G24/100 -> 1.0287188 | H25: =D25+H24/100 -> 1.0549959 | I25: =E25+I24/100 -> 1.0097229
B26: Like-for-like ticket price change + mix | D26: ='Net Yield Build'!L41+'Net Yield Build'!L42+('Net Yield Build'!L44+'KPI 2 Booking Build'!D52)+'Net Yield Build'!L16 -> -0.1005 | E26: ='Net Yield Build'!M41+'Net Yield Build'!M42+('Net Yield Build'!M44+'KPI 2 Booking Build'!E52)+'Net Yield Build'!M16 -> -0.0712 | F26: ='Net Yield Build'!N41+'Net Yield Build'!N15+'Net Yield Build'!N17+'Net Yield Build'!N16 -> -0.0035598342 | G26: ='Net Yield Build'!O41+'Net Yield Build'!O15+'Net Yield Build'!O17+'Net Yield Build'!O16 -> 0.0019382335 | H26: ='Net Yield Build'!P41+'Net Yield Build'!P15+'Net Yield Build'!P17+'Net Yield Build'!P16 -> 0.01390929 | I26: ='Net Yield Build'!Q41+'Net Yield Build'!Q15+'Net Yield Build'!Q17+'Net Yield Build'!Q16 -> 0.012969926
B27: Ticket revenue per passenger day ($) | D27: ='Net Yield Build'!H25*(1+D26) -> 270.04351 | E27: ='Net Yield Build'!I25*(1+E26) -> 220.03486 | F27: ='Net Yield Build'!J25*(1+F26) -> 231.64226 | G27: ='Net Yield Build'!K25*(1+G26) -> 256.92126 | H27: =D27*(1+H26) -> 273.79963 | I27: =E27*(1+I26) -> 222.8887
B28: Onboard revenue per passenger day ($) | D28: ='Net Yield Build'!H26*(1+'Net Yield Build'!L45) -> 135.27676 | E28: ='Net Yield Build'!I26*(1+'Net Yield Build'!M45) -> 118.66645 | F28: ='Net Yield Build'!J26*(1+'Net Yield Build'!N18) -> 123.07054 | G28: ='Net Yield Build'!K26*(1+'Net Yield Build'!O18) -> 139.04939 | H28: =D28*(1+'Net Yield Build'!P18) -> 140.01145 | I28: =E28*(1+'Net Yield Build'!Q18) -> 122.81978
B29: Adjusted gross margin ($mm) | D29: ='Net Yield Build'!L19*D25*(D27*(1-'Net Yield Build'!L54)+D28*(1-'Net Yield Build'!L55)) -> 2129.5244 | E29: ='Net Yield Build'!M19*E25*(E27*(1-'Net Yield Build'!M54)+E28*(1-'Net Yield Build'!M55)) -> 1658.8169 | F29: ='Net Yield Build'!N19*F25*(F27*(1-'Net Yield Build'!N54)+F28*(1-'Net Yield Build'!N55)) -> 1821.7515 | G29: ='Net Yield Build'!O19*G25*(G27*(1-'Net Yield Build'!O54)+G28*(1-'Net Yield Build'!O55)) -> 1980.551 | H29: ='Net Yield Build'!P19*H25*(H27*(1-'Net Yield Build'!P54)+H28*(1-'Net Yield Build'!P55)) -> 2297.5171 | I29: ='Net Yield Build'!Q19*I25*(I27*(1-'Net Yield Build'!Q54)+I28*(1-'Net Yield Build'!Q55)) -> 1806.5743 | J29: =SUM(F29:I29) -> 7906.3938
B30: Adjusted EBITDA ($mm) | J30: =J29-'Operating Model'!$G$45*(1+'Operating Model'!$H$11)*(1+'Operating Model'!$I$11)*'Net Yield Build'!$U$19-'Operating Model'!$H$47*('Net Yield Build'!$U$19/'Net Yield Build'!$T$19)*0.99*'Operating Model'!$I$16/1000 -> 2757.7146
B32: Block 2: Thesis 1 -> KPI 1: fare cuts on unsold cabins | D32: 3Q26E | E32: 4Q26E | F32: 1Q27E | G32: 2Q27E | H32: 3Q27E | I32: 4Q27E | J32: FY2027E
B33: Occupancy change y/y (pts) | D33: ='Net Yield Build'!L40 -> -2.4 | E33: ='Net Yield Build'!M40 -> -2.8 | F33: ='Net Yield Build'!N13 -> -1 | G33: ='Net Yield Build'!O13 -> 0.5 | H33: ='Net Yield Build'!P13 -> 1.5 | I33: ='Net Yield Build'!Q13 -> 2
B34: Occupancy | D34: ='Net Yield Build'!H20+D33/100 -> 1.0399959 | E34: ='Net Yield Build'!I20+E33/100 -> 0.98972285 | F34: ='Net Yield Build'!J20+F33/100 -> 1.0277757 | G34: ='Net Yield Build'!K20+G33/100 -> 1.0287188 | H34: =D34+H33/100 -> 1.0549959 | I34: =E34+I33/100 -> 1.0097229
B35: Like-for-like ticket price change + mix | D35: ='Net Yield Build'!L41+'Net Yield Build'!L42+('Net Yield Build'!L44+'KPI 2 Booking Build'!D52)+'Net Yield Build'!L16 -> -0.1005 | E35: ='Net Yield Build'!M41+'Net Yield Build'!M42+('Net Yield Build'!M44+'KPI 2 Booking Build'!E52)+'Net Yield Build'!M16 -> -0.0712 | F35: ='Net Yield Build'!N41+'Net Yield Build'!N42+'Net Yield Build'!N17+'Net Yield Build'!N16 -> -0.018407702 | G35: ='Net Yield Build'!O41+'Net Yield Build'!O42+'Net Yield Build'!O17+'Net Yield Build'!O16 -> -0.013735886 | H35: ='Net Yield Build'!P41+'Net Yield Build'!P42+'Net Yield Build'!P17+'Net Yield Build'!P16 -> 0.012164155 | I35: ='Net Yield Build'!Q41+'Net Yield Build'!Q42+'Net Yield Build'!Q17+'Net Yield Build'!Q16 -> 0.0089097768
B36: Ticket revenue per passenger day ($) | D36: ='Net Yield Build'!H25*(1+D35) -> 270.04351 | E36: ='Net Yield Build'!I25*(1+E35) -> 220.03486 | F36: ='Net Yield Build'!J25*(1+F35) -> 228.19058 | G36: ='Net Yield Build'!K25*(1+G35) -> 252.90204 | H36: =D36*(1+H35) -> 273.32836 | I36: =E36*(1+I35) -> 221.99532
B37: Onboard revenue per passenger day ($) | D37: ='Net Yield Build'!H26*(1+'Net Yield Build'!L45) -> 135.27676 | E37: ='Net Yield Build'!I26*(1+'Net Yield Build'!M45) -> 118.66645 | F37: ='Net Yield Build'!J26*(1+'Net Yield Build'!N18) -> 123.07054 | G37: ='Net Yield Build'!K26*(1+'Net Yield Build'!O18) -> 139.04939 | H37: =D37*(1+'Net Yield Build'!P18) -> 140.01145 | I37: =E37*(1+'Net Yield Build'!Q18) -> 122.81978
B38: Adjusted gross margin ($mm) | D38: ='Net Yield Build'!L19*D34*(D36*(1-'Net Yield Build'!L54)+D37*(1-'Net Yield Build'!L55)) -> 2129.5244 | E38: ='Net Yield Build'!M19*E34*(E36*(1-'Net Yield Build'!M54)+E37*(1-'Net Yield Build'!M55)) -> 1658.8169 | F38: ='Net Yield Build'!N19*F34*(F36*(1-'Net Yield Build'!N54)+F37*(1-'Net Yield Build'!N55)) -> 1804.6608 | G38: ='Net Yield Build'!O19*G34*(G36*(1-'Net Yield Build'!O54)+G37*(1-'Net Yield Build'!O55)) -> 1961.2231 | H38: ='Net Yield Build'!P19*H34*(H36*(1-'Net Yield Build'!P54)+H37*(1-'Net Yield Build'!P55)) -> 2294.9224 | I38: ='Net Yield Build'!Q19*I34*(I36*(1-'Net Yield Build'!Q54)+I37*(1-'Net Yield Build'!Q55)) -> 1802.0639 | J38: =SUM(F38:I38) -> 7862.8701
B39: Adjusted EBITDA ($mm) | J39: =J38-'Operating Model'!$G$45*(1+'Operating Model'!$H$11)*(1+'Operating Model'!$I$11)*'Net Yield Build'!$U$19-'Operating Model'!$H$47*('Net Yield Build'!$U$19/'Net Yield Build'!$T$19)*0.99*'Operating Model'!$I$16/1000 -> 2714.1909
B41: Block 3: Thesis 2 -> KPI 1: late discounts on the shortfall | D41: 3Q26E | E41: 4Q26E | F41: 1Q27E | G41: 2Q27E | H41: 3Q27E | I41: 4Q27E | J41: FY2027E
B42: Occupancy change y/y (pts) | D42: ='Net Yield Build'!L40 -> -2.4 | E42: ='Net Yield Build'!M40 -> -2.8 | F42: ='Net Yield Build'!N13 -> -1 | G42: ='Net Yield Build'!O13 -> 0.5 | H42: ='Net Yield Build'!P13 -> 1.5 | I42: ='Net Yield Build'!Q13 -> 2
B43: Occupancy | D43: ='Net Yield Build'!H20+D42/100 -> 1.0399959 | E43: ='Net Yield Build'!I20+E42/100 -> 0.98972285 | F43: ='Net Yield Build'!J20+F42/100 -> 1.0277757 | G43: ='Net Yield Build'!K20+G42/100 -> 1.0287188 | H43: =D43+H42/100 -> 1.0549959 | I43: =E43+I42/100 -> 1.0097229
B44: Like-for-like ticket price change + mix | D44: ='Net Yield Build'!L41+'Net Yield Build'!L42+('Net Yield Build'!L44+'KPI 2 Booking Build'!D52)+'Net Yield Build'!L16 -> -0.1005 | E44: ='Net Yield Build'!M41+'Net Yield Build'!M42+('Net Yield Build'!M44+'KPI 2 Booking Build'!E52)+'Net Yield Build'!M16 -> -0.0712 | F44: ='Net Yield Build'!N41+'Net Yield Build'!N42+('Net Yield Build'!N44+'KPI 2 Booking Build'!F52)+'Net Yield Build'!N16 -> -0.018407702 | G44: ='Net Yield Build'!O41+'Net Yield Build'!O42+('Net Yield Build'!O44+'KPI 2 Booking Build'!G52)+'Net Yield Build'!O16 -> -0.013735886 | H44: ='Net Yield Build'!P41+'Net Yield Build'!P42+('Net Yield Build'!P44+'KPI 2 Booking Build'!H52)+'Net Yield Build'!P16 -> 0.0055849259 | I44: ='Net Yield Build'!Q41+'Net Yield Build'!Q42+('Net Yield Build'!Q44+'KPI 2 Booking Build'!I52)+'Net Yield Build'!Q16 -> 0.0023305479
B45: Ticket revenue per passenger day ($) | D45: ='Net Yield Build'!H25*(1+D44) -> 270.04351 | E45: ='Net Yield Build'!I25*(1+E44) -> 220.03486 | F45: ='Net Yield Build'!J25*(1+F44) -> 228.19058 | G45: ='Net Yield Build'!K25*(1+G44) -> 252.90204 | H45: =D45*(1+H44) -> 271.55169 | I45: =E45*(1+I44) -> 220.54767
B46: Onboard revenue per passenger day ($) | D46: ='Net Yield Build'!H26*(1+'Net Yield Build'!L45) -> 135.27676 | E46: ='Net Yield Build'!I26*(1+'Net Yield Build'!M45) -> 118.66645 | F46: ='Net Yield Build'!J26*(1+'Net Yield Build'!N18) -> 123.07054 | G46: ='Net Yield Build'!K26*(1+'Net Yield Build'!O18) -> 139.04939 | H46: =D46*(1+'Net Yield Build'!P18) -> 140.01145 | I46: =E46*(1+'Net Yield Build'!Q18) -> 122.81978
B47: Adjusted gross margin ($mm) | D47: ='Net Yield Build'!L19*D43*(D45*(1-'Net Yield Build'!L54)+D46*(1-'Net Yield Build'!L55)) -> 2129.5244 | E47: ='Net Yield Build'!M19*E43*(E45*(1-'Net Yield Build'!M54)+E46*(1-'Net Yield Build'!M55)) -> 1658.8169 | F47: ='Net Yield Build'!N19*F43*(F45*(1-'Net Yield Build'!N54)+F46*(1-'Net Yield Build'!N55)) -> 1804.6608 | G47: ='Net Yield Build'!O19*G43*(G45*(1-'Net Yield Build'!O54)+G46*(1-'Net Yield Build'!O55)) -> 1961.2231 | H47: ='Net Yield Build'!P19*H43*(H45*(1-'Net Yield Build'!P54)+H46*(1-'Net Yield Build'!P55)) -> 2285.1403 | I47: ='Net Yield Build'!Q19*I43*(I45*(1-'Net Yield Build'!Q54)+I46*(1-'Net Yield Build'!Q55)) -> 1794.7551 | J47: =SUM(F47:I47) -> 7845.7792
B48: Adjusted EBITDA ($mm) | J48: =J47-'Operating Model'!$G$45*(1+'Operating Model'!$H$11)*(1+'Operating Model'!$I$11)*'Net Yield Build'!$U$19-'Operating Model'!$H$47*('Net Yield Build'!$U$19/'Net Yield Build'!$T$19)*0.99*'Operating Model'!$I$16/1000 -> 2697.1
B50: Block 4: Thesis 2 -> KPI 2: occupancy | D50: 3Q26E | E50: 4Q26E | F50: 1Q27E | G50: 2Q27E | H50: 3Q27E | I50: 4Q27E | J50: FY2027E
B51: Occupancy change y/y (pts) | D51: ='Net Yield Build'!L40 -> -2.4 | E51: ='Net Yield Build'!M40 -> -2.8 | F51: ='Net Yield Build'!N40 -> -2 | G51: ='Net Yield Build'!O40 -> -0.5 | H51: ='Net Yield Build'!P40 -> 0.5 | I51: ='Net Yield Build'!Q40 -> 1
B52: Occupancy | D52: ='Net Yield Build'!H20+D51/100 -> 1.0399959 | E52: ='Net Yield Build'!I20+E51/100 -> 0.98972285 | F52: ='Net Yield Build'!J20+F51/100 -> 1.0177757 | G52: ='Net Yield Build'!K20+G51/100 -> 1.0187188 | H52: =D52+H51/100 -> 1.0449959 | I52: =E52+I51/100 -> 0.99972285
B53: Like-for-like ticket price change + mix | D53: ='Net Yield Build'!L41+'Net Yield Build'!L42+('Net Yield Build'!L44+'KPI 2 Booking Build'!D52)+'Net Yield Build'!L16 -> -0.1005 | E53: ='Net Yield Build'!M41+'Net Yield Build'!M42+('Net Yield Build'!M44+'KPI 2 Booking Build'!E52)+'Net Yield Build'!M16 -> -0.0712 | F53: ='Net Yield Build'!N41+'Net Yield Build'!N42+('Net Yield Build'!N44+'KPI 2 Booking Build'!F52)+'Net Yield Build'!N16 -> -0.018407702 | G53: ='Net Yield Build'!O41+'Net Yield Build'!O42+('Net Yield Build'!O44+'KPI 2 Booking Build'!G52)+'Net Yield Build'!O16 -> -0.013735886 | H53: ='Net Yield Build'!P41+'Net Yield Build'!P42+('Net Yield Build'!P44+'KPI 2 Booking Build'!H52)+'Net Yield Build'!P16 -> 0.0055849259 | I53: ='Net Yield Build'!Q41+'Net Yield Build'!Q42+('Net Yield Build'!Q44+'KPI 2 Booking Build'!I52)+'Net Yield Build'!Q16 -> 0.0023305479
B54: Ticket revenue per passenger day ($) | D54: ='Net Yield Build'!H25*(1+D53) -> 270.04351 | E54: ='Net Yield Build'!I25*(1+E53) -> 220.03486 | F54: ='Net Yield Build'!J25*(1+F53) -> 228.19058 | G54: ='Net Yield Build'!K25*(1+G53) -> 252.90204 | H54: =D54*(1+H53) -> 271.55169 | I54: =E54*(1+I53) -> 220.54767
B55: Onboard revenue per passenger day ($) | D55: ='Net Yield Build'!H26*(1+'Net Yield Build'!L45) -> 135.27676 | E55: ='Net Yield Build'!I26*(1+'Net Yield Build'!M45) -> 118.66645 | F55: ='Net Yield Build'!J26*(1+'Net Yield Build'!N18) -> 123.07054 | G55: ='Net Yield Build'!K26*(1+'Net Yield Build'!O18) -> 139.04939 | H55: =D55*(1+'Net Yield Build'!P18) -> 140.01145 | I55: =E55*(1+'Net Yield Build'!Q18) -> 122.81978
B56: Adjusted gross margin ($mm) | D56: ='Net Yield Build'!L19*D52*(D54*(1-'Net Yield Build'!L54)+D55*(1-'Net Yield Build'!L55)) -> 2129.5244 | E56: ='Net Yield Build'!M19*E52*(E54*(1-'Net Yield Build'!M54)+E55*(1-'Net Yield Build'!M55)) -> 1658.8169 | F56: ='Net Yield Build'!N19*F52*(F54*(1-'Net Yield Build'!N54)+F55*(1-'Net Yield Build'!N55)) -> 1787.1019 | G56: ='Net Yield Build'!O19*G52*(G54*(1-'Net Yield Build'!O54)+G55*(1-'Net Yield Build'!O55)) -> 1942.1583 | H56: ='Net Yield Build'!P19*H52*(H54*(1-'Net Yield Build'!P54)+H55*(1-'Net Yield Build'!P55)) -> 2263.4801 | I56: ='Net Yield Build'!Q19*I52*(I54*(1-'Net Yield Build'!Q54)+I55*(1-'Net Yield Build'!Q55)) -> 1776.9803 | J56: =SUM(F56:I56) -> 7769.7207
B57: Adjusted EBITDA ($mm) | J57: =J56-'Operating Model'!$G$45*(1+'Operating Model'!$H$11)*(1+'Operating Model'!$I$11)*'Net Yield Build'!$U$19-'Operating Model'!$H$47*('Net Yield Build'!$U$19/'Net Yield Build'!$T$19)*0.99*'Operating Model'!$I$16/1000 -> 2621.0415
B59: Block 5: Other: onboard spend growth | D59: 3Q26E | E59: 4Q26E | F59: 1Q27E | G59: 2Q27E | H59: 3Q27E | I59: 4Q27E | J59: FY2027E
B60: Occupancy change y/y (pts) | D60: ='Net Yield Build'!L40 -> -2.4 | E60: ='Net Yield Build'!M40 -> -2.8 | F60: ='Net Yield Build'!N40 -> -2 | G60: ='Net Yield Build'!O40 -> -0.5 | H60: ='Net Yield Build'!P40 -> 0.5 | I60: ='Net Yield Build'!Q40 -> 1
B61: Occupancy | D61: ='Net Yield Build'!H20+D60/100 -> 1.0399959 | E61: ='Net Yield Build'!I20+E60/100 -> 0.98972285 | F61: ='Net Yield Build'!J20+F60/100 -> 1.0177757 | G61: ='Net Yield Build'!K20+G60/100 -> 1.0187188 | H61: =D61+H60/100 -> 1.0449959 | I61: =E61+I60/100 -> 0.99972285
B62: Like-for-like ticket price change + mix | D62: ='Net Yield Build'!L41+'Net Yield Build'!L42+('Net Yield Build'!L44+'KPI 2 Booking Build'!D52)+'Net Yield Build'!L16 -> -0.1005 | E62: ='Net Yield Build'!M41+'Net Yield Build'!M42+('Net Yield Build'!M44+'KPI 2 Booking Build'!E52)+'Net Yield Build'!M16 -> -0.0712 | F62: ='Net Yield Build'!N41+'Net Yield Build'!N42+('Net Yield Build'!N44+'KPI 2 Booking Build'!F52)+'Net Yield Build'!N16 -> -0.018407702 | G62: ='Net Yield Build'!O41+'Net Yield Build'!O42+('Net Yield Build'!O44+'KPI 2 Booking Build'!G52)+'Net Yield Build'!O16 -> -0.013735886 | H62: ='Net Yield Build'!P41+'Net Yield Build'!P42+('Net Yield Build'!P44+'KPI 2 Booking Build'!H52)+'Net Yield Build'!P16 -> 0.0055849259 | I62: ='Net Yield Build'!Q41+'Net Yield Build'!Q42+('Net Yield Build'!Q44+'KPI 2 Booking Build'!I52)+'Net Yield Build'!Q16 -> 0.0023305479
B63: Ticket revenue per passenger day ($) | D63: ='Net Yield Build'!H25*(1+D62) -> 270.04351 | E63: ='Net Yield Build'!I25*(1+E62) -> 220.03486 | F63: ='Net Yield Build'!J25*(1+F62) -> 228.19058 | G63: ='Net Yield Build'!K25*(1+G62) -> 252.90204 | H63: =D63*(1+H62) -> 271.55169 | I63: =E63*(1+I62) -> 220.54767
B64: Onboard revenue per passenger day ($) | D64: ='Net Yield Build'!H26*(1+'Net Yield Build'!L45) -> 135.27676 | E64: ='Net Yield Build'!I26*(1+'Net Yield Build'!M45) -> 118.66645 | F64: ='Net Yield Build'!J26*(1+'Net Yield Build'!N45) -> 121.28691 | G64: ='Net Yield Build'!K26*(1+'Net Yield Build'!O45) -> 137.0244 | H64: =D64*(1+'Net Yield Build'!P45) -> 137.9823 | I64: =E64*(1+'Net Yield Build'!Q45) -> 121.03978
B65: Adjusted gross margin ($mm) | D65: ='Net Yield Build'!L19*D61*(D63*(1-'Net Yield Build'!L54)+D64*(1-'Net Yield Build'!L55)) -> 2129.5244 | E65: ='Net Yield Build'!M19*E61*(E63*(1-'Net Yield Build'!M54)+E64*(1-'Net Yield Build'!M55)) -> 1658.8169 | F65: ='Net Yield Build'!N19*F61*(F63*(1-'Net Yield Build'!N54)+F64*(1-'Net Yield Build'!N55)) -> 1777.4174 | G65: ='Net Yield Build'!O19*G61*(G63*(1-'Net Yield Build'!O54)+G64*(1-'Net Yield Build'!O55)) -> 1931.4136 | H65: ='Net Yield Build'!P19*H61*(H63*(1-'Net Yield Build'!P54)+H64*(1-'Net Yield Build'!P55)) -> 2252.139 | I65: ='Net Yield Build'!Q19*I61*(I63*(1-'Net Yield Build'!Q54)+I64*(1-'Net Yield Build'!Q55)) -> 1767.2046 | J65: =SUM(F65:I65) -> 7728.1746
B66: Adjusted EBITDA ($mm) | J66: =J65-'Operating Model'!$G$45*(1+'Operating Model'!$H$11)*(1+'Operating Model'!$I$11)*'Net Yield Build'!$U$19-'Operating Model'!$H$47*('Net Yield Build'!$U$19/'Net Yield Build'!$T$19)*0.99*'Operating Model'!$I$16/1000 -> 2579.4953

Sheet Operating Model
B2: NCLH Operating Model | F2: FY2024A | G2: FY2025A | H2: FY2026E | I2: FY2027E | J2: FY2028E | K2: FY2029E | L2: FY2030E
B3: $mm except per-share and per-day data | F3: 2024-12-31 | G3: 2025-12-31 | H3: 2026-12-31 | I3: 2027-12-31 | J3: 2028-12-31 | K3: 2029-12-31 | L3: 2030-12-31
B5: Case inputs (selected by DCF!C9)
B6: Net yield growth 2028E-30E: Bull | J6: 0.035 | K6: 0.03 | L6: 0.03
B7: Net yield growth 2028E-30E: Base | J7: 0.025 | K7: 0.025 | L7: 0.025
B8: Net yield growth 2028E-30E: Bear | J8: 0.01 | K8: 0.015 | L8: 0.015
B9: Net yield growth 2028E-30E: selected | J9: =CHOOSE(DCF!$C$9,J6,J7,J8) -> 0.025 | K9: =CHOOSE(DCF!$C$9,K6,K7,K8) -> 0.025 | L9: =CHOOSE(DCF!$C$9,L6,L7,L8) -> 0.025
B11: NCC ex fuel per capacity day growth: Bull | H11: 0 | I11: -0.005 | J11: 0.015 | K11: 0.015 | L11: 0.015
B12: NCC ex fuel per capacity day growth: Base | H12: 0 | I12: 0.01 | J12: 0.02 | K12: 0.02 | L12: 0.02
B13: NCC ex fuel per capacity day growth: Bear | H13: 0 | I13: 0.015 | J13: 0.025 | K13: 0.025 | L13: 0.025
B14: NCC ex fuel per capacity day growth: selected | H14: =CHOOSE(DCF!$C$9,H11,H12,H13) -> 0 | I14: =CHOOSE(DCF!$C$9,I11,I12,I13) -> 0.01 | J14: =CHOOSE(DCF!$C$9,J11,J12,J13) -> 0.02 | K14: =CHOOSE(DCF!$C$9,K11,K12,K13) -> 0.02 | L14: =CHOOSE(DCF!$C$9,L11,L12,L13) -> 0.02
B16: Fuel price per metric ton, net of hedges ($): Bull | H16: 790 | I16: 760 | J16: 760 | K16: 760 | L16: 760
B17: Fuel price per metric ton, net of hedges ($): Base | H17: 810 | I17: 800 | J17: 800 | K17: 800 | L17: 800
B18: Fuel price per metric ton, net of hedges ($): Bear | H18: 830 | I18: 850 | J18: 850 | K18: 850 | L18: 850
B19: Fuel price per metric ton, net of hedges ($): selected | H19: =CHOOSE(DCF!$C$9,H16,H17,H18) -> 810 | I19: =CHOOSE(DCF!$C$9,I16,I17,I18) -> 800 | J19: =CHOOSE(DCF!$C$9,J16,J17,J18) -> 800 | K19: =CHOOSE(DCF!$C$9,K16,K17,K18) -> 800 | L19: =CHOOSE(DCF!$C$9,L16,L17,L18) -> 800
B21: Advance ticket sales at YE2026 ($mm): Bull | H21: 3200
B22: Advance ticket sales at YE2026 ($mm): Base | H22: 3000
B23: Advance ticket sales at YE2026 ($mm): Bear | H23: 2900
B24: Advance ticket sales at YE2026 ($mm): selected | H24: =CHOOSE(DCF!$C$9,H21,H22,H23) -> 3000
B26: Capacity, occupancy and net yield
B27: Capacity days (M) | F27: ='Quarterly (A)'!L29 -> 23.4454 | G27: ='Quarterly (A)'!M29 -> 24.4336 | H27: ='Net Yield Build'!T94 -> 26.249873 | I27: ='Net Yield Build'!U94 -> 27.121933 | J27: =I27*(1+J28) -> 27.963719 | K27: =J27*(1+K28) -> 29.049173 | L27: =K27*(1+L28) -> 30.334185
B28: Capacity growth | G28: =G27/F27-1 -> 0.042148993 | H28: =H27/G27-1 -> 0.074335075 | I28: =I27/H27-1 -> 0.033221479 | J28: ='Fleet Build'!L60 -> 0.031037101 | K28: ='Fleet Build'!M60 -> 0.038816504 | L28: ='Fleet Build'!N60 -> 0.04423575
B29: Occupancy | F29: ='Quarterly (A)'!L31 -> 1.0489606 | G29: ='Quarterly (A)'!M31 -> 1.0345753 | H29: ='Net Yield Build'!T95 -> 1.0229831 | I29: ='Net Yield Build'!U95 -> 1.0206424 | J29: =I29 -> 1.0206424 | K29: =J29 -> 1.0206424 | L29: =K29 -> 1.0206424
B30: Passenger cruise days (M) | F30: =F27*F29 -> 24.5933 | G30: =G27*G29 -> 25.2784 | H30: =H27*H29 -> 26.853176 | I30: =I27*I29 -> 27.681795 | J30: =J27*J29 -> 28.540957 | K30: =K27*K29 -> 29.648818 | L30: =L27*L29 -> 30.960355
B31: Net yield ($ per capacity day) | F31: ='Quarterly (A)'!L32 -> 294.32874 | G31: ='Quarterly (A)'!M32 -> 301.0962 | H31: ='Net Yield Build'!T102 -> 287.03069 | I31: ='Net Yield Build'!U102 -> 284.94188 | J31: =I31*(1+J9) -> 292.06543 | K31: =J31*(1+K9) -> 299.36706 | L31: =K31*(1+L9) -> 306.85124
B32: Net yield growth | G32: =G31/F31-1 -> 0.022992852 | H32: =H31/G31-1 -> -0.046714321 | I32: =I31/H31-1 -> -0.0072773132 | J32: =J31/I31-1 -> 0.025 | K32: =K31/J31-1 -> 0.025 | L32: =L31/K31-1 -> 0.025
B33: Adjusted gross margin ($mm) | F33: =F31*F27 -> 6900.655 | G33: =G31*G27 -> 7356.864 | H33: =H31*H27 -> 7534.5193 | I33: =I31*I27 -> 7728.1746 | J33: =J31*J27 -> 8167.2356 | K33: =K31*K27 -> 8696.3656 | L33: =L31*L27 -> 9308.0822
B35: Revenue
B36: Passenger ticket revenue | F36: ='Quarterly (A)'!L5 -> 6415.545 | G36: ='Quarterly (A)'!M5 -> 6687.667 | H36: ='Net Yield Build'!T104 -> 6590.2719 | I36: ='Net Yield Build'!U104 -> 6753.9799 | J36: =I36*J33/I33 -> 7137.6939 | K36: =J36*K33/J33 -> 7600.1231 | L36: =K36*L33/K33 -> 8134.7283
B37: Onboard and other revenue | F37: ='Quarterly (A)'!L6 -> 3064.106 | G37: ='Quarterly (A)'!M6 -> 3139.925 | H37: ='Net Yield Build'!T105 -> 3415.8265 | I37: ='Net Yield Build'!U105 -> 3585.9006 | J37: =I37*J33/I33 -> 3789.6265 | K37: =J37*K33/J33 -> 4035.1447 | L37: =K37*L33/K33 -> 4318.9834
B38: Total revenue | F38: =F36+F37 -> 9479.651 | G38: =G36+G37 -> 9827.592 | H38: =H36+H37 -> 10006.098 | I38: =I36+I37 -> 10339.88 | J38: =J36+J37 -> 10927.32 | K38: =K36+K37 -> 11635.268 | L38: =L36+L37 -> 12453.712
B39: Revenue growth | G39: =G38/F38-1 -> 0.036703988 | H39: =H38/G38-1 -> 0.018163799 | I39: =I38/H38-1 -> 0.033357864 | J39: =J38/I38-1 -> 0.056813029 | K39: =K38/J38-1 -> 0.064786916 | L39: =L38/K38-1 -> 0.070341644
B40: Commissions, transportation and other | F40: ='Quarterly (A)'!L8 -> 1917.443 | G40: ='Quarterly (A)'!M8 -> 1782.004 | H40: ='Net Yield Build'!T107 -> 1744.157 | I40: ='Net Yield Build'!U107 -> 1847.3597 | J40: =I40*J33/I33 -> 1952.3138 | K40: =J40*K33/J33 -> 2078.7981 | L40: =K40*L33/K33 -> 2225.0242
B41: Onboard and other expense | F41: ='Quarterly (A)'!L9 -> 661.553 | G41: ='Quarterly (A)'!M9 -> 688.724 | H41: ='Net Yield Build'!T108 -> 727.42208 | I41: ='Net Yield Build'!U108 -> 764.34623 | J41: =I41*J33/I33 -> 807.77106 | K41: =J41*K33/J33 -> 860.10405 | L41: =K41*L33/K33 -> 920.60518
B42: Gross margin check (revenue - commissions - onboard costs) | F42: =F38-F40-F41-F33 -> 0 | G42: =G38-G40-G41-G33 -> 0 | H42: =H38-H40-H41-H33 -> 0 | I42: =I38-I40-I41-I33 -> 0 | J42: =J38-J40-J41-J33 -> 0 | K42: =K38-K40-K41-K33 -> 0 | L42: =L38-L40-L41-L33 -> 0
B44: Costs
B45: Adjusted NCC ex fuel per capacity day ($) | F45: ='Quarterly (A)'!L21/'Quarterly (A)'!L29 -> 160.0229 | G45: ='Quarterly (A)'!M21/'Quarterly (A)'!M29 -> 161.69336 | H45: =G45*(1+H14) -> 161.69336 | I45: =H45*(1+I14) -> 163.3103 | J45: =I45*(1+J14) -> 166.5765 | K45: =J45*(1+K14) -> 169.90803 | L45: =K45*(1+L14) -> 173.3062
B46: Adjusted NCC ex fuel ($mm) | F46: =F45*F27 -> 3751.801 | G46: =G45*G27 -> 3950.751 | H46: =H45*H27 -> 4244.4304 | I46: =I45*I27 -> 4429.291 | J46: =J45*J27 -> 4658.0986 | K46: =K45*K27 -> 4935.6879 | L46: =L45*L27 -> 5257.1022
B47: Fuel consumption (k metric tons) | H47: =Consensus!C39 -> 1010 | I47: =H47*(1+I28)*(1-0.01) -> 1033.1182 | J47: =I47*(1+J28)*(1-0.01) -> 1054.5313 | K47: =J47*(1+K28)*(1-0.01) -> 1084.5099 | L47: =K47*(1+L28)*(1-0.01) -> 1121.1592
B48: Fuel price per ton, net of hedges ($) | H48: =H19 -> 810 | I48: =I19 -> 800 | J48: =J19 -> 800 | K48: =K19 -> 800 | L48: =L19 -> 800
B49: Fuel expense ($mm) | F49: ='Quarterly (A)'!L11 -> 698.05 | G49: ='Quarterly (A)'!M11 -> 675.887 | H49: =H47*H48/1000 -> 818.1 | I49: =I47*I48/1000 -> 826.49453 | J49: =J47*J48/1000 -> 843.62505 | K49: =K47*K48/1000 -> 867.60791 | L49: =L47*L48/1000 -> 896.92733
B51: Income statement (adjusted)
B52: Adjusted EBITDA | F52: =F33-F46-F49 -> 2450.804 | G52: =G33-G46-G49 -> 2730.226 | H52: =H33-H46-H49 -> 2471.989 | I52: =I33-I46-I49 -> 2472.3891 | J52: =J33-J46-J49 -> 2665.5119 | K52: =K33-K46-K49 -> 2893.0698 | L52: =L33-L46-L49 -> 3154.0527
B53: EBITDA margin (% of revenue) | F53: =F52/F38 -> 0.25853315 | G53: =G52/G38 -> 0.27781231 | H53: =H52/H38 -> 0.24704824 | I53: =I52/I38 -> 0.23911196 | J53: =J52/J38 -> 0.24393097 | K53: =K52/K38 -> 0.2486466 | L53: =L52/L38 -> 0.25326206
B54: Depreciation and amortization | F54: ='Quarterly (A)'!L16 -> 890.242 | G54: ='Quarterly (A)'!M16 -> 1078.755 | H54: 1085 | I54: 1150 | J54: 1230 | K54: 1300 | L54: 1370
B55: Adjusted EBIT | F55: =F52-F54 -> 1560.562 | G55: =G52-G54 -> 1651.471 | H55: =H52-H54 -> 1386.989 | I55: =I52-I54 -> 1322.3891 | J55: =J52-J54 -> 1435.5119 | K55: =K52-K54 -> 1593.0698 | L55: =L52-L54 -> 1784.0527
B56: Net interest expense (ex. debt extinguishment) | F56: =F55-F61 -> 648.874 | G56: =G55-G61 -> 606.719 | H56: =Consensus!C37 -> 705 | I56: =Consensus!C43 -> 870 | J56: =I88*J57 -> 968.95517 | K56: =J88*K57 -> 999.4455 | L56: =K88*L57 -> 1001.9648
B57: Interest rate on opening net debt | I57: =I56/H88 -> 0.054774705 | J57: =I57 -> 0.054774705 | K57: =J57 -> 0.054774705 | L57: =K57 -> 0.054774705
B58: Pre-tax income | H58: =H55-H56 -> 681.98896 | I58: =I55-I56 -> 452.38906 | J58: =J55-J56 -> 466.55675 | K58: =K55-K56 -> 593.62427 | L58: =L55-L56 -> 782.08794
B59: Income tax | H59: =MAX(0,H58*H60) -> 13.639779 | I59: =MAX(0,I58*I60) -> 9.0477812 | J59: =MAX(0,J58*J60) -> 9.331135 | K59: =MAX(0,K58*K60) -> 11.872485 | L59: =MAX(0,L58*L60) -> 15.641759
B60: Tax rate | H60: 0.02 | I60: 0.02 | J60: 0.02 | K60: 0.02 | L60: 0.02
B61: Adjusted net income | F61: ='Quarterly (A)'!L25 -> 911.688 | G61: ='Quarterly (A)'!M25 -> 1044.752 | H61: =H58-H59 -> 668.34918 | I61: =I58-I59 -> 443.34128 | J61: =J58-J59 -> 457.22561 | K61: =K58-K59 -> 581.75179 | L61: =L58-L59 -> 766.44618
B62: Diluted shares (M) | F62: ='Quarterly (A)'!L26 -> 515.0305 | G62: ='Quarterly (A)'!M26 -> 495.3854 | H62: =Consensus!C38 -> 464 | I62: 466 | J62: 468 | K62: 470 | L62: 472
B63: Adjusted EPS | F63: ='Quarterly (A)'!L27 -> 1.77 | G63: ='Quarterly (A)'!M27 -> 2.11 | H63: =H61/H62 -> 1.4404077 | I63: =I61/I62 -> 0.95137614 | J63: =J61/J62 -> 0.97697781 | K63: =K61/K62 -> 1.2377698 | L63: =L61/L62 -> 1.6238267
B64: EPS growth | G64: =G63/F63-1 -> 0.1920904 | H64: =H63/G63-1 -> -0.31734232 | I64: =I63/H63-1 -> -0.33950913 | J64: =J63/I63-1 -> 0.026910145 | K64: =K63/J63-1 -> 0.26693744 | L64: =L63/K63-1 -> 0.31189718
B66: Versus consensus
B67: Consensus revenue | H67: =Consensus!C6 -> 10030 | I67: =Consensus!D6 -> 10570
B68: Revenue: ours less consensus ($mm) | H68: =H38-H67 -> -23.901594 | I68: =I38-I67 -> -230.11953
B69: Revenue: ours vs consensus (%) | H69: =H38/H67-1 -> -0.0023830104 | I69: =I38/I67-1 -> -0.021771005
B70: Consensus adjusted EPS (Yahoo) | H70: =Consensus!C7 -> 1.54 | I70: =Consensus!D7 -> 1.67 | J70: =Consensus!E7 -> 1.75
B71: EPS: ours less consensus ($) | H71: =H63-H70 -> -0.099592287 | I71: =I63-I70 -> -0.71862386 | J71: =J63-J70 -> -0.77302219
B72: EPS: ours vs consensus (%) | H72: =H63/H70-1 -> -0.064670317 | I72: =I63/I70-1 -> -0.43031369 | J72: =J63/J70-1 -> -0.44172697
B73: Consensus adjusted EPS (Nasdaq / Zacks) | H73: =Consensus!C8 -> 1.36 | I73: =Consensus!D8 -> 1.46 | J73: =Consensus!E8 -> 1.75
B74: EPS: ours vs Zacks consensus (%) | H74: =H63/H73-1 -> 0.059123318 | I74: =I63/I73-1 -> -0.34837251 | J74: =J63/J73-1 -> -0.44172697
B75: Street-implied EBITDA | I75: =Consensus!C57 -> 2693.22
B76: EBITDA: ours vs Street (%) | I76: =I52/I75-1 -> -0.081995135
B78: Cash flow and net debt
B79: Adjusted EBITDA | H79: =H52 -> 2471.989 | I79: =I52 -> 2472.3891 | J79: =J52 -> 2665.5119 | K79: =K52 -> 2893.0698 | L79: =L52 -> 3154.0527
B80: (-) Net interest | H80: =H56 -> 705 | I80: =I56 -> 870 | J80: =J56 -> 968.95517 | K80: =K56 -> 999.4455 | L80: =L56 -> 1001.9648
B81: (-) Income tax | H81: =H59 -> 13.639779 | I81: =I59 -> 9.0477812 | J81: =J59 -> 9.331135 | K81: =K59 -> 11.872485 | L81: =L59 -> 15.641759
B82: (-) Newbuild capex, gross | H82: 2900 | I82: 2900 | J82: 1800 | K82: 1500 | L82: 1800
B83: (-) Other capex | H83: 540 | I83: 600 | J83: 620 | K83: 640 | L83: 660
B84: Advance ticket sales (year end) | G84: ='Quarterly (A)'!M39 -> 3200.593 | H84: =H24 -> 3000 | I84: =H84*(1+I39) -> 3100.0736 | J84: =I84*(1+J39) -> 3276.1982 | K84: =J84*(1+K39) -> 3488.4529 | L84: =K84*(1+L39) -> 3733.8365
B85: (+) Change in advance ticket sales | H85: =H84-G84 -> -200.593 | I85: =I84-H84 -> 100.07359 | J85: =J84-I84 -> 176.12457 | K85: =K84-J84 -> 212.25478 | L85: =L84-K84 -> 245.38351
B86: (+) Other (asset sales, other working capital) | H86: 400 | I86: 0 | J86: 0 | K86: 0 | L86: 0
B87: Free cash flow before financing | H87: =H79-H80-H81-H82-H83+H85+H86 -> -1487.2438 | I87: =I79-I80-I81-I82-I83+I85+I86 -> -1806.5851 | J87: =J79-J80-J81-J82-J83+J85+J86 -> -556.64982 | K87: =K79-K80-K81-K82-K83+K85+K86 -> -45.993438 | L87: =L79-L80-L81-L82-L83+L85+L86 -> -78.170305
B88: Net debt (year end) | G88: ='Quarterly (A)'!M40 -> 14396 | H88: =G88-H87 -> 15883.244 | I88: =H88-I87 -> 17689.829 | J88: =I88-J87 -> 18246.479 | K88: =J88-K87 -> 18292.472 | L88: =K88-L87 -> 18370.643
B89: Net debt / EBITDA | G89: =G88/G52 -> 5.2728236 | H89: =H88/H52 -> 6.4252891 | I89: =I88/I52 -> 7.1549536 | J89: =J88/J52 -> 6.8453938 | K89: =K88/K52 -> 6.322859 | L89: =L88/L52 -> 5.8244564
B91: Returns on capital (threshold test)
B92: Book equity (year end) | G92: 2210 | H92: =G92+H61 -> 2878.3492 | I92: =H92+I61 -> 3321.6905 | J92: =I92+J61 -> 3778.9161 | K92: =J92+K61 -> 4360.6679 | L92: =K92+L61 -> 5127.114
B93: Invested capital (net debt + equity) | G93: =G88+G92 -> 16606 | H93: =H88+H92 -> 18761.593 | I93: =I88+I92 -> 21011.519 | J93: =J88+J92 -> 22025.395 | K93: =K88+K92 -> 22653.14 | L93: =L88+L92 -> 23497.757
B94: Pre-tax return on invested capital | G94: =G55/G93 -> 0.099450259 | H94: =H55/((H93+G93)/2) -> 0.078432759 | I94: =I55/((I93+H93)/2) -> 0.066496635 | J94: =J55/((J93+I93)/2) -> 0.066710727 | K94: =K55/((K93+J93)/2) -> 0.071312534 | L94: =L55/((L93+K93)/2) -> 0.077313892
B95: Cost of capital (DCF tab) | G95: =DCF!$L$24 -> 0.090451112 | H95: =DCF!$L$24 -> 0.090451112 | I95: =DCF!$L$24 -> 0.090451112 | J95: =DCF!$L$24 -> 0.090451112 | K95: =DCF!$L$24 -> 0.090451112 | L95: =DCF!$L$24 -> 0.090451112
B96: ROIC less cost of capital | G96: =G94-G95 -> 0.0089991473 | H96: =H94-H95 -> -0.012018352 | I96: =I94-I95 -> -0.023954477 | J96: =J94-J95 -> -0.023740385 | K96: =K94-K95 -> -0.019138578 | L96: =L94-L95 -> -0.01313722
B98: Unlevered free cash flow (DCF cross-check)
B99: Adjusted EBIT | I99: =I55 -> 1322.3891 | J99: =J55 -> 1435.5119 | K99: =K55 -> 1593.0698 | L99: =L55 -> 1784.0527
B100: (-) Taxes on EBIT | I100: =MAX(0,I55*I60) -> 26.447781 | J100: =MAX(0,J55*J60) -> 28.710238 | K100: =MAX(0,K55*K60) -> 31.861395 | L100: =MAX(0,L55*L60) -> 35.681054
B101: NOPAT | I101: =I99-I100 -> 1295.9413 | J101: =J99-J100 -> 1406.8017 | K101: =K99-K100 -> 1561.2084 | L101: =L99-L100 -> 1748.3717
B102: (+) D&A | I102: =I54 -> 1150 | J102: =J54 -> 1230 | K102: =K54 -> 1300 | L102: =L54 -> 1370
B103: (-) Capex (newbuild + other) | I103: =I82+I83 -> 3500 | J103: =J82+J83 -> 2420 | K103: =K82+K83 -> 2140 | L103: =L82+L83 -> 2460
B104: (+) Change in advance ticket sales | I104: =I85 -> 100.07359 | J104: =J85 -> 176.12457 | K104: =K85 -> 212.25478 | L104: =L85 -> 245.38351
B105: Unlevered free cash flow | I105: =I101+I102-I103+I104 -> -953.98513 | J105: =J101+J102-J103+J104 -> 392.92625 | K105: =K101+K102-K103+K104 -> 933.46315 | L105: =L101+L102-L103+L104 -> 903.75517
B106: Discount period (years from YE2026) | I106: 0.5 | J106: 1.5 | K106: 2.5 | L106: 3.5
B107: Present value | I107: =I105/(1+DCF!$L$24)^I106 -> -913.56301 | J107: =J105/(1+DCF!$L$24)^J106 -> 345.06566 | K107: =K105/(1+DCF!$L$24)^K106 -> 751.76427 | L107: =L105/(1+DCF!$L$24)^L106 -> 667.46592

Sheet Net Yield Build
B2: Net Yield Build: occupancy x (ticket + onboard - commissions - onboard costs) per passenger day | F2: Q1'25A | G2: Q2'25A | H2: Q3'25A | I2: Q4'25A | J2: Q1'26A | K2: Q2'26A | L2: Q3'26E | M2: Q4'26E | N2: Q1'27E | O2: Q2'27E | P2: Q3'27E | Q2: Q4'27E | S2: FY2025A | T2: FY2026E | U2: FY2027E
B3: $ per day unless noted. Case switch: DCF!C9 (1 = Bull, consensus-calibrated; 2 = Base; 3 = Bear)
B5: Common drivers (all cases)
B6: Capacity days growth y/y (3Q-4Q26 guidance; 2027 Fleet Qtr Build) | C6: fleet / guidance | L6: 0.05957 | M6: 0.0326 | N6: ='Fleet Qtr Build'!L12 -> 0.033419921 | O6: ='Fleet Qtr Build'!M12 -> 0.00079604886 | P6: ='Fleet Qtr Build'!N12 -> 0.04866049 | Q6: ='Fleet Qtr Build'!O12 -> 0.04983149
B7: Caribbean share of NCLH capacity (KPI 1 build) | C7: deployment est. | L7: ='KPI 1 Price Build'!D10 -> 0.18 | M7: ='KPI 1 Price Build'!E10 -> 0.5 | N7: ='KPI 1 Price Build'!F10 -> 0.62 | O7: ='KPI 1 Price Build'!G10 -> 0.38 | P7: ='KPI 1 Price Build'!H10 -> 0.2 | Q7: ='KPI 1 Price Build'!I10 -> 0.48
B8: Observed NCL fare change: Caribbean (KPI 1 build) | L8: ='KPI 1 Price Build'!D16 -> 0 | M8: ='KPI 1 Price Build'!E16 -> -0.36 | N8: ='KPI 1 Price Build'!F16 -> -0.145 | O8: ='KPI 1 Price Build'!G16 -> -0.145 | P8: ='KPI 1 Price Build'!H16 -> -0.02 | Q8: ='KPI 1 Price Build'!I16 -> -0.02
B9: Observed NCL fare change: other regions (KPI 1 build) | L9: ='KPI 1 Price Build'!D17 -> 0 | M9: ='KPI 1 Price Build'!E17 -> -0.13434783 | N9: ='KPI 1 Price Build'!F17 -> -0.028461538 | O9: ='KPI 1 Price Build'!G17 -> -0.028461538 | P9: ='KPI 1 Price Build'!H17 -> -0.003 | Q9: ='KPI 1 Price Build'!I17 -> -0.003
B10: Full-fare commission step-up (pts of ticket; KPI 1 build) | C10: NCF elimination | L10: ='KPI 1 Price Build'!D49 -> 0.006 | M10: ='KPI 1 Price Build'!E49 -> 0.009 | N10: ='KPI 1 Price Build'!F49 -> 0.0130005 | O10: ='KPI 1 Price Build'!G49 -> 0.0109995 | P10: ='KPI 1 Price Build'!H49 -> 0.0075 | Q10: ='KPI 1 Price Build'!I49 -> 0.0049995
B12: Bull case: Street-like recovery (approximates consensus)
B13: Occupancy change y/y (pts) | L13: -2.4 | M13: -2.8 | N13: -1 | O13: 0.5 | P13: 1.5 | Q13: 2
B14: Underlying price change y/y (3Q-4Q26 calibrated to guidance) | L14: -0.0995 | M14: -0.027403856 | N14: 0.005 | O14: 0.005 | P14: 0.005 | Q14: 0.005
B15: Thesis 1: fare cuts on unsold cabins (KPI 1 build) | L15: ='KPI 1 Price Build'!D40 -> 0 | M15: ='KPI 1 Price Build'!E40 -> -0.032896144 | N15: ='KPI 1 Price Build'!F40 -> -0.018559834 | O15: ='KPI 1 Price Build'!G40 -> -0.013061766 | P15: ='KPI 1 Price Build'!H40 -> -0.0010907097 | Q15: ='KPI 1 Price Build'!I40 -> -0.0020300744
B16: Brand / new-ship mix effect on ticket price | L16: 0.005 | M16: 0.005 | N16: 0.01 | O16: 0.01 | P16: 0.01 | Q16: 0.01
B17: Thesis 2: late discounts on the booking shortfall (KPI 2 build) | L17: 0 | M17: 0 | N17: 0 | O17: 0 | P17: 0 | Q17: 0
B18: Onboard revenue per passenger day growth | L18: 0.04 | M18: 0.03 | N18: 0.035 | O18: 0.03 | P18: 0.035 | Q18: 0.035
B19: Capacity days (M) | F19: ='Quarterly (A)'!E29 -> 5.7006 | G19: ='Quarterly (A)'!F29 -> 6.0523 | H19: ='Quarterly (A)'!G29 -> 6.4176 | I19: ='Quarterly (A)'!H29 -> 6.2631 | J19: ='Quarterly (A)'!I29 -> 6.393 | K19: ='Quarterly (A)'!J29 -> 6.5897 | L19: =H19*(1+L$6) -> 6.7998964 | M19: =I19*(1+M$6) -> 6.4672771 | N19: =J19*(1+N$6) -> 6.6066536 | O19: =K19*(1+O$6) -> 6.5949457 | P19: =L19*(1+P$6) -> 7.1307827 | Q19: =M19*(1+Q$6) -> 6.7895511 | S19: =SUM(F19:I19) -> 24.4336 | T19: =SUM(J19:M19) -> 26.249873 | U19: =SUM(N19:Q19) -> 27.121933
B20: Occupancy | F20: ='Quarterly (A)'!E31 -> 1.0151914 | G20: ='Quarterly (A)'!F31 -> 1.0390761 | H20: ='Quarterly (A)'!G31 -> 1.0639959 | I20: ='Quarterly (A)'!H31 -> 1.0177229 | J20: ='Quarterly (A)'!I31 -> 1.0377757 | K20: ='Quarterly (A)'!J31 -> 1.0237188 | L20: =H20+L13/100 -> 1.0399959 | M20: =I20+M13/100 -> 0.98972285 | N20: =J20+N13/100 -> 1.0277757 | O20: =K20+O13/100 -> 1.0287188 | P20: =L20+P13/100 -> 1.0549959 | Q20: =M20+Q13/100 -> 1.0097229 | S20: =S21/S19 -> 1.0345753 | T20: =T21/T19 -> 1.0229831 | U20: =U21/U19 -> 1.0306424
B21: Passenger cruise days (M) | F21: =F19*F20 -> 5.7872 | G21: =G19*G20 -> 6.2888 | H21: =H19*H20 -> 6.8283 | I21: =I19*I20 -> 6.3741 | J21: =J19*J20 -> 6.6345 | K21: =K19*K20 -> 6.746 | L21: =L19*L20 -> 7.0718643 | M21: =M19*M20 -> 6.4008119 | ... Q21: =Q19*Q20 -> 6.8555649 | S21: =SUM(F21:I21) -> 25.2784 | T21: =SUM(J21:M21) -> 26.853176 | U21: =SUM(N21:Q21) -> 27.953014
B22: Underlying price change | L22: =L14 -> -0.0995 | M22: =M14 -> -0.027403856 | N22: =N14 -> 0.005 | O22: =O14 -> 0.005 | P22: =P14 -> 0.005 | Q22: =Q14 -> 0.005
B23: Thesis effects (Thesis 1 + Thesis 2) | L23: =L15+L17 -> 0 | M23: =M15+M17 -> -0.032896144 | N23: =N15+N17 -> -0.018559834 | O23: =O15+O17 -> -0.013061766 | P23: =P15+P17 -> -0.0010907097 | Q23: =Q15+Q17 -> -0.0020300744
B24: KPI 1: like-for-like ticket price change y/y | L24: =L22+L23 -> -0.0995 | M24: =M22+M23 -> -0.0603 | N24: =N22+N23 -> -0.013559834 | O24: =O22+O23 -> -0.0080617665 | P24: =P22+P23 -> 0.0039092903 | Q24: =Q22+Q23 -> 0.0029699256
B25: Ticket revenue per passenger day | F25: ='Quarterly (A)'!E34 -> 245.14169 | G25: ='Quarterly (A)'!F34 -> 271.75057 | H25: ='Quarterly (A)'!G34 -> 300.21513 | I25: ='Quarterly (A)'!H34 -> 236.90231 | J25: ='Quarterly (A)'!I34 -> 232.46982 | K25: ='Quarterly (A)'!J34 -> 256.42425 | L25: =H25*(1+L24+L16) -> 271.8448 | M25: =I25*(1+M24+M16) -> 223.80161 | N25: =J25*(1+N24+N16) -> 231.64226 | O25: =K25*(1+O24+O16) -> 256.92126 | P25: =L25*(1+P24+P16) -> 275.62597 | Q25: =M25*(1+Q24+Q16) -> 226.7043 | S25: =S32/S21 -> 264.56053 | T25: =T32/T21 -> 246.79094 | U25: =U32/U21 -> 248.40382
B26: Onboard revenue per passenger day | F26: ='Quarterly (A)'!E35 -> 122.48911 | G26: ='Quarterly (A)'!F35 -> 128.5638 | H26: ='Quarterly (A)'!G35 -> 130.07381 | I26: ='Quarterly (A)'!H35 -> 115.21015 | J26: ='Quarterly (A)'!I35 -> 118.90873 | K26: ='Quarterly (A)'!J35 -> 134.99941 | L26: =H26*(1+L18) -> 135.27676 | M26: =I26*(1+M18) -> 118.66645 | N26: =J26*(1+N18) -> 123.07054 | O26: =K26*(1+O18) -> 139.04939 | P26: =L26*(1+P18) -> 140.01145 | Q26: =M26*(1+Q18) -> 122.81978 | S26: =S33/S21 -> 124.21376 | T26: =T33/T21 -> 127.20382 | U26: =U33/U21 -> 131.44647
B27: Commissions/transport % of ticket | F27: ='Quarterly (A)'!E36 -> 0.27866882 | G27: ='Quarterly (A)'!F36 -> 0.28545306 | H27: ='Quarterly (A)'!G36 -> 0.25462997 | I27: ='Quarterly (A)'!H36 -> 0.24955978 | J27: ='Quarterly (A)'!I36 -> 0.25779653 | K27: ='Quarterly (A)'!J36 -> 0.28018115 | L27: =H27+L$10 -> 0.26062997 | M27: =I27+M$10 -> 0.25855978 | N27: =J27+N$10 -> 0.27079703 | O27: =K27+O$10 -> 0.29118065 | P27: =L27+P$10 -> 0.26812997 | Q27: =M27+Q$10 -> 0.26355928 | S27: =S35/S32 -> 0.26646123 | T27: =T35/T32 -> 0.26462639 | U27: =U35/U32 -> 0.27349742
B28: Onboard costs % of onboard revenue | F28: ='Quarterly (A)'!E37 -> 0.19588669 | G28: ='Quarterly (A)'!F37 -> 0.23213508 | H28: ='Quarterly (A)'!G37 -> 0.24995074 | I28: ='Quarterly (A)'!H37 -> 0.19088704 | J28: ='Quarterly (A)'!I37 -> 0.19250602 | K28: ='Quarterly (A)'!J37 -> 0.21021713 | L28: =H28 -> 0.24995074 | M28: =I28 -> 0.19088704 | N28: =J28 -> 0.19250602 | O28: =K28 -> 0.21021713 | P28: =L28 -> 0.24995074 | Q28: =M28 -> 0.19088704 | S28: =S36/S33 -> 0.21934409 | T28: =T36/T33 -> 0.21295639 | U28: =U36/U33 -> 0.2131496
B29: Net per diem | F29: =F25+F26-F25*F27-F26*F28 -> 275.32347 | G29: =G25+G26-G25*G27-G26*G28 -> 292.89817 | H29: =H25+H26-H25*H27-H26*H28 -> 321.33313 | I29: =I25+I26-I25*I27-I26*I28 -> 270.99904 | J29: =J25+J26-J25*J27-J26*J28 -> 268.55799 | K29: =K25+K26-K25*K27-K26*K28 -> 291.19923 | L29: =L25+L26-L25*L27-L26*L28 -> 302.45814 | M29: =M25+M26-M25*M27-M26*M28 -> 261.95008 | ... Q29: =Q25+Q26-Q25*Q27-Q26*Q28 -> 266.32935 | S29: =S37/S21 -> 291.03361 | T29: =T37/T21 -> 281.5985 | U29: =U37/U21 -> 283.89472
B30: NET YIELD ($ per capacity day) | F30: =F29*F20 -> 279.50602 | G30: =G29*G20 -> 304.34347 | H30: =H29*H20 -> 341.89713 | I30: =I29*I20 -> 275.80192 | J30: =J29*J20 -> 278.70296 | K30: =K29*K20 -> 298.10614 | L30: =L29*L20 -> 314.55522 | M30: =M29*M20 -> 259.25798 | ... Q30: =Q29*Q20 -> 268.91883 | S30: =S37/S19 -> 301.0962 | T30: =T37/T19 -> 288.0705 | U30: =U37/U19 -> 292.59394
B31: Net yield y/y | J31: =J30/F30-1 -> -0.0028731423 | K31: =K30/G30-1 -> -0.020494402 | L31: =L30/H30-1 -> -0.079971158 | M31: =M30/I30-1 -> -0.059984861 | N31: =N30/J30-1 -> -0.010613405 | O31: =O30/K30-1 -> 0.007404509 | P31: =P30/L30-1 -> 0.028777065 | Q31: =Q30/M30-1 -> 0.037263476 | S31: =S30/'Quarterly (A)'!L32-1 -> 0.022992852 | T31: =T30/S30-1 -> -0.043260922 | U31: =U30/T30-1 -> 0.015702552
B32: Passenger ticket revenue ($mm) | F32: =F25*F21 -> 1418.684 | G32: =G25*G21 -> 1708.985 | H32: =H25*H21 -> 2049.959 | I32: =I25*I21 -> 1510.039 | J32: =J25*J21 -> 1542.321 | K32: =K25*K21 -> 1729.838 | L32: =L25*L21 -> 1922.4496 | M32: =M25*M21 -> 1432.512 | ... Q32: =Q25*Q21 -> 1554.186 | S32: =SUM(F32:I32) -> 6687.667 | T32: =SUM(J32:M32) -> 6627.1206 | U32: =SUM(N32:Q32) -> 6943.6355
B33: Onboard and other revenue ($mm) | F33: =F26*F21 -> 708.869 | G33: =G26*G21 -> 808.512 | H33: =H26*H21 -> 888.183 | I33: =I26*I21 -> 734.361 | J33: =J26*J21 -> 788.9 | K33: =K26*K21 -> 910.706 | L33: =L26*L21 -> 956.65891 | M33: =M26*M21 -> 759.56164 | ... Q33: =Q26*Q21 -> 841.99896 | S33: =SUM(F33:I33) -> 3139.925 | T33: =SUM(J33:M33) -> 3415.8265 | U33: =SUM(N33:Q33) -> 3674.325
B34: Total revenue ($mm) | F34: =F32+F33 -> 2127.553 | G34: =G32+G33 -> 2517.497 | H34: =H32+H33 -> 2938.142 | I34: =I32+I33 -> 2244.4 | J34: =J32+J33 -> 2331.221 | K34: =K32+K33 -> 2640.544 | L34: =L32+L33 -> 2879.1085 | M34: =M32+M33 -> 2192.0736 | ... Q34: =Q32+Q33 -> 2396.185 | S34: =SUM(F34:I34) -> 9827.592 | T34: =SUM(J34:M34) -> 10042.947 | U34: =SUM(N34:Q34) -> 10617.96
B35: Commissions, transportation and other ($mm) | F35: =F32*F27 -> 395.343 | G35: =G32*G27 -> 487.835 | H35: =H32*H27 -> 521.981 | I35: =I32*I27 -> 376.845 | J35: =J32*J27 -> 397.605 | K35: =K32*K27 -> 484.668 | L35: =L32*L27 -> 501.04797 | M35: =M32*M27 -> 370.38999 | ... Q35: =Q32*Q27 -> 409.62016 | S35: =SUM(F35:I35) -> 1782.004 | T35: =SUM(J35:M35) -> 1753.711 | U35: =SUM(N35:Q35) -> 1899.0664
B36: Onboard and other expense ($mm) | F36: =F33*F28 -> 138.858 | G36: =G33*G28 -> 187.684 | H36: =H33*H28 -> 222.002 | I36: =I33*I28 -> 140.18 | J36: =J33*J28 -> 151.868 | K36: =K33*K28 -> 191.446 | L36: =L33*L28 -> 239.11761 | M36: =M33*M28 -> 144.99048 | ... Q36: =Q33*Q28 -> 160.72669 | S36: =SUM(F36:I36) -> 688.724 | T36: =SUM(J36:M36) -> 727.42208 | U36: =SUM(N36:Q36) -> 783.18089
B37: Adjusted gross margin ($mm) | F37: =F34-F35-F36 -> 1593.352 | G37: =G34-G35-G36 -> 1841.978 | H37: =H34-H35-H36 -> 2194.159 | I37: =I34-I35-I36 -> 1727.375 | J37: =J34-J35-J36 -> 1781.748 | K37: =K34-K35-K36 -> 1964.43 | L37: =L34-L35-L36 -> 2138.9429 | M37: =M34-M35-M36 -> 1676.6932 | ... Q37: =Q34-Q35-Q36 -> 1825.8382 | S37: =SUM(F37:I37) -> 7356.864 | T37: =SUM(J37:M37) -> 7561.8141 | U37: =SUM(N37:Q37) -> 7935.7132
B39: Base case: our view
B40: Occupancy change y/y (pts): consensus case + KPI 2 (2027) | L40: -2.4 | M40: -2.8 | N40: =N13+'KPI 2 Booking Build'!F26 -> -2 | O40: =O13+'KPI 2 Booking Build'!G26 -> -0.5 | P40: =P13+'KPI 2 Booking Build'!H26 -> 0.5 | Q40: =Q13+'KPI 2 Booking Build'!I26 -> 1
B41: Underlying price on sold cabins (2H26 calibrated to guidance; 2027 = consensus case) | L41: -0.1055 | M41: -0.043303856 | N41: =N14 -> 0.005 | O41: =O14 -> 0.005 | P41: =P14 -> 0.005 | Q41: =Q14 -> 0.005
B42: Thesis 1: fare cuts on unsold cabins (KPI 1 build) | L42: ='KPI 1 Price Build'!D39 -> 0 | M42: ='KPI 1 Price Build'!E39 -> -0.032896144 | N42: ='KPI 1 Price Build'!F39 -> -0.033407702 | O42: ='KPI 1 Price Build'!G39 -> -0.028735886 | P42: ='KPI 1 Price Build'!H39 -> -0.0028358453 | Q42: ='KPI 1 Price Build'!I39 -> -0.0060902232
B43: Brand / new-ship mix effect on ticket price | L43: 0.005 | M43: 0.005 | N43: 0.01 | O43: 0.01 | P43: 0.01 | Q43: 0.01
B44: Thesis 2: late discounts on the booking shortfall (KPI 2 build) | L44: ='KPI 2 Booking Build'!D32 -> 0 | M44: ='KPI 2 Booking Build'!E32 -> 0 | N44: ='KPI 2 Booking Build'!F32 -> 0 | O44: ='KPI 2 Booking Build'!G32 -> 0 | P44: ='KPI 2 Booking Build'!H32 -> -0.0065792288 | Q44: ='KPI 2 Booking Build'!I32 -> -0.0065792288
B45: Onboard revenue per passenger day growth | L45: 0.04 | M45: 0.03 | N45: 0.02 | O45: 0.015 | P45: 0.02 | Q45: 0.02
B46: Capacity days (M) | F46: ='Quarterly (A)'!E29 -> 5.7006 | G46: ='Quarterly (A)'!F29 -> 6.0523 | H46: ='Quarterly (A)'!G29 -> 6.4176 | I46: ='Quarterly (A)'!H29 -> 6.2631 | J46: ='Quarterly (A)'!I29 -> 6.393 | K46: ='Quarterly (A)'!J29 -> 6.5897 | L46: =H46*(1+L$6) -> 6.7998964 | M46: =I46*(1+M$6) -> 6.4672771 | N46: =J46*(1+N$6) -> 6.6066536 | O46: =K46*(1+O$6) -> 6.5949457 | P46: =L46*(1+P$6) -> 7.1307827 | Q46: =M46*(1+Q$6) -> 6.7895511 | S46: =SUM(F46:I46) -> 24.4336 | T46: =SUM(J46:M46) -> 26.249873 | U46: =SUM(N46:Q46) -> 27.121933
B47: Occupancy | F47: ='Quarterly (A)'!E31 -> 1.0151914 | G47: ='Quarterly (A)'!F31 -> 1.0390761 | H47: ='Quarterly (A)'!G31 -> 1.0639959 | I47: ='Quarterly (A)'!H31 -> 1.0177229 | J47: ='Quarterly (A)'!I31 -> 1.0377757 | K47: ='Quarterly (A)'!J31 -> 1.0237188 | L47: =H47+L40/100 -> 1.0399959 | M47: =I47+M40/100 -> 0.98972285 | N47: =J47+N40/100 -> 1.0177757 | O47: =K47+O40/100 -> 1.0187188 | P47: =L47+P40/100 -> 1.0449959 | Q47: =M47+Q40/100 -> 0.99972285 | S47: =S48/S46 -> 1.0345753 | T47: =T48/T46 -> 1.0229831 | U47: =U48/U46 -> 1.0206424
B48: Passenger cruise days (M) | F48: =F46*F47 -> 5.7872 | G48: =G46*G47 -> 6.2888 | H48: =H46*H47 -> 6.8283 | I48: =I46*I47 -> 6.3741 | J48: =J46*J47 -> 6.6345 | K48: =K46*K47 -> 6.746 | L48: =L46*L47 -> 7.0718643 | M48: =M46*M47 -> 6.4008119 | ... Q48: =Q46*Q47 -> 6.7876694 | S48: =SUM(F48:I48) -> 25.2784 | T48: =SUM(J48:M48) -> 26.853176 | U48: =SUM(N48:Q48) -> 27.681795
B49: Underlying price change | L49: =L41 -> -0.1055 | M49: =M41 -> -0.043303856 | N49: =N41 -> 0.005 | O49: =O41 -> 0.005 | P49: =P41 -> 0.005 | Q49: =Q41 -> 0.005
B50: Thesis effects (Thesis 1 + Thesis 2) | L50: =L42+L44 -> 0 | M50: =M42+M44 -> -0.032896144 | N50: =N42+N44 -> -0.033407702 | O50: =O42+O44 -> -0.028735886 | P50: =P42+P44 -> -0.0094150741 | Q50: =Q42+Q44 -> -0.012669452
B51: KPI 1: like-for-like ticket price change y/y | L51: =L49+L50 -> -0.1055 | M51: =M49+M50 -> -0.0762 | N51: =N49+N50 -> -0.028407702 | O51: =O49+O50 -> -0.023735886 | P51: =P49+P50 -> -0.0044150741 | Q51: =Q49+Q50 -> -0.0076694521
B52: Ticket revenue per passenger day | F52: ='Quarterly (A)'!E34 -> 245.14169 | G52: ='Quarterly (A)'!F34 -> 271.75057 | H52: ='Quarterly (A)'!G34 -> 300.21513 | I52: ='Quarterly (A)'!H34 -> 236.90231 | J52: ='Quarterly (A)'!I34 -> 232.46982 | K52: ='Quarterly (A)'!J34 -> 256.42425 | L52: =H52*(1+L51+L43+'KPI 2 Booking Build'!D52) -> 270.04351 | M52: =I52*(1+M51+M43+'KPI 2 Booking Build'!E52) -> 220.03486 | N52: =J52*(1+N51+N43+'KPI 2 Booking Build'!F52) -> 228.19058 | O52: =K52*(1+O51+O43+'KPI 2 Booking Build'!G52) -> 252.90204 | P52: =L52*(1+P51+P43+'KPI 2 Booking Build'!H52) -> 271.55169 | Q52: =M52*(1+Q51+Q43+'KPI 2 Booking Build'!I52) -> 220.54767 | S52: =S59/S48 -> 264.56053 | T52: =T59/T48 -> 245.41871 | U52: =U59/U48 -> 243.98634
B53: Onboard revenue per passenger day | F53: ='Quarterly (A)'!E35 -> 122.48911 | G53: ='Quarterly (A)'!F35 -> 128.5638 | H53: ='Quarterly (A)'!G35 -> 130.07381 | I53: ='Quarterly (A)'!H35 -> 115.21015 | J53: ='Quarterly (A)'!I35 -> 118.90873 | K53: ='Quarterly (A)'!J35 -> 134.99941 | L53: =H53*(1+L45) -> 135.27676 | M53: =I53*(1+M45) -> 118.66645 | N53: =J53*(1+N45) -> 121.28691 | O53: =K53*(1+O45) -> 137.0244 | P53: =L53*(1+P45) -> 137.9823 | Q53: =M53*(1+Q45) -> 121.03978 | S53: =S60/S48 -> 124.21376 | T53: =T60/T48 -> 127.20382 | U53: =U60/U48 -> 129.54003
B54: Commissions/transport % of ticket | F54: ='Quarterly (A)'!E36 -> 0.27866882 | G54: ='Quarterly (A)'!F36 -> 0.28545306 | H54: ='Quarterly (A)'!G36 -> 0.25462997 | I54: ='Quarterly (A)'!H36 -> 0.24955978 | J54: ='Quarterly (A)'!I36 -> 0.25779653 | K54: ='Quarterly (A)'!J36 -> 0.28018115 | L54: =H54+L$10 -> 0.26062997 | M54: =I54+M$10 -> 0.25855978 | N54: =J54+N$10 -> 0.27079703 | O54: =K54+O$10 -> 0.29118065 | P54: =L54+P$10 -> 0.26812997 | Q54: =M54+Q$10 -> 0.26355928 | S54: =S62/S59 -> 0.26646123 | T54: =T62/T59 -> 0.2646563 | U54: =U62/U59 -> 0.27352164
B55: Onboard costs % of onboard revenue | F55: ='Quarterly (A)'!E37 -> 0.19588669 | G55: ='Quarterly (A)'!F37 -> 0.23213508 | H55: ='Quarterly (A)'!G37 -> 0.24995074 | I55: ='Quarterly (A)'!H37 -> 0.19088704 | J55: ='Quarterly (A)'!I37 -> 0.19250602 | K55: ='Quarterly (A)'!J37 -> 0.21021713 | L55: =H55 -> 0.24995074 | M55: =I55 -> 0.19088704 | N55: =J55 -> 0.19250602 | O55: =K55 -> 0.21021713 | P55: =L55 -> 0.24995074 | Q55: =M55 -> 0.19088704 | S55: =S63/S60 -> 0.21934409 | T55: =T63/T60 -> 0.21295639 | U55: =U63/U60 -> 0.21315321
B56: Net per diem | F56: =F52+F53-F52*F54-F53*F55 -> 275.32347 | G56: =G52+G53-G52*G54-G53*G55 -> 292.89817 | H56: =H52+H53-H52*H54-H53*H55 -> 321.33313 | I56: =I52+I53-I52*I54-I53*I55 -> 270.99904 | J56: =J52+J53-J52*J54-J53*J55 -> 268.55799 | K56: =K52+K53-K52*K54-K53*K55 -> 291.19923 | L56: =L52+L53-L52*L54-L53*L55 -> 301.12632 | M56: =M52+M53-M52*M54-M53*M55 -> 259.15726 | ... Q56: =Q52+Q53-Q52*Q54-Q53*Q55 -> 260.35514 | S56: =S64/S48 -> 291.03361 | T56: =T64/T48 -> 280.58205 | U56: =U64/U48 -> 279.17896
B57: NET YIELD ($ per capacity day) | F57: =F56*F47 -> 279.50602 | G57: =G56*G47 -> 304.34347 | H57: =H56*H47 -> 341.89713 | I57: =I56*I47 -> 275.80192 | J57: =J56*J47 -> 278.70296 | K57: =K56*K47 -> 298.10614 | L57: =L56*L47 -> 313.17013 | M57: =M56*M47 -> 256.49386 | ... Q57: =Q56*Q47 -> 260.28298 | S57: =S64/S46 -> 301.0962 | T57: =T64/T46 -> 287.03069 | U57: =U64/U46 -> 284.94188
B58: Net yield y/y | J58: =J57/F57-1 -> -0.0028731423 | K58: =K57/G57-1 -> -0.020494402 | L58: =L57/H57-1 -> -0.084022341 | M58: =M57/I57-1 -> -0.070006965 | N58: =N57/J57-1 -> -0.034691082 | O58: =O57/K57-1 -> -0.017589168 | P58: =P57/L57-1 -> 0.0085040694 | Q58: =Q57/M57-1 -> 0.014772734 | S58: =S57/'Quarterly (A)'!L32-1 -> 0.022992852 | T58: =T57/S57-1 -> -0.046714321 | U58: =U57/T57-1 -> -0.0072773132
B59: Passenger ticket revenue ($mm) | F59: =F52*F48 -> 1418.684 | G59: =G52*G48 -> 1708.985 | H59: =H52*H48 -> 2049.959 | I59: =I52*I48 -> 1510.039 | J59: =J52*J48 -> 1542.321 | K59: =K52*K48 -> 1729.838 | L59: =L52*L48 -> 1909.7111 | M59: =M52*M48 -> 1408.4018 | ... Q59: =Q52*Q48 -> 1497.0046 | S59: =SUM(F59:I59) -> 6687.667 | T59: =SUM(J59:M59) -> 6590.2719 | U59: =SUM(N59:Q59) -> 6753.9799
B60: Onboard and other revenue ($mm) | F60: =F53*F48 -> 708.869 | G60: =G53*G48 -> 808.512 | H60: =H53*H48 -> 888.183 | I60: =I53*I48 -> 734.361 | J60: =J53*J48 -> 788.9 | K60: =K53*K48 -> 910.706 | L60: =L53*L48 -> 956.65891 | M60: =M53*M48 -> 759.56164 | ... Q60: =Q53*Q48 -> 821.57802 | S60: =SUM(F60:I60) -> 3139.925 | T60: =SUM(J60:M60) -> 3415.8265 | U60: =SUM(N60:Q60) -> 3585.9006
B61: Total revenue ($mm) | F61: =F59+F60 -> 2127.553 | G61: =G59+G60 -> 2517.497 | H61: =H59+H60 -> 2938.142 | I61: =I59+I60 -> 2244.4 | J61: =J59+J60 -> 2331.221 | K61: =K59+K60 -> 2640.544 | L61: =L59+L60 -> 2866.37 | M61: =M59+M60 -> 2167.9634 | ... Q61: =Q59+Q60 -> 2318.5827 | S61: =SUM(F61:I61) -> 9827.592 | T61: =SUM(J61:M61) -> 10006.098 | U61: =SUM(N61:Q61) -> 10339.88
B62: Commissions, transportation and other ($mm) | F62: =F59*F54 -> 395.343 | G62: =G59*G54 -> 487.835 | H62: =H59*H54 -> 521.981 | I62: =I59*I54 -> 376.845 | J62: =J59*J54 -> 397.605 | K62: =K59*K54 -> 484.668 | L62: =L59*L54 -> 497.72794 | M62: =M59*M54 -> 364.15605 | ... Q62: =Q59*Q54 -> 394.54946 | S62: =SUM(F62:I62) -> 1782.004 | T62: =SUM(J62:M62) -> 1744.157 | U62: =SUM(N62:Q62) -> 1847.3597
B63: Onboard and other expense ($mm) | F63: =F60*F55 -> 138.858 | G63: =G60*G55 -> 187.684 | H63: =H60*H55 -> 222.002 | I63: =I60*I55 -> 140.18 | J63: =J60*J55 -> 151.868 | K63: =K60*K55 -> 191.446 | L63: =L60*L55 -> 239.11761 | M63: =M60*M55 -> 144.99048 | ... Q63: =Q60*Q55 -> 156.8286 | S63: =SUM(F63:I63) -> 688.724 | T63: =SUM(J63:M63) -> 727.42208 | U63: =SUM(N63:Q63) -> 764.34623
B64: Adjusted gross margin ($mm) | F64: =F61-F62-F63 -> 1593.352 | G64: =G61-G62-G63 -> 1841.978 | H64: =H61-H62-H63 -> 2194.159 | I64: =I61-I62-I63 -> 1727.375 | J64: =J61-J62-J63 -> 1781.748 | K64: =K61-K62-K63 -> 1964.43 | L64: =L61-L62-L63 -> 2129.5244 | M64: =M61-M62-M63 -> 1658.8169 | ... Q64: =Q61-Q62-Q63 -> 1767.2046 | S64: =SUM(F64:I64) -> 7356.864 | T64: =SUM(J64:M64) -> 7534.5193 | U64: =SUM(N64:Q64) -> 7728.1746
B66: Bear case: Caribbean discounting deepens
B67: Occupancy change y/y (pts): consensus case + KPI 2 (2027) | L67: -2.4 | M67: -2.8 | N67: =N13+'KPI 2 Booking Build'!F27 -> -2.6 | O67: =O13+'KPI 2 Booking Build'!G27 -> -1.1 | P67: =P13+'KPI 2 Booking Build'!H27 -> -0.1 | Q67: =Q13+'KPI 2 Booking Build'!I27 -> 0.4
B68: Underlying price change y/y (3Q-4Q26 calibrated to guidance) | L68: -0.1129 | M68: -0.054219434 | N68: -0.005 | O68: -0.005 | P68: -0.005 | Q68: -0.005
B69: Thesis 1: fare cuts on unsold cabins (KPI 1 build) | L69: ='KPI 1 Price Build'!D41 -> 0 | M69: ='KPI 1 Price Build'!E41 -> -0.037830566 | N69: ='KPI 1 Price Build'!F41 -> -0.035634882 | O69: ='KPI 1 Price Build'!G41 -> -0.030303298 | P69: ='KPI 1 Price Build'!H41 -> -0.0076792646 | Q69: ='KPI 1 Price Build'!I41 -> -0.020381721
B70: Brand / new-ship mix effect on ticket price | L70: 0.005 | M70: 0.005 | N70: 0.01 | O70: 0.01 | P70: 0.01 | Q70: 0.01
B71: Thesis 2: late discounts on the booking shortfall (KPI 2 build) | L71: ='KPI 2 Booking Build'!D33 -> 0 | M71: ='KPI 2 Booking Build'!E33 -> 0 | N71: ='KPI 2 Booking Build'!F33 -> 0 | O71: ='KPI 2 Booking Build'!G33 -> 0 | P71: ='KPI 2 Booking Build'!H33 -> -0.010526766 | Q71: ='KPI 2 Booking Build'!I33 -> -0.010526766
B72: Onboard revenue per passenger day growth | L72: 0.04 | M72: 0.03 | N72: 0.01 | O72: 0.01 | P72: 0.015 | Q72: 0.015
B73: Capacity days (M) | F73: ='Quarterly (A)'!E29 -> 5.7006 | G73: ='Quarterly (A)'!F29 -> 6.0523 | H73: ='Quarterly (A)'!G29 -> 6.4176 | I73: ='Quarterly (A)'!H29 -> 6.2631 | J73: ='Quarterly (A)'!I29 -> 6.393 | K73: ='Quarterly (A)'!J29 -> 6.5897 | L73: =H73*(1+L$6) -> 6.7998964 | M73: =I73*(1+M$6) -> 6.4672771 | N73: =J73*(1+N$6) -> 6.6066536 | O73: =K73*(1+O$6) -> 6.5949457 | P73: =L73*(1+P$6) -> 7.1307827 | Q73: =M73*(1+Q$6) -> 6.7895511 | S73: =SUM(F73:I73) -> 24.4336 | T73: =SUM(J73:M73) -> 26.249873 | U73: =SUM(N73:Q73) -> 27.121933
B74: Occupancy | F74: ='Quarterly (A)'!E31 -> 1.0151914 | G74: ='Quarterly (A)'!F31 -> 1.0390761 | H74: ='Quarterly (A)'!G31 -> 1.0639959 | I74: ='Quarterly (A)'!H31 -> 1.0177229 | J74: ='Quarterly (A)'!I31 -> 1.0377757 | K74: ='Quarterly (A)'!J31 -> 1.0237188 | L74: =H74+L67/100 -> 1.0399959 | M74: =I74+M67/100 -> 0.98972285 | N74: =J74+N67/100 -> 1.0117757 | O74: =K74+O67/100 -> 1.0127188 | P74: =L74+P67/100 -> 1.0389959 | Q74: =M74+Q67/100 -> 0.99372285 | S74: =S75/S73 -> 1.0345753 | T74: =T75/T73 -> 1.0229831 | U74: =U75/U73 -> 1.0146424
B75: Passenger cruise days (M) | F75: =F73*F74 -> 5.7872 | G75: =G73*G74 -> 6.2888 | H75: =H73*H74 -> 6.8283 | I75: =I73*I74 -> 6.3741 | J75: =J73*J74 -> 6.6345 | K75: =K73*K74 -> 6.746 | L75: =L73*L74 -> 7.0718643 | M75: =M73*M74 -> 6.4008119 | ... Q75: =Q73*Q74 -> 6.7469321 | S75: =SUM(F75:I75) -> 25.2784 | T75: =SUM(J75:M75) -> 26.853176 | U75: =SUM(N75:Q75) -> 27.519063
B76: Underlying price change | L76: =L68 -> -0.1129 | M76: =M68 -> -0.054219434 | N76: =N68 -> -0.005 | O76: =O68 -> -0.005 | P76: =P68 -> -0.005 | Q76: =Q68 -> -0.005
B77: Thesis effects (Thesis 1 + Thesis 2) | L77: =L69+L71 -> 0 | M77: =M69+M71 -> -0.037830566 | N77: =N69+N71 -> -0.035634882 | O77: =O69+O71 -> -0.030303298 | P77: =P69+P71 -> -0.018206031 | Q77: =Q69+Q71 -> -0.030908488
B78: KPI 1: like-for-like ticket price change y/y | L78: =L76+L77 -> -0.1129 | M78: =M76+M77 -> -0.09205 | N78: =N76+N77 -> -0.040634882 | O78: =O76+O77 -> -0.035303298 | P78: =P76+P77 -> -0.023206031 | Q78: =Q76+Q77 -> -0.035908488
B79: Ticket revenue per passenger day | F79: ='Quarterly (A)'!E34 -> 245.14169 | G79: ='Quarterly (A)'!F34 -> 271.75057 | H79: ='Quarterly (A)'!G34 -> 300.21513 | I79: ='Quarterly (A)'!H34 -> 236.90231 | J79: ='Quarterly (A)'!I34 -> 232.46982 | K79: ='Quarterly (A)'!J34 -> 256.42425 | L79: =H79*(1+L78+L70+'KPI 2 Booking Build'!D52) -> 267.82192 | M79: =I79*(1+M78+M70+'KPI 2 Booking Build'!E52) -> 216.27996 | N79: =J79*(1+N78+N70+'KPI 2 Booking Build'!F52) -> 225.34813 | O79: =K79*(1+O78+O70+'KPI 2 Booking Build'!G52) -> 249.93587 | P79: =L79*(1+P78+P70+'KPI 2 Booking Build'!H52) -> 264.28506 | Q79: =M79*(1+Q78+Q70+'KPI 2 Booking Build'!I52) -> 210.67648 | S79: =S86/S75 -> 264.56053 | T79: =T86/T75 -> 243.93862 | U79: =U86/U75 -> 238.20128
B80: Onboard revenue per passenger day | F80: ='Quarterly (A)'!E35 -> 122.48911 | G80: ='Quarterly (A)'!F35 -> 128.5638 | H80: ='Quarterly (A)'!G35 -> 130.07381 | I80: ='Quarterly (A)'!H35 -> 115.21015 | J80: ='Quarterly (A)'!I35 -> 118.90873 | K80: ='Quarterly (A)'!J35 -> 134.99941 | L80: =H80*(1+L72) -> 135.27676 | M80: =I80*(1+M72) -> 118.66645 | N80: =J80*(1+N72) -> 120.09782 | O80: =K80*(1+O72) -> 136.3494 | P80: =L80*(1+P72) -> 137.30591 | Q80: =M80*(1+Q72) -> 120.44645 | S80: =S87/S75 -> 124.21376 | T80: =T87/T75 -> 127.20382 | U80: =U87/U75 -> 128.76039
B81: Commissions/transport % of ticket | F81: ='Quarterly (A)'!E36 -> 0.27866882 | G81: ='Quarterly (A)'!F36 -> 0.28545306 | H81: ='Quarterly (A)'!G36 -> 0.25462997 | I81: ='Quarterly (A)'!H36 -> 0.24955978 | J81: ='Quarterly (A)'!I36 -> 0.25779653 | K81: ='Quarterly (A)'!J36 -> 0.28018115 | L81: =H81+L$10 -> 0.26062997 | M81: =I81+M$10 -> 0.25855978 | N81: =J81+N$10 -> 0.27079703 | O81: =K81+O$10 -> 0.29118065 | P81: =L81+P$10 -> 0.26812997 | Q81: =M81+Q$10 -> 0.26355928 | S81: =S89/S86 -> 0.26646123 | T81: =T89/T86 -> 0.26468833 | U81: =U89/U86 -> 0.27362168
B82: Onboard costs % of onboard revenue | F82: ='Quarterly (A)'!E37 -> 0.19588669 | G82: ='Quarterly (A)'!F37 -> 0.23213508 | H82: ='Quarterly (A)'!G37 -> 0.24995074 | I82: ='Quarterly (A)'!H37 -> 0.19088704 | J82: ='Quarterly (A)'!I37 -> 0.19250602 | K82: ='Quarterly (A)'!J37 -> 0.21021713 | L82: =H82 -> 0.24995074 | M82: =I82 -> 0.19088704 | N82: =J82 -> 0.19250602 | O82: =K82 -> 0.21021713 | P82: =L82 -> 0.24995074 | Q82: =M82 -> 0.19088704 | S82: =S90/S87 -> 0.21934409 | T82: =T90/T87 -> 0.21295639 | U82: =U90/U87 -> 0.21317856
B83: Net per diem | F83: =F79+F80-F79*F81-F80*F82 -> 275.32347 | G83: =G79+G80-G79*G81-G80*G82 -> 292.89817 | H83: =H79+H80-H79*H81-H80*H82 -> 321.33313 | I83: =I79+I80-I79*I81-I80*I82 -> 270.99904 | J83: =J79+J80-J79*J81-J80*J82 -> 268.55799 | K83: =K79+K80-K79*K81-K80*K82 -> 291.19923 | L83: =L79+L80-L79*L81-L80*L82 -> 299.48374 | M83: =M79+M80-M79*M81-M80*M82 -> 256.37323 | ... Q83: =Q79+Q80-Q79*Q81-Q80*Q82 -> 252.60552 | S83: =S91/S75 -> 291.03361 | T83: =T91/T75 -> 279.48586 | U83: =U91/U75 -> 274.33568
B84: NET YIELD ($ per capacity day) | F84: =F83*F74 -> 279.50602 | G84: =G83*G74 -> 304.34347 | H84: =H83*H74 -> 341.89713 | I84: =I83*I74 -> 275.80192 | J84: =J83*J74 -> 278.70296 | K84: =K83*K74 -> 298.10614 | L84: =L83*L74 -> 311.46185 | M84: =M83*M74 -> 253.73844 | ... Q84: =Q83*Q74 -> 251.01988 | S84: =S91/S73 -> 301.0962 | T84: =T91/T73 -> 285.90931 | U84: =U91/U73 -> 278.35261
B85: Net yield y/y | J85: =J84/F84-1 -> -0.0028731423 | K85: =K84/G84-1 -> -0.020494402 | L85: =L84/H84-1 -> -0.0890188 | M85: =M84/I84-1 -> -0.079997552 | N85: =N84/J84-1 -> -0.051392135 | O85: =O84/K84-1 -> -0.032328838 | P85: =P84/L84-1 -> -0.011220093 | Q85: =Q84/M84-1 -> -0.010714047 | S85: =S84/'Quarterly (A)'!L32-1 -> 0.022992852 | T85: =T84/S84-1 -> -0.050438657 | U85: =U84/T84-1 -> -0.026430387
B86: Passenger ticket revenue ($mm) | F86: =F79*F75 -> 1418.684 | G86: =G79*G75 -> 1708.985 | H86: =H79*H75 -> 2049.959 | I86: =I79*I75 -> 1510.039 | J86: =J79*J75 -> 1542.321 | K86: =K79*K75 -> 1729.838 | L86: =L79*L75 -> 1894.0003 | M86: =M79*M75 -> 1384.3674 | ... Q86: =Q79*Q75 -> 1421.4199 | S86: =SUM(F86:I86) -> 6687.667 | T86: =SUM(J86:M86) -> 6550.5266 | U86: =SUM(N86:Q86) -> 6555.076
B87: Onboard and other revenue ($mm) | F87: =F80*F75 -> 708.869 | G87: =G80*G75 -> 808.512 | H87: =H80*H75 -> 888.183 | I87: =I80*I75 -> 734.361 | J87: =J80*J75 -> 788.9 | K87: =K80*K75 -> 910.706 | L87: =L80*L75 -> 956.65891 | M87: =M80*M75 -> 759.56164 | ... Q87: =Q80*Q75 -> 812.64401 | S87: =SUM(F87:I87) -> 3139.925 | T87: =SUM(J87:M87) -> 3415.8265 | U87: =SUM(N87:Q87) -> 3543.3654
B88: Total revenue ($mm) | F88: =F86+F87 -> 2127.553 | G88: =G86+G87 -> 2517.497 | H88: =H86+H87 -> 2938.142 | I88: =I86+I87 -> 2244.4 | J88: =J86+J87 -> 2331.221 | K88: =K86+K87 -> 2640.544 | L88: =L86+L87 -> 2850.6592 | M88: =M86+M87 -> 2143.929 | ... Q88: =Q86+Q87 -> 2234.0639 | S88: =SUM(F88:I88) -> 9827.592 | T88: =SUM(J88:M88) -> 9966.3532 | U88: =SUM(N88:Q88) -> 10098.441
B89: Commissions, transportation and other ($mm) | F89: =F86*F81 -> 395.343 | G89: =G86*G81 -> 487.835 | H89: =H86*H81 -> 521.981 | I89: =I86*I81 -> 376.845 | J89: =J86*J81 -> 397.605 | K89: =K86*K81 -> 484.668 | L89: =L86*L81 -> 493.63324 | M89: =M86*M81 -> 357.94172 | ... Q89: =Q86*Q81 -> 374.6284 | S89: =SUM(F89:I89) -> 1782.004 | T89: =SUM(J89:M89) -> 1733.848 | U89: =SUM(N89:Q89) -> 1793.6109
B90: Onboard and other expense ($mm) | F90: =F87*F82 -> 138.858 | G90: =G87*G82 -> 187.684 | H90: =H87*H82 -> 222.002 | I90: =I87*I82 -> 140.18 | J90: =J87*J82 -> 151.868 | K90: =K87*K82 -> 191.446 | L90: =L87*L82 -> 239.11761 | M90: =M87*M82 -> 144.99048 | ... Q90: =Q87*Q82 -> 155.12321 | S90: =SUM(F90:I90) -> 688.724 | T90: =SUM(J90:M90) -> 727.42208 | U90: =SUM(N90:Q90) -> 755.36955
B91: Adjusted gross margin ($mm) | F91: =F88-F89-F90 -> 1593.352 | G91: =G88-G89-G90 -> 1841.978 | H91: =H88-H89-H90 -> 2194.159 | I91: =I88-I89-I90 -> 1727.375 | J91: =J88-J89-J90 -> 1781.748 | K91: =K88-K89-K90 -> 1964.43 | L91: =L88-L89-L90 -> 2117.9084 | M91: =M88-M89-M90 -> 1640.9968 | ... Q91: =Q88-Q89-Q90 -> 1704.3123 | S91: =SUM(F91:I91) -> 7356.864 | T91: =SUM(J91:M91) -> 7505.0832 | U91: =SUM(N91:Q91) -> 7549.461
B93: Selected case (feeds the Operating Model)
B94: Capacity days (M) | F94: =CHOOSE(DCF!$C$9,F19,F46,F73) -> 5.7006 | G94: =CHOOSE(DCF!$C$9,G19,G46,G73) -> 6.0523 | H94: =CHOOSE(DCF!$C$9,H19,H46,H73) -> 6.4176 | I94: =CHOOSE(DCF!$C$9,I19,I46,I73) -> 6.2631 | J94: =CHOOSE(DCF!$C$9,J19,J46,J73) -> 6.393 | K94: =CHOOSE(DCF!$C$9,K19,K46,K73) -> 6.5897 | L94: =CHOOSE(DCF!$C$9,L19,L46,L73) -> 6.7998964 | M94: =CHOOSE(DCF!$C$9,M19,M46,M73) -> 6.4672771 | ... Q94: =CHOOSE(DCF!$C$9,Q19,Q46,Q73) -> 6.7895511 | S94: =CHOOSE(DCF!$C$9,S19,S46,S73) -> 24.4336 | T94: =CHOOSE(DCF!$C$9,T19,T46,T73) -> 26.249873 | U94: =CHOOSE(DCF!$C$9,U19,U46,U73) -> 27.121933
B95: Occupancy | F95: =CHOOSE(DCF!$C$9,F20,F47,F74) -> 1.0151914 | G95: =CHOOSE(DCF!$C$9,G20,G47,G74) -> 1.0390761 | H95: =CHOOSE(DCF!$C$9,H20,H47,H74) -> 1.0639959 | I95: =CHOOSE(DCF!$C$9,I20,I47,I74) -> 1.0177229 | J95: =CHOOSE(DCF!$C$9,J20,J47,J74) -> 1.0377757 | K95: =CHOOSE(DCF!$C$9,K20,K47,K74) -> 1.0237188 | L95: =CHOOSE(DCF!$C$9,L20,L47,L74) -> 1.0399959 | M95: =CHOOSE(DCF!$C$9,M20,M47,M74) -> 0.98972285 | ... Q95: =CHOOSE(DCF!$C$9,Q20,Q47,Q74) -> 0.99972285 | S95: =CHOOSE(DCF!$C$9,S20,S47,S74) -> 1.0345753 | T95: =CHOOSE(DCF!$C$9,T20,T47,T74) -> 1.0229831 | U95: =CHOOSE(DCF!$C$9,U20,U47,U74) -> 1.0206424
B96: Passenger cruise days (M) | F96: =CHOOSE(DCF!$C$9,F21,F48,F75) -> 5.7872 | G96: =CHOOSE(DCF!$C$9,G21,G48,G75) -> 6.2888 | H96: =CHOOSE(DCF!$C$9,H21,H48,H75) -> 6.8283 | I96: =CHOOSE(DCF!$C$9,I21,I48,I75) -> 6.3741 | J96: =CHOOSE(DCF!$C$9,J21,J48,J75) -> 6.6345 | K96: =CHOOSE(DCF!$C$9,K21,K48,K75) -> 6.746 | L96: =CHOOSE(DCF!$C$9,L21,L48,L75) -> 7.0718643 | M96: =CHOOSE(DCF!$C$9,M21,M48,M75) -> 6.4008119 | ... Q96: =CHOOSE(DCF!$C$9,Q21,Q48,Q75) -> 6.7876694 | S96: =CHOOSE(DCF!$C$9,S21,S48,S75) -> 25.2784 | T96: =CHOOSE(DCF!$C$9,T21,T48,T75) -> 26.853176 | U96: =CHOOSE(DCF!$C$9,U21,U48,U75) -> 27.681795
B97: Ticket revenue per passenger day | F97: =CHOOSE(DCF!$C$9,F25,F52,F79) -> 245.14169 | G97: =CHOOSE(DCF!$C$9,G25,G52,G79) -> 271.75057 | H97: =CHOOSE(DCF!$C$9,H25,H52,H79) -> 300.21513 | I97: =CHOOSE(DCF!$C$9,I25,I52,I79) -> 236.90231 | J97: =CHOOSE(DCF!$C$9,J25,J52,J79) -> 232.46982 | K97: =CHOOSE(DCF!$C$9,K25,K52,K79) -> 256.42425 | L97: =CHOOSE(DCF!$C$9,L25,L52,L79) -> 270.04351 | M97: =CHOOSE(DCF!$C$9,M25,M52,M79) -> 220.03486 | ... Q97: =CHOOSE(DCF!$C$9,Q25,Q52,Q79) -> 220.54767 | S97: =CHOOSE(DCF!$C$9,S25,S52,S79) -> 264.56053 | T97: =CHOOSE(DCF!$C$9,T25,T52,T79) -> 245.41871 | U97: =CHOOSE(DCF!$C$9,U25,U52,U79) -> 243.98634
B98: Onboard revenue per passenger day | F98: =CHOOSE(DCF!$C$9,F26,F53,F80) -> 122.48911 | G98: =CHOOSE(DCF!$C$9,G26,G53,G80) -> 128.5638 | H98: =CHOOSE(DCF!$C$9,H26,H53,H80) -> 130.07381 | I98: =CHOOSE(DCF!$C$9,I26,I53,I80) -> 115.21015 | J98: =CHOOSE(DCF!$C$9,J26,J53,J80) -> 118.90873 | K98: =CHOOSE(DCF!$C$9,K26,K53,K80) -> 134.99941 | L98: =CHOOSE(DCF!$C$9,L26,L53,L80) -> 135.27676 | M98: =CHOOSE(DCF!$C$9,M26,M53,M80) -> 118.66645 | ... Q98: =CHOOSE(DCF!$C$9,Q26,Q53,Q80) -> 121.03978 | S98: =CHOOSE(DCF!$C$9,S26,S53,S80) -> 124.21376 | T98: =CHOOSE(DCF!$C$9,T26,T53,T80) -> 127.20382 | U98: =CHOOSE(DCF!$C$9,U26,U53,U80) -> 129.54003
B99: Commissions/transport % of ticket | F99: =CHOOSE(DCF!$C$9,F27,F54,F81) -> 0.27866882 | G99: =CHOOSE(DCF!$C$9,G27,G54,G81) -> 0.28545306 | H99: =CHOOSE(DCF!$C$9,H27,H54,H81) -> 0.25462997 | I99: =CHOOSE(DCF!$C$9,I27,I54,I81) -> 0.24955978 | J99: =CHOOSE(DCF!$C$9,J27,J54,J81) -> 0.25779653 | K99: =CHOOSE(DCF!$C$9,K27,K54,K81) -> 0.28018115 | L99: =CHOOSE(DCF!$C$9,L27,L54,L81) -> 0.26062997 | M99: =CHOOSE(DCF!$C$9,M27,M54,M81) -> 0.25855978 | ... Q99: =CHOOSE(DCF!$C$9,Q27,Q54,Q81) -> 0.26355928 | S99: =CHOOSE(DCF!$C$9,S27,S54,S81) -> 0.26646123 | T99: =CHOOSE(DCF!$C$9,T27,T54,T81) -> 0.2646563 | U99: =CHOOSE(DCF!$C$9,U27,U54,U81) -> 0.27352164
B100: Onboard costs % of onboard revenue | F100: =CHOOSE(DCF!$C$9,F28,F55,F82) -> 0.19588669 | G100: =CHOOSE(DCF!$C$9,G28,G55,G82) -> 0.23213508 | H100: =CHOOSE(DCF!$C$9,H28,H55,H82) -> 0.24995074 | I100: =CHOOSE(DCF!$C$9,I28,I55,I82) -> 0.19088704 | J100: =CHOOSE(DCF!$C$9,J28,J55,J82) -> 0.19250602 | K100: =CHOOSE(DCF!$C$9,K28,K55,K82) -> 0.21021713 | L100: =CHOOSE(DCF!$C$9,L28,L55,L82) -> 0.24995074 | M100: =CHOOSE(DCF!$C$9,M28,M55,M82) -> 0.19088704 | ... Q100: =CHOOSE(DCF!$C$9,Q28,Q55,Q82) -> 0.19088704 | S100: =CHOOSE(DCF!$C$9,S28,S55,S82) -> 0.21934409 | T100: =CHOOSE(DCF!$C$9,T28,T55,T82) -> 0.21295639 | U100: =CHOOSE(DCF!$C$9,U28,U55,U82) -> 0.21315321
B101: Net per diem | F101: =CHOOSE(DCF!$C$9,F29,F56,F83) -> 275.32347 | G101: =CHOOSE(DCF!$C$9,G29,G56,G83) -> 292.89817 | H101: =CHOOSE(DCF!$C$9,H29,H56,H83) -> 321.33313 | I101: =CHOOSE(DCF!$C$9,I29,I56,I83) -> 270.99904 | J101: =CHOOSE(DCF!$C$9,J29,J56,J83) -> 268.55799 | K101: =CHOOSE(DCF!$C$9,K29,K56,K83) -> 291.19923 | L101: =CHOOSE(DCF!$C$9,L29,L56,L83) -> 301.12632 | M101: =CHOOSE(DCF!$C$9,M29,M56,M83) -> 259.15726 | ... Q101: =CHOOSE(DCF!$C$9,Q29,Q56,Q83) -> 260.35514 | S101: =CHOOSE(DCF!$C$9,S29,S56,S83) -> 291.03361 | T101: =CHOOSE(DCF!$C$9,T29,T56,T83) -> 280.58205 | U101: =CHOOSE(DCF!$C$9,U29,U56,U83) -> 279.17896
B102: NET YIELD ($ per capacity day) | F102: =CHOOSE(DCF!$C$9,F30,F57,F84) -> 279.50602 | G102: =CHOOSE(DCF!$C$9,G30,G57,G84) -> 304.34347 | H102: =CHOOSE(DCF!$C$9,H30,H57,H84) -> 341.89713 | I102: =CHOOSE(DCF!$C$9,I30,I57,I84) -> 275.80192 | J102: =CHOOSE(DCF!$C$9,J30,J57,J84) -> 278.70296 | K102: =CHOOSE(DCF!$C$9,K30,K57,K84) -> 298.10614 | L102: =CHOOSE(DCF!$C$9,L30,L57,L84) -> 313.17013 | M102: =CHOOSE(DCF!$C$9,M30,M57,M84) -> 256.49386 | ... Q102: =CHOOSE(DCF!$C$9,Q30,Q57,Q84) -> 260.28298 | S102: =CHOOSE(DCF!$C$9,S30,S57,S84) -> 301.0962 | T102: =CHOOSE(DCF!$C$9,T30,T57,T84) -> 287.03069 | U102: =CHOOSE(DCF!$C$9,U30,U57,U84) -> 284.94188
B103: Net yield y/y | J103: =CHOOSE(DCF!$C$9,J31,J58,J85) -> -0.0028731423 | K103: =CHOOSE(DCF!$C$9,K31,K58,K85) -> -0.020494402 | L103: =CHOOSE(DCF!$C$9,L31,L58,L85) -> -0.084022341 | M103: =CHOOSE(DCF!$C$9,M31,M58,M85) -> -0.070006965 | N103: =CHOOSE(DCF!$C$9,N31,N58,N85) -> -0.034691082 | O103: =CHOOSE(DCF!$C$9,O31,O58,O85) -> -0.017589168 | P103: =CHOOSE(DCF!$C$9,P31,P58,P85) -> 0.0085040694 | Q103: =CHOOSE(DCF!$C$9,Q31,Q58,Q85) -> 0.014772734 | S103: =CHOOSE(DCF!$C$9,S31,S58,S85) -> 0.022992852 | T103: =CHOOSE(DCF!$C$9,T31,T58,T85) -> -0.046714321 | U103: =CHOOSE(DCF!$C$9,U31,U58,U85) -> -0.0072773132
B104: Passenger ticket revenue ($mm) | F104: =CHOOSE(DCF!$C$9,F32,F59,F86) -> 1418.684 | G104: =CHOOSE(DCF!$C$9,G32,G59,G86) -> 1708.985 | H104: =CHOOSE(DCF!$C$9,H32,H59,H86) -> 2049.959 | I104: =CHOOSE(DCF!$C$9,I32,I59,I86) -> 1510.039 | J104: =CHOOSE(DCF!$C$9,J32,J59,J86) -> 1542.321 | K104: =CHOOSE(DCF!$C$9,K32,K59,K86) -> 1729.838 | L104: =CHOOSE(DCF!$C$9,L32,L59,L86) -> 1909.7111 | M104: =CHOOSE(DCF!$C$9,M32,M59,M86) -> 1408.4018 | ... Q104: =CHOOSE(DCF!$C$9,Q32,Q59,Q86) -> 1497.0046 | S104: =CHOOSE(DCF!$C$9,S32,S59,S86) -> 6687.667 | T104: =CHOOSE(DCF!$C$9,T32,T59,T86) -> 6590.2719 | U104: =CHOOSE(DCF!$C$9,U32,U59,U86) -> 6753.9799
B105: Onboard and other revenue ($mm) | F105: =CHOOSE(DCF!$C$9,F33,F60,F87) -> 708.869 | G105: =CHOOSE(DCF!$C$9,G33,G60,G87) -> 808.512 | H105: =CHOOSE(DCF!$C$9,H33,H60,H87) -> 888.183 | I105: =CHOOSE(DCF!$C$9,I33,I60,I87) -> 734.361 | J105: =CHOOSE(DCF!$C$9,J33,J60,J87) -> 788.9 | K105: =CHOOSE(DCF!$C$9,K33,K60,K87) -> 910.706 | L105: =CHOOSE(DCF!$C$9,L33,L60,L87) -> 956.65891 | M105: =CHOOSE(DCF!$C$9,M33,M60,M87) -> 759.56164 | ... Q105: =CHOOSE(DCF!$C$9,Q33,Q60,Q87) -> 821.57802 | S105: =CHOOSE(DCF!$C$9,S33,S60,S87) -> 3139.925 | T105: =CHOOSE(DCF!$C$9,T33,T60,T87) -> 3415.8265 | U105: =CHOOSE(DCF!$C$9,U33,U60,U87) -> 3585.9006
B106: Total revenue ($mm) | F106: =CHOOSE(DCF!$C$9,F34,F61,F88) -> 2127.553 | G106: =CHOOSE(DCF!$C$9,G34,G61,G88) -> 2517.497 | H106: =CHOOSE(DCF!$C$9,H34,H61,H88) -> 2938.142 | I106: =CHOOSE(DCF!$C$9,I34,I61,I88) -> 2244.4 | J106: =CHOOSE(DCF!$C$9,J34,J61,J88) -> 2331.221 | K106: =CHOOSE(DCF!$C$9,K34,K61,K88) -> 2640.544 | L106: =CHOOSE(DCF!$C$9,L34,L61,L88) -> 2866.37 | M106: =CHOOSE(DCF!$C$9,M34,M61,M88) -> 2167.9634 | ... Q106: =CHOOSE(DCF!$C$9,Q34,Q61,Q88) -> 2318.5827 | S106: =CHOOSE(DCF!$C$9,S34,S61,S88) -> 9827.592 | T106: =CHOOSE(DCF!$C$9,T34,T61,T88) -> 10006.098 | U106: =CHOOSE(DCF!$C$9,U34,U61,U88) -> 10339.88
...

Sheet KPI 1 Price Build
B2: KPI 1 Price Build (Thesis 1): fare cuts on unsold cabins -> ticket revenue per passenger day
B3: Thesis 1: NCL is cutting prices to fill Caribbean ships because it is losing share there. The fare panel measures the cuts; this sheet applies them only to cabins NCL still has to sell, by brand and region. Output (section E) feeds the Net Yield Build.
C5: Logic / source | D5: 3Q26E | E5: 4Q26E | F5: 1Q27E | G5: 2Q27E | H5: 3Q27E | I5: 4Q27E
B6: Fare-panel sailing window | D6: sailed | E6: Q4 2026 | F6: 1H 2027 | G6: 1H 2027 | H6: 2H 2027 | I6: 2H 2027
B7: Months from Oct 2, 2026 to mid-quarter sailing | D7: 0 | E7: 1.5 | F7: 4.5 | G7: 7.5 | H7: 10.5 | I7: 13.5
B9: A. Where NCLH capacity sails
B10: NCLH Caribbean share of capacity (deployment estimate) | C10: Team estimate from published itinerary schedules | D10: 0.18 | E10: 0.5 | F10: 0.62 | G10: 0.38 | H10: 0.2 | I10: 0.48
B11: Oceania + Regent share of NCLH capacity | C11: Fleet Qtr Build row 11 | D11: ='Fleet Qtr Build'!J11 -> 0.1558885 | E11: ='Fleet Qtr Build'!K11 -> 0.1602809 | F11: ='Fleet Qtr Build'!L11 -> 0.16954423 | G11: ='Fleet Qtr Build'!M11 -> 0.16673483 | H11: ='Fleet Qtr Build'!N11 -> 0.17116326 | I11: ='Fleet Qtr Build'!O11 -> 0.17527449
B12: Oceania + Regent: Caribbean share of their itineraries | C12: Fare Panel A: itinerary counts in the window | D12: =IF(D$6="sailed",0,(SUMIFS('Fare Panel'!$E$8:$E$114,'Fare Panel'!$B$8:$B$114,"Oceania",'Fare Panel'!$C$8:$C$114,"Caribbean/Bahamas",'Fare Panel'!$D$8:$D$114,D$6)+SUMIFS('Fare Panel'!$E$8:$E$114,'Fare Panel'!$B$8:$B$114,"Regent Seven Seas",'Fare Panel'!$C$8:$C$114,"Caribbean/Bahamas",'Fare Panel'!$D$8:$D$114,D$6))/(SUMIFS('Fare Panel'!$E$8:$E$114,'Fare Panel'!$B$8:$B$114,"Oceania",'Fare Panel'!$D$8:$D$114,D$6)+SUMIFS('Fare Panel'!$E$8:$E$114,'Fare Panel'!$B$8:$B$114,"Regent Seven Seas",'Fare Panel'!$D$8:$D$114,D$6))) -> 0 | E12: =IF(E$6="sailed",0,(SUMIFS('Fare Panel'!$E$8:$E$114,'Fare Panel'!$B$8:$B$114,"Oceania",'Fare Panel'!$C$8:$C$114,"Caribbean/Bahamas",'Fare Panel'!$D$8:$D$114,E$6)+SUMIFS('Fare Panel'!$E$8:$E$114,'Fare Panel'!$B$8:$B$114,"Regent Seven Seas",'Fare Panel'!$C$8:$C$114,"Caribbean/Bahamas",'Fare Panel'!$D$8:$D$114,E$6))/(SUMIFS('Fare Panel'!$E$8:$E$114,'Fare Panel'!$B$8:$B$114,"Oceania",'Fare Panel'!$D$8:$D$114,E$6)+SUMIFS('Fare Panel'!$E$8:$E$114,'Fare Panel'!$B$8:$B$114,"Regent Seven Seas",'Fare Panel'!$D$8:$D$114,E$6))) -> 0.36363636 | F12: =IF(F$6="sailed",0,(SUMIFS('Fare Panel'!$E$8:$E$114,'Fare Panel'!$B$8:$B$114,"Oceania",'Fare Panel'!$C$8:$C$114,"Caribbean/Bahamas",'Fare Panel'!$D$8:$D$114,F$6)+SUMIFS('Fare Panel'!$E$8:$E$114,'Fare Panel'!$B$8:$B$114,"Regent Seven Seas",'Fare Panel'!$C$8:$C$114,"Caribbean/Bahamas",'Fare Panel'!$D$8:$D$114,F$6))/(SUMIFS('Fare Panel'!$E$8:$E$114,'Fare Panel'!$B$8:$B$114,"Oceania",'Fare Panel'!$D$8:$D$114,F$6)+SUMIFS('Fare Panel'!$E$8:$E$114,'Fare Panel'!$B$8:$B$114,"Regent Seven Seas",'Fare Panel'!$D$8:$D$114,F$6))) -> 0.052631579 | G12: =IF(G$6="sailed",0,(SUMIFS('Fare Panel'!$E$8:$E$114,'Fare Panel'!$B$8:$B$114,"Oceania",'Fare Panel'!$C$8:$C$114,"Caribbean/Bahamas",'Fare Panel'!$D$8:$D$114,G$6)+SUMIFS('Fare Panel'!$E$8:$E$114,'Fare Panel'!$B$8:$B$114,"Regent Seven Seas",'Fare Panel'!$C$8:$C$114,"Caribbean/Bahamas",'Fare Panel'!$D$8:$D$114,G$6))/(SUMIFS('Fare Panel'!$E$8:$E$114,'Fare Panel'!$B$8:$B$114,"Oceania",'Fare Panel'!$D$8:$D$114,G$6)+SUMIFS('Fare Panel'!$E$8:$E$114,'Fare Panel'!$B$8:$B$114,"Regent Seven Seas",'Fare Panel'!$D$8:$D$114,G$6))) -> 0.052631579 | H12: =IF(H$6="sailed",0,(SUMIFS('Fare Panel'!$E$8:$E$114,'Fare Panel'!$B$8:$B$114,"Oceania",'Fare Panel'!$C$8:$C$114,"Caribbean/Bahamas",'Fare Panel'!$D$8:$D$114,H$6)+SUMIFS('Fare Panel'!$E$8:$E$114,'Fare Panel'!$B$8:$B$114,"Regent Seven Seas",'Fare Panel'!$C$8:$C$114,"Caribbean/Bahamas",'Fare Panel'!$D$8:$D$114,H$6))/(SUMIFS('Fare Panel'!$E$8:$E$114,'Fare Panel'!$B$8:$B$114,"Oceania",'Fare Panel'!$D$8:$D$114,H$6)+SUMIFS('Fare Panel'!$E$8:$E$114,'Fare Panel'!$B$8:$B$114,"Regent Seven Seas",'Fare Panel'!$D$8:$D$114,H$6))) -> 0.11111111 | I12: =IF(I$6="sailed",0,(SUMIFS('Fare Panel'!$E$8:$E$114,'Fare Panel'!$B$8:$B$114,"Oceania",'Fare Panel'!$C$8:$C$114,"Caribbean/Bahamas",'Fare Panel'!$D$8:$D$114,I$6)+SUMIFS('Fare Panel'!$E$8:$E$114,'Fare Panel'!$B$8:$B$114,"Regent Seven Seas",'Fare Panel'!$C$8:$C$114,"Caribbean/Bahamas",'Fare Panel'!$D$8:$D$114,I$6))/(SUMIFS('Fare Panel'!$E$8:$E$114,'Fare Panel'!$B$8:$B$114,"Oceania",'Fare Panel'!$D$8:$D$114,I$6)+SUMIFS('Fare Panel'!$E$8:$E$114,'Fare Panel'!$B$8:$B$114,"Regent Seven Seas",'Fare Panel'!$D$8:$D$114,I$6))) -> 0.11111111
B13: NCL brand: Caribbean share of its capacity | C13: (NCLH share - luxury share x luxury Caribbean share) / NCL share | D13: =MIN(1,(D10-D11*D12)/(1-D11)) -> 0.21324197 | E13: =MIN(1,(E10-E11*E12)/(1-E11)) -> 0.52602833 | F13: =MIN(1,(F10-F11*F12)/(1-F11)) -> 0.73583283 | G13: =MIN(1,(G10-G11*G12)/(1-G11)) -> 0.44550582 | H13: =MIN(1,(H10-H11*H12)/(1-H11)) -> 0.21835646 | I13: =MIN(1,(I10-I11*I12)/(1-I11)) -> 0.55839798
B15: B. Observed fare change: median vs. each itinerary's own 90-day average (Oct 2, 2026)
B16: NCL: Caribbean | C16: Fare Panel A | D16: =IF(D$6="sailed",0,SUMIFS('Fare Panel'!$F$8:$F$114,'Fare Panel'!$B$8:$B$114,"Norwegian",'Fare Panel'!$C$8:$C$114,"Caribbean/Bahamas",'Fare Panel'!$D$8:$D$114,D$6)) -> 0 | E16: =IF(E$6="sailed",0,SUMIFS('Fare Panel'!$F$8:$F$114,'Fare Panel'!$B$8:$B$114,"Norwegian",'Fare Panel'!$C$8:$C$114,"Caribbean/Bahamas",'Fare Panel'!$D$8:$D$114,E$6)) -> -0.36 | F16: =IF(F$6="sailed",0,SUMIFS('Fare Panel'!$F$8:$F$114,'Fare Panel'!$B$8:$B$114,"Norwegian",'Fare Panel'!$C$8:$C$114,"Caribbean/Bahamas",'Fare Panel'!$D$8:$D$114,F$6)) -> -0.145 | G16: =IF(G$6="sailed",0,SUMIFS('Fare Panel'!$F$8:$F$114,'Fare Panel'!$B$8:$B$114,"Norwegian",'Fare Panel'!$C$8:$C$114,"Caribbean/Bahamas",'Fare Panel'!$D$8:$D$114,G$6)) -> -0.145 | H16: =IF(H$6="sailed",0,SUMIFS('Fare Panel'!$F$8:$F$114,'Fare Panel'!$B$8:$B$114,"Norwegian",'Fare Panel'!$C$8:$C$114,"Caribbean/Bahamas",'Fare Panel'!$D$8:$D$114,H$6)) -> -0.02 | I16: =IF(I$6="sailed",0,SUMIFS('Fare Panel'!$F$8:$F$114,'Fare Panel'!$B$8:$B$114,"Norwegian",'Fare Panel'!$C$8:$C$114,"Caribbean/Bahamas",'Fare Panel'!$D$8:$D$114,I$6)) -> -0.02
B17: NCL: Europe, Alaska and other (itinerary-weighted) | C17: Fare Panel A | D17: =IF(D$6="sailed",0,SUMPRODUCT(('Fare Panel'!$B$8:$B$114="Norwegian")*('Fare Panel'!$C$8:$C$114<>"Caribbean/Bahamas")*('Fare Panel'!$D$8:$D$114=D$6)*'Fare Panel'!$E$8:$E$114*'Fare Panel'!$F$8:$F$114)/SUMPRODUCT(('Fare Panel'!$B$8:$B$114="Norwegian")*('Fare Panel'!$C$8:$C$114<>"Caribbean/Bahamas")*('Fare Panel'!$D$8:$D$114=D$6)*'Fare Panel'!$E$8:$E$114)) -> 0 | E17: =IF(E$6="sailed",0,SUMPRODUCT(('Fare Panel'!$B$8:$B$114="Norwegian")*('Fare Panel'!$C$8:$C$114<>"Caribbean/Bahamas")*('Fare Panel'!$D$8:$D$114=E$6)*'Fare Panel'!$E$8:$E$114*'Fare Panel'!$F$8:$F$114)/SUMPRODUCT(('Fare Panel'!$B$8:$B$114="Norwegian")*('Fare Panel'!$C$8:$C$114<>"Caribbean/Bahamas")*('Fare Panel'!$D$8:$D$114=E$6)*'Fare Panel'!$E$8:$E$114)) -> -0.13434783 | F17: =IF(F$6="sailed",0,SUMPRODUCT(('Fare Panel'!$B$8:$B$114="Norwegian")*('Fare Panel'!$C$8:$C$114<>"Caribbean/Bahamas")*('Fare Panel'!$D$8:$D$114=F$6)*'Fare Panel'!$E$8:$E$114*'Fare Panel'!$F$8:$F$114)/SUMPRODUCT(('Fare Panel'!$B$8:$B$114="Norwegian")*('Fare Panel'!$C$8:$C$114<>"Caribbean/Bahamas")*('Fare Panel'!$D$8:$D$114=F$6)*'Fare Panel'!$E$8:$E$114)) -> -0.028461538 | G17: =IF(G$6="sailed",0,SUMPRODUCT(('Fare Panel'!$B$8:$B$114="Norwegian")*('Fare Panel'!$C$8:$C$114<>"Caribbean/Bahamas")*('Fare Panel'!$D$8:$D$114=G$6)*'Fare Panel'!$E$8:$E$114*'Fare Panel'!$F$8:$F$114)/SUMPRODUCT(('Fare Panel'!$B$8:$B$114="Norwegian")*('Fare Panel'!$C$8:$C$114<>"Caribbean/Bahamas")*('Fare Panel'!$D$8:$D$114=G$6)*'Fare Panel'!$E$8:$E$114)) -> -0.028461538 | H17: =IF(H$6="sailed",0,SUMPRODUCT(('Fare Panel'!$B$8:$B$114="Norwegian")*('Fare Panel'!$C$8:$C$114<>"Caribbean/Bahamas")*('Fare Panel'!$D$8:$D$114=H$6)*'Fare Panel'!$E$8:$E$114*'Fare Panel'!$F$8:$F$114)/SUMPRODUCT(('Fare Panel'!$B$8:$B$114="Norwegian")*('Fare Panel'!$C$8:$C$114<>"Caribbean/Bahamas")*('Fare Panel'!$D$8:$D$114=H$6)*'Fare Panel'!$E$8:$E$114)) -> -0.003 | I17: =IF(I$6="sailed",0,SUMPRODUCT(('Fare Panel'!$B$8:$B$114="Norwegian")*('Fare Panel'!$C$8:$C$114<>"Caribbean/Bahamas")*('Fare Panel'!$D$8:$D$114=I$6)*'Fare Panel'!$E$8:$E$114*'Fare Panel'!$F$8:$F$114)/SUMPRODUCT(('Fare Panel'!$B$8:$B$114="Norwegian")*('Fare Panel'!$C$8:$C$114<>"Caribbean/Bahamas")*('Fare Panel'!$D$8:$D$114=I$6)*'Fare Panel'!$E$8:$E$114)) -> -0.003
B18: Oceania and Regent: all regions (itinerary-weighted) | C18: Fare Panel A | D18: =IF(D$6="sailed",0,SUMPRODUCT((('Fare Panel'!$B$8:$B$114="Oceania")+('Fare Panel'!$B$8:$B$114="Regent Seven Seas"))*('Fare Panel'!$D$8:$D$114=D$6)*'Fare Panel'!$E$8:$E$114*'Fare Panel'!$F$8:$F$114)/SUMPRODUCT((('Fare Panel'!$B$8:$B$114="Oceania")+('Fare Panel'!$B$8:$B$114="Regent Seven Seas"))*('Fare Panel'!$D$8:$D$114=D$6)*'Fare Panel'!$E$8:$E$114)) -> 0 | E18: =IF(E$6="sailed",0,SUMPRODUCT((('Fare Panel'!$B$8:$B$114="Oceania")+('Fare Panel'!$B$8:$B$114="Regent Seven Seas"))*('Fare Panel'!$D$8:$D$114=E$6)*'Fare Panel'!$E$8:$E$114*'Fare Panel'!$F$8:$F$114)/SUMPRODUCT((('Fare Panel'!$B$8:$B$114="Oceania")+('Fare Panel'!$B$8:$B$114="Regent Seven Seas"))*('Fare Panel'!$D$8:$D$114=E$6)*'Fare Panel'!$E$8:$E$114)) -> 0 | F18: =IF(F$6="sailed",0,SUMPRODUCT((('Fare Panel'!$B$8:$B$114="Oceania")+('Fare Panel'!$B$8:$B$114="Regent Seven Seas"))*('Fare Panel'!$D$8:$D$114=F$6)*'Fare Panel'!$E$8:$E$114*'Fare Panel'!$F$8:$F$114)/SUMPRODUCT((('Fare Panel'!$B$8:$B$114="Oceania")+('Fare Panel'!$B$8:$B$114="Regent Seven Seas"))*('Fare Panel'!$D$8:$D$114=F$6)*'Fare Panel'!$E$8:$E$114)) -> 0 | G18: =IF(G$6="sailed",0,SUMPRODUCT((('Fare Panel'!$B$8:$B$114="Oceania")+('Fare Panel'!$B$8:$B$114="Regent Seven Seas"))*('Fare Panel'!$D$8:$D$114=G$6)*'Fare Panel'!$E$8:$E$114*'Fare Panel'!$F$8:$F$114)/SUMPRODUCT((('Fare Panel'!$B$8:$B$114="Oceania")+('Fare Panel'!$B$8:$B$114="Regent Seven Seas"))*('Fare Panel'!$D$8:$D$114=G$6)*'Fare Panel'!$E$8:$E$114)) -> 0 | H18: =IF(H$6="sailed",0,SUMPRODUCT((('Fare Panel'!$B$8:$B$114="Oceania")+('Fare Panel'!$B$8:$B$114="Regent Seven Seas"))*('Fare Panel'!$D$8:$D$114=H$6)*'Fare Panel'!$E$8:$E$114*'Fare Panel'!$F$8:$F$114)/SUMPRODUCT((('Fare Panel'!$B$8:$B$114="Oceania")+('Fare Panel'!$B$8:$B$114="Regent Seven Seas"))*('Fare Panel'!$D$8:$D$114=H$6)*'Fare Panel'!$E$8:$E$114)) -> 0 | I18: =IF(I$6="sailed",0,SUMPRODUCT((('Fare Panel'!$B$8:$B$114="Oceania")+('Fare Panel'!$B$8:$B$114="Regent Seven Seas"))*('Fare Panel'!$D$8:$D$114=I$6)*'Fare Panel'!$E$8:$E$114*'Fare Panel'!$F$8:$F$114)/SUMPRODUCT((('Fare Panel'!$B$8:$B$114="Oceania")+('Fare Panel'!$B$8:$B$114="Regent Seven Seas"))*('Fare Panel'!$D$8:$D$114=I$6)*'Fare Panel'!$E$8:$E$114)) -> 0
B19: Memo: Royal Caribbean and Carnival, Caribbean (average) | C19: Fare Panel A | D19: =IF(D$6="sailed",0,AVERAGE(SUMIFS('Fare Panel'!$F$8:$F$114,'Fare Panel'!$B$8:$B$114,"Royal Caribbean",'Fare Panel'!$C$8:$C$114,"Caribbean/Bahamas",'Fare Panel'!$D$8:$D$114,D$6),SUMIFS('Fare Panel'!$F$8:$F$114,'Fare Panel'!$B$8:$B$114,"Carnival",'Fare Panel'!$C$8:$C$114,"Caribbean/Bahamas",'Fare Panel'!$D$8:$D$114,D$6))) -> 0 | E19: =IF(E$6="sailed",0,AVERAGE(SUMIFS('Fare Panel'!$F$8:$F$114,'Fare Panel'!$B$8:$B$114,"Royal Caribbean",'Fare Panel'!$C$8:$C$114,"Caribbean/Bahamas",'Fare Panel'!$D$8:$D$114,E$6),SUMIFS('Fare Panel'!$F$8:$F$114,'Fare Panel'!$B$8:$B$114,"Carnival",'Fare Panel'!$C$8:$C$114,"Caribbean/Bahamas",'Fare Panel'!$D$8:$D$114,E$6))) -> -0.03 | F19: =IF(F$6="sailed",0,AVERAGE(SUMIFS('Fare Panel'!$F$8:$F$114,'Fare Panel'!$B$8:$B$114,"Royal Caribbean",'Fare Panel'!$C$8:$C$114,"Caribbean/Bahamas",'Fare Panel'!$D$8:$D$114,F$6),SUMIFS('Fare Panel'!$F$8:$F$114,'Fare Panel'!$B$8:$B$114,"Carnival",'Fare Panel'!$C$8:$C$114,"Caribbean/Bahamas",'Fare Panel'!$D$8:$D$114,F$6))) -> -0.005 | G19: =IF(G$6="sailed",0,AVERAGE(SUMIFS('Fare Panel'!$F$8:$F$114,'Fare Panel'!$B$8:$B$114,"Royal Caribbean",'Fare Panel'!$C$8:$C$114,"Caribbean/Bahamas",'Fare Panel'!$D$8:$D$114,G$6),SUMIFS('Fare Panel'!$F$8:$F$114,'Fare Panel'!$B$8:$B$114,"Carnival",'Fare Panel'!$C$8:$C$114,"Caribbean/Bahamas",'Fare Panel'!$D$8:$D$114,G$6))) -> -0.005 | H19: =IF(H$6="sailed",0,AVERAGE(SUMIFS('Fare Panel'!$F$8:$F$114,'Fare Panel'!$B$8:$B$114,"Royal Caribbean",'Fare Panel'!$C$8:$C$114,"Caribbean/Bahamas",'Fare Panel'!$D$8:$D$114,H$6),SUMIFS('Fare Panel'!$F$8:$F$114,'Fare Panel'!$B$8:$B$114,"Carnival",'Fare Panel'!$C$8:$C$114,"Caribbean/Bahamas",'Fare Panel'!$D$8:$D$114,H$6))) -> 0 | I19: =IF(I$6="sailed",0,AVERAGE(SUMIFS('Fare Panel'!$F$8:$F$114,'Fare Panel'!$B$8:$B$114,"Royal Caribbean",'Fare Panel'!$C$8:$C$114,"Caribbean/Bahamas",'Fare Panel'!$D$8:$D$114,I$6),SUMIFS('Fare Panel'!$F$8:$F$114,'Fare Panel'!$B$8:$B$114,"Carnival",'Fare Panel'!$C$8:$C$114,"Caribbean/Bahamas",'Fare Panel'!$D$8:$D$114,I$6))) -> 0
B20: Memo: NCL Caribbean cut beyond its peers | D20: =D16-D19 -> 0 | E20: =E16-E19 -> -0.33 | F20: =F16-F19 -> -0.14 | G20: =G16-G19 -> -0.14 | H20: =H16-H19 -> -0.02 | I20: =I16-I19 -> -0.02
B22: C. Cabins still unsold at today's fares
B23: Booking curve: months before sailing | D23: 0-3 | E23: 3-6 | F23: 6-9 | G23: 9-12 | H23: 12-15
B24: Typical share of cabins already sold (industry curve) | C24: Industry booking curve (team, from line commentary) | D24: 0.85 | E24: 0.6 | F24: 0.5 | G24: 0.35 | H24: 0.25
B25: Typical share sold at this quarter's lead time | D25: =IF(D$6="sailed",1,IF(D7<=3,$D$24,IF(D7<=6,$E$24,IF(D7<=9,$F$24,IF(D7<=12,$G$24,$H$24))))) -> 1 | E25: =IF(E$6="sailed",1,IF(E7<=3,$D$24,IF(E7<=6,$E$24,IF(E7<=9,$F$24,IF(E7<=12,$G$24,$H$24))))) -> 0.85 | F25: =IF(F$6="sailed",1,IF(F7<=3,$D$24,IF(F7<=6,$E$24,IF(F7<=9,$F$24,IF(F7<=12,$G$24,$H$24))))) -> 0.6 | G25: =IF(G$6="sailed",1,IF(G7<=3,$D$24,IF(G7<=6,$E$24,IF(G7<=9,$F$24,IF(G7<=12,$G$24,$H$24))))) -> 0.5 | H25: =IF(H$6="sailed",1,IF(H7<=3,$D$24,IF(H7<=6,$E$24,IF(H7<=9,$F$24,IF(H7<=12,$G$24,$H$24))))) -> 0.35 | I25: =IF(I$6="sailed",1,IF(I7<=3,$D$24,IF(I7<=6,$E$24,IF(I7<=9,$F$24,IF(I7<=12,$G$24,$H$24))))) -> 0.25
B26: Booking shortfall in windows the panel already prices (KPI 2 build) | C26: Q4 2026 and 1H27 only; 2H27 shortfall is Thesis 2 | D26: =IF(OR(D$6="Q4 2026",D$6="1H 2027"),'KPI 2 Booking Build'!$D$11,0) -> 0 | E26: =IF(OR(E$6="Q4 2026",E$6="1H 2027"),'KPI 2 Booking Build'!$D$11,0) -> 0.05 | F26: =IF(OR(F$6="Q4 2026",F$6="1H 2027"),'KPI 2 Booking Build'!$D$11,0) -> 0.05 | G26: =IF(OR(G$6="Q4 2026",G$6="1H 2027"),'KPI 2 Booking Build'!$D$11,0) -> 0.05 | H26: =IF(OR(H$6="Q4 2026",H$6="1H 2027"),'KPI 2 Booking Build'!$D$11,0) -> 0 | I26: =IF(OR(I$6="Q4 2026",I$6="1H 2027"),'KPI 2 Booking Build'!$D$11,0) -> 0
B27: Share of cabins unsold at today's fares: base case | C27: 1 - typical share sold + shortfall | D27: =IF(D$6="sailed",0,1-D25+D26) -> 0 | E27: =IF(E$6="sailed",0,1-E25+E26) -> 0.2 | F27: =IF(F$6="sailed",0,1-F25+F26) -> 0.45 | G27: =IF(G$6="sailed",0,1-G25+G26) -> 0.55 | H27: =IF(H$6="sailed",0,1-H25+H26) -> 0.65 | I27: =IF(I$6="sailed",0,1-I25+I26) -> 0.75
B28: Same: consensus case | C28: Calibrated so the consensus case reproduces consensus 2027 EPS | D28: 0 | E28: 0.2 | F28: 0.25 | G28: 0.25 | H28: 0.25 | I28: 0.25
B29: Same: bear case | C29: Bear shortfall from KPI 2 build | D29: =IF(D$6="sailed",0,1-D25+IF(OR(D$6="Q4 2026",D$6="1H 2027"),'KPI 2 Booking Build'!$D$12,0)) -> 0 | E29: =IF(E$6="sailed",0,1-E25+IF(OR(E$6="Q4 2026",E$6="1H 2027"),'KPI 2 Booking Build'!$D$12,0)) -> 0.23 | F29: =IF(F$6="sailed",0,1-F25+IF(OR(F$6="Q4 2026",F$6="1H 2027"),'KPI 2 Booking Build'!$D$12,0)) -> 0.48 | G29: =IF(G$6="sailed",0,1-G25+IF(OR(G$6="Q4 2026",G$6="1H 2027"),'KPI 2 Booking Build'!$D$12,0)) -> 0.58 | H29: =IF(H$6="sailed",0,1-H25+IF(OR(H$6="Q4 2026",H$6="1H 2027"),'KPI 2 Booking Build'!$D$12,0)) -> 0.65 | I29: =IF(I$6="sailed",0,1-I25+IF(OR(I$6="Q4 2026",I$6="1H 2027"),'KPI 2 Booking Build'!$D$12,0)) -> 0.75
B30: Bear: share of the 1H27 Caribbean cut that carries into 2H27 sailings | D30: 0.5
B32: D. Weighting by brand (Oceania and Regent show no cuts)
B33: NCL brand share of NCLH ticket revenue | C33: Assumption; between the panel cross-check (row 36) and berth share (row 34) | D33: 0.65
B34: Cross-check: NCL brand share of 2027 berths (ceiling) | D34: ='Fleet Build'!K50/'Fleet Build'!K53 -> 0.82927457
B35: Cross-check: median lowest fare per night (NCL / Oceania / Regent) | D35: =SUMPRODUCT(('Fare Panel'!$B$8:$B$114="Norwegian")*'Fare Panel'!$E$8:$E$114*'Fare Panel'!$J$8:$J$114)/SUMIFS('Fare Panel'!$E$8:$E$114,'Fare Panel'!$B$8:$B$114,"Norwegian") -> 161.74425 | E35: =SUMPRODUCT(('Fare Panel'!$B$8:$B$114="Oceania")*'Fare Panel'!$E$8:$E$114*'Fare Panel'!$J$8:$J$114)/SUMIFS('Fare Panel'!$E$8:$E$114,'Fare Panel'!$B$8:$B$114,"Oceania") -> 387.81818 | F35: =SUMPRODUCT(('Fare Panel'!$B$8:$B$114="Regent Seven Seas")*'Fare Panel'!$E$8:$E$114*'Fare Panel'!$J$8:$J$114)/SUMIFS('Fare Panel'!$E$8:$E$114,'Fare Panel'!$B$8:$B$114,"Regent Seven Seas") -> 882.47222
B36: Cross-check: NCL share of ticket revenue implied by berths x panel fares | C36: Lowest fares overstate luxury weight (narrower cabin spread) | D36: ='Fleet Build'!K50*D35/('Fleet Build'!K50*D35+'Fleet Build'!K51*E35+'Fleet Build'!K52*F35) -> 0.57872488
B38: E. KPI 1 output: Thesis 1 effect on NCLH ticket revenue per passenger day (y/y)
B39: Base case | D39: =IF(D$6="sailed",0,$D$33*D27*(D13*D16+(1-D13)*D17)+(1-$D$33)*D27*D18) -> 0 | E39: =IF(E$6="sailed",0,$D$33*E27*(E13*E16+(1-E13)*E17)+(1-$D$33)*E27*E18) -> -0.032896144 | F39: =IF(F$6="sailed",0,$D$33*F27*(F13*F16+(1-F13)*F17)+(1-$D$33)*F27*F18) -> -0.033407702 | G39: =IF(G$6="sailed",0,$D$33*G27*(G13*G16+(1-G13)*G17)+(1-$D$33)*G27*G18) -> -0.028735886 | H39: =IF(H$6="sailed",0,$D$33*H27*(H13*H16+(1-H13)*H17)+(1-$D$33)*H27*H18) -> -0.0028358453 | I39: =IF(I$6="sailed",0,$D$33*I27*(I13*I16+(1-I13)*I17)+(1-$D$33)*I27*I18) -> -0.0060902232
B40: Consensus case | D40: =IF(D$6="sailed",0,$D$33*D28*(D13*D16+(1-D13)*D17)+(1-$D$33)*D28*D18) -> 0 | E40: =IF(E$6="sailed",0,$D$33*E28*(E13*E16+(1-E13)*E17)+(1-$D$33)*E28*E18) -> -0.032896144 | F40: =IF(F$6="sailed",0,$D$33*F28*(F13*F16+(1-F13)*F17)+(1-$D$33)*F28*F18) -> -0.018559834 | G40: =IF(G$6="sailed",0,$D$33*G28*(G13*G16+(1-G13)*G17)+(1-$D$33)*G28*G18) -> -0.013061766 | H40: =IF(H$6="sailed",0,$D$33*H28*(H13*H16+(1-H13)*H17)+(1-$D$33)*H28*H18) -> -0.0010907097 | I40: =IF(I$6="sailed",0,$D$33*I28*(I13*I16+(1-I13)*I17)+(1-$D$33)*I28*I18) -> -0.0020300744
B41: Bear case | C41: 2H27: part of the 1H27 Caribbean cut carries over (row 30) | D41: =IF(D$6="sailed",0,$D$33*D29*(D13*IF(D$6="2H 2027",MIN(D16,$D$30*$F$16),D16)+(1-D13)*D17)+(1-$D$33)*D29*D18) -> 0 | E41: =IF(E$6="sailed",0,$D$33*E29*(E13*IF(E$6="2H 2027",MIN(E16,$D$30*$F$16),E16)+(1-E13)*E17)+(1-$D$33)*E29*E18) -> -0.037830566 | F41: =IF(F$6="sailed",0,$D$33*F29*(F13*IF(F$6="2H 2027",MIN(F16,$D$30*$F$16),F16)+(1-F13)*F17)+(1-$D$33)*F29*F18) -> -0.035634882 | G41: =IF(G$6="sailed",0,$D$33*G29*(G13*IF(G$6="2H 2027",MIN(G16,$D$30*$F$16),G16)+(1-G13)*G17)+(1-$D$33)*G29*G18) -> -0.030303298 | H41: =IF(H$6="sailed",0,$D$33*H29*(H13*IF(H$6="2H 2027",MIN(H16,$D$30*$F$16),H16)+(1-H13)*H17)+(1-$D$33)*H29*H18) -> -0.0076792646 | I41: =IF(I$6="sailed",0,$D$33*I29*(I13*IF(I$6="2H 2027",MIN(I16,$D$30*$F$16),I16)+(1-I13)*I17)+(1-$D$33)*I29*I18) -> -0.020381721
B42: Base less consensus (pts) | D42: =D39-D40 -> 0 | E42: =E39-E40 -> 0 | F42: =F39-F40 -> -0.014847867 | G42: =G39-G40 -> -0.01567412 | H42: =H39-H40 -> -0.0017451356 | I42: =I39-I40 -> -0.0040601488
B43: Memo: part of the base effect that is NCL-specific (Caribbean cut beyond peers) | D43: =IF(D$6="sailed",0,$D$33*D27*D13*D20) -> 0 | E43: =IF(E$6="sailed",0,$D$33*E27*E13*E20) -> -0.022566615 | F43: =IF(F$6="sailed",0,$D$33*F27*F13*F20) -> -0.030132354 | G43: =IF(G$6="sailed",0,$D$33*G27*G13*G20) -> -0.022297566 | H43: =IF(H$6="sailed",0,$D$33*H27*H13*H20) -> -0.0018451121 | I43: =IF(I$6="sailed",0,$D$33*I27*I13*I20) -> -0.0054443803
B45: F. Other ticket-price items, the same in every case
B46: Full-fare commissions: run-rate cost (pts of ticket revenue) | C46: Non-commissionable fares ended for bookings from Dec 26, 2025 | D46: 0.015
B47: Share of the quarter's sailings booked under the new terms | D47: 0.4 | E47: 0.6 | F47: 0.8667 | G47: 0.8833 | H47: 0.9 | I47: 0.9333
B48: Same quarter a year earlier | D48: 0 | E48: 0 | F48: 0 | G48: 0.15 | H48: =D47 -> 0.4 | I48: =E47 -> 0.6
B49: Commission step-up y/y (pts of ticket) | D49: =$D$46*(D47-D48) -> 0.006 | E49: =$D$46*(E47-E48) -> 0.009 | F49: =$D$46*(F47-F48) -> 0.0130005 | G49: =$D$46*(G47-G48) -> 0.0109995 | H49: =$D$46*(H47-H48) -> 0.0075 | I49: =$D$46*(I47-I48) -> 0.0049995
B51: G. Sensitivity: 1Q27 Thesis 1 effect (base) vs. NCL revenue weight (across) and 1H27 Caribbean cut (down)
D52: 0.55 | E52: 0.6 | F52: 0.65 | G52: 0.7 | H52: 0.8
C53: -0.05 | D53: =D$52*$F$27*($F$13*$C53+(1-$F$13)*$F$17)+(1-D$52)*$F$27*$F$18 -> -0.010966786 | E53: =E$52*$F$27*($F$13*$C53+(1-$F$13)*$F$17)+(1-E$52)*$F$27*$F$18 -> -0.011963766 | F53: =F$52*$F$27*($F$13*$C53+(1-$F$13)*$F$17)+(1-F$52)*$F$27*$F$18 -> -0.012960747 | G53: =G$52*$F$27*($F$13*$C53+(1-$F$13)*$F$17)+(1-G$52)*$F$27*$F$18 -> -0.013957727 | H53: =H$52*$F$27*($F$13*$C53+(1-$F$13)*$F$17)+(1-H$52)*$F$27*$F$18 -> -0.015951688
C54: -0.1 | D54: =D$52*$F$27*($F$13*$C54+(1-$F$13)*$F$17)+(1-D$52)*$F$27*$F$18 -> -0.020072717 | E54: =E$52*$F$27*($F$13*$C54+(1-$F$13)*$F$17)+(1-E$52)*$F$27*$F$18 -> -0.021897509 | F54: =F$52*$F$27*($F$13*$C54+(1-$F$13)*$F$17)+(1-F$52)*$F$27*$F$18 -> -0.023722302 | G54: =G$52*$F$27*($F$13*$C54+(1-$F$13)*$F$17)+(1-G$52)*$F$27*$F$18 -> -0.025547094 | H54: =H$52*$F$27*($F$13*$C54+(1-$F$13)*$F$17)+(1-H$52)*$F$27*$F$18 -> -0.029196679
C55: -0.145 | D55: =D$52*$F$27*($F$13*$C55+(1-$F$13)*$F$17)+(1-D$52)*$F$27*$F$18 -> -0.028268055 | E55: =E$52*$F$27*($F$13*$C55+(1-$F$13)*$F$17)+(1-E$52)*$F$27*$F$18 -> -0.030837878 | F55: =F$52*$F$27*($F$13*$C55+(1-$F$13)*$F$17)+(1-F$52)*$F$27*$F$18 -> -0.033407702 | G55: =G$52*$F$27*($F$13*$C55+(1-$F$13)*$F$17)+(1-G$52)*$F$27*$F$18 -> -0.035977525 | H55: =H$52*$F$27*($F$13*$C55+(1-$F$13)*$F$17)+(1-H$52)*$F$27*$F$18 -> -0.041117171
C56: -0.2 | D56: =D$52*$F$27*($F$13*$C56+(1-$F$13)*$F$17)+(1-D$52)*$F$27*$F$18 -> -0.038284579 | E56: =E$52*$F$27*($F$13*$C56+(1-$F$13)*$F$17)+(1-E$52)*$F$27*$F$18 -> -0.041764996 | F56: =F$52*$F$27*($F$13*$C56+(1-$F$13)*$F$17)+(1-F$52)*$F$27*$F$18 -> -0.045245412 | G56: =G$52*$F$27*($F$13*$C56+(1-$F$13)*$F$17)+(1-G$52)*$F$27*$F$18 -> -0.048725828 | H56: =H$52*$F$27*($F$13*$C56+(1-$F$13)*$F$17)+(1-H$52)*$F$27*$F$18 -> -0.055686661
B58: Blue on gray = assumptions; blue = data; black = formulas; green = links. Fare data: Fare Panel (allaboarddeals.com, Oct 2, 2026). Capacity: Fleet Build / Fleet Qtr Build.

Sheet KPI 2 Booking Build
B2: KPI 2 Booking Build (Thesis 2): booking shortfall -> occupancy and late discounts
B3: Thesis 2: NCL's Best Price Guarantee removes the reason to book early, so the booking shortfall persists and NCL fills it late at a discount, leaving some cabins empty. Deposits size the shortfall; this sheet splits it into empty cabins (KPI 2: occupancy) and late-sold cabins (price, 2H27).
B5: A. How short is the booked position? (Jun 30, 2026) | C5: Logic / source
B6: Deposits per future berth-day, y/y | C6: Deposits sheet: advance ticket sales / next-4Q capacity days | D6: =Deposits!F26 -> -0.082514538
B7: Ticket revenue per passenger day, 1H26 y/y (realized price) | C7: Quarterly (A) | D7: =(('Quarterly (A)'!I5+'Quarterly (A)'!J5)/('Quarterly (A)'!I30+'Quarterly (A)'!J30))/(('Quarterly (A)'!E5+'Quarterly (A)'!F5)/('Quarterly (A)'!E30+'Quarterly (A)'!F30))-1 -> -0.055799176
B8: Shortfall if booked fares fell as much as realized fares (share of cabins) | D8: =D7-D6 -> 0.026715362
B9: Shortfall if booked fares were flat | D9: =-D6 -> 0.082514538
B10: Midpoint | D10: =AVERAGE(D8:D9) -> 0.05461495
B11: Base-case booking shortfall | C11: Midpoint, rounded down; 4Q26 through 4Q27 | D11: 0.05
B12: Bear-case booking shortfall | C12: About the fares-flat reading (row 9) | D12: 0.08
B13: Consensus case: no shortfall (base-loading works) | D13: 0
B14: Management: NCL is "below its optimal booked position for the next 12 months" (2Q26 call).
B16: B. How much of the shortfall stays empty (KPI 2: occupancy)
B17: Cross-check: 2Q26 occupancy change y/y (pts) | D17: =('Quarterly (A)'!J31-'Quarterly (A)'!F31)*100 -> -1.535722
B18: Deposit indicator a quarter earlier (Mar 31, 2026) | D18: =Deposits!F25 -> -0.06071791
B19: Occupancy points per 1% of indicator decline (2Q26) | D19: =D17/(D18*100) -> 0.25292735
B20: Same, 3Q26 guide vs. the Jun 30 indicator | D20: =(('Net Yield Build'!L47-'Quarterly (A)'!G31)*100)/(Deposits!F26*100) -> 0.29085784
B21: Occupancy drop that relationship implies at today's indicator (pts) | D21: =AVERAGE(D19:D20)*Deposits!F26*100 -> -2.2435092
B22: Share of the shortfall that stays unsold | C22: Gives 1.0 pt vs. consensus case, about half of row 21 | D22: 0.2
D24: 3Q26E | E24: 4Q26E | F24: 1Q27E | G24: 2Q27E | H24: 3Q27E | I24: 4Q27E
B25: Apply to quarter (2027 sailings) | D25: 0 | E25: 0 | F25: 1 | G25: 1 | H25: 1 | I25: 1
B26: KPI 2: occupancy vs. consensus case, base (pts) | D26: =-D25*$D$11*$D$22*100 -> 0 | E26: =-E25*$D$11*$D$22*100 -> 0 | F26: =-F25*$D$11*$D$22*100 -> -1 | G26: =-G25*$D$11*$D$22*100 -> -1 | H26: =-H25*$D$11*$D$22*100 -> -1 | I26: =-I25*$D$11*$D$22*100 -> -1
B27: KPI 2: occupancy vs. consensus case, bear (pts) | D27: =-D25*$D$12*$D$22*100 -> 0 | E27: =-E25*$D$12*$D$22*100 -> 0 | F27: =-F25*$D$12*$D$22*100 -> -1.6 | G27: =-G25*$D$12*$D$22*100 -> -1.6 | H27: =-H25*$D$12*$D$22*100 -> -1.6 | I27: =-I25*$D$12*$D$22*100 -> -1.6
B29: C. Cabins sold late: the close-in discount (price, 2H27 sailings)
B30: Close-in discount: NCL cut on sailings within ~3 months (4Q26) | C30: KPI 1 build, 4Q26, NCL brand Caribbean/other mix | D30: ='KPI 1 Price Build'!E13*'KPI 1 Price Build'!E16+(1-'KPI 1 Price Build'!E13)*'KPI 1 Price Build'!E17 -> -0.25304726
B31: Apply to quarter (2H27: not yet visible in the fare panel) | D31: 0 | E31: 0 | F31: 0 | G31: 0 | H31: 1 | I31: 1
B32: Thesis 2 price effect, base (pts of NCLH ticket revenue per passenger day) | C32: shortfall x share sold late x close-in discount x NCL weight | D32: =D31*$D$11*(1-$D$22)*$D$30*'KPI 1 Price Build'!$D$33 -> 0 | E32: =E31*$D$11*(1-$D$22)*$D$30*'KPI 1 Price Build'!$D$33 -> 0 | F32: =F31*$D$11*(1-$D$22)*$D$30*'KPI 1 Price Build'!$D$33 -> 0 | G32: =G31*$D$11*(1-$D$22)*$D$30*'KPI 1 Price Build'!$D$33 -> 0 | H32: =H31*$D$11*(1-$D$22)*$D$30*'KPI 1 Price Build'!$D$33 -> -0.0065792288 | I32: =I31*$D$11*(1-$D$22)*$D$30*'KPI 1 Price Build'!$D$33 -> -0.0065792288
B33: Thesis 2 price effect, bear | D33: =D31*$D$12*(1-$D$22)*$D$30*'KPI 1 Price Build'!$D$33 -> 0 | E33: =E31*$D$12*(1-$D$22)*$D$30*'KPI 1 Price Build'!$D$33 -> 0 | F33: =F31*$D$12*(1-$D$22)*$D$30*'KPI 1 Price Build'!$D$33 -> 0 | G33: =G31*$D$12*(1-$D$22)*$D$30*'KPI 1 Price Build'!$D$33 -> 0 | H33: =H31*$D$12*(1-$D$22)*$D$30*'KPI 1 Price Build'!$D$33 -> -0.010526766 | I33: =I31*$D$12*(1-$D$22)*$D$30*'KPI 1 Price Build'!$D$33 -> -0.010526766
B35: D. Best Price Guarantee claims (not in the base case; switch for sensitivity)
B36: Include in the Net Yield Build? (1 = yes) | D36: 0
B37: Claim rate: booked guests who reprice before final payment | D37: 0.33333333
B38: Claim rate: paid-up guests who take an upgrade or credit | D38: 0.33333333
B39: Share of claims taken as future-cruise credit (rest as upgrades) | D39: 0.5
B40: Credits redeemed evenly over the next quarters (valid two years) | D40: 8
D41: 3Q26E | E41: 4Q26E | F41: 1Q27E | G41: 2Q27E | H41: 3Q27E | I41: 4Q27E
B42: NCL brand fare cut on the quarter's sailings | D42: ='KPI 1 Price Build'!D13*'KPI 1 Price Build'!D16+(1-'KPI 1 Price Build'!D13)*'KPI 1 Price Build'!D17 -> 0 | E42: ='KPI 1 Price Build'!E13*'KPI 1 Price Build'!E16+(1-'KPI 1 Price Build'!E13)*'KPI 1 Price Build'!E17 -> -0.25304726 | F42: ='KPI 1 Price Build'!F13*'KPI 1 Price Build'!F16+(1-'KPI 1 Price Build'!F13)*'KPI 1 Price Build'!F17 -> -0.11421436 | G42: ='KPI 1 Price Build'!G13*'KPI 1 Price Build'!G16+(1-'KPI 1 Price Build'!G13)*'KPI 1 Price Build'!G17 -> -0.080380101 | H42: ='KPI 1 Price Build'!H13*'KPI 1 Price Build'!H16+(1-'KPI 1 Price Build'!H13)*'KPI 1 Price Build'!H17 -> -0.0067120599 | I42: ='KPI 1 Price Build'!I13*'KPI 1 Price Build'!I16+(1-'KPI 1 Price Build'!I13)*'KPI 1 Price Build'!I17 -> -0.012492766
B43: Share of booked guests already past final payment when cut | D43: 1 | E43: 1 | F43: 0.3 | G43: 0 | H43: 0 | I43: 0
B44: Share of cabins sold before the cuts (base) | D44: =1-'KPI 1 Price Build'!D27 -> 1 | E44: =1-'KPI 1 Price Build'!E27 -> 0.8 | F44: =1-'KPI 1 Price Build'!F27 -> 0.55 | G44: =1-'KPI 1 Price Build'!G27 -> 0.45 | H44: =1-'KPI 1 Price Build'!H27 -> 0.35 | I44: =1-'KPI 1 Price Build'!I27 -> 0.25
B45: Repricing cost before final payment (pts of NCLH ticket revenue) | D45: =D44*(1-D43)*$D$37*D42*'KPI 1 Price Build'!$D$33 -> 0 | E45: =E44*(1-E43)*$D$37*E42*'KPI 1 Price Build'!$D$33 -> 0 | F45: =F44*(1-F43)*$D$37*F42*'KPI 1 Price Build'!$D$33 -> -0.0095273815 | G45: =G44*(1-G43)*$D$37*G42*'KPI 1 Price Build'!$D$33 -> -0.0078370599 | H45: =H44*(1-H43)*$D$37*H42*'KPI 1 Price Build'!$D$33 -> -0.00050899788 | I45: =I44*(1-I43)*$D$37*I42*'KPI 1 Price Build'!$D$33 -> -0.00067669147
B46: Credits issued to paid-up guests (pts of NCLH ticket revenue) | D46: =D44*D43*'Fare Panel'!$F$196*$D$38*$D$39*D42*'KPI 1 Price Build'!$D$33 -> 0 | E46: =E44*E43*'Fare Panel'!$F$196*$D$38*$D$39*E42*'KPI 1 Price Build'!$D$33 -> -0.014496606 | F46: =F44*F43*'Fare Panel'!$F$196*$D$38*$D$39*F42*'KPI 1 Price Build'!$D$33 -> -0.0013495201 | G46: =G44*G43*'Fare Panel'!$F$196*$D$38*$D$39*G42*'KPI 1 Price Build'!$D$33 -> 0 | H46: =H44*H43*'Fare Panel'!$F$196*$D$38*$D$39*H42*'KPI 1 Price Build'!$D$33 -> 0 | I46: =I44*I43*'Fare Panel'!$F$196*$D$38*$D$39*I42*'KPI 1 Price Build'!$D$33 -> 0
B47: Ticket revenue, consensus case ($mm) | D47: ='Net Yield Build'!L32 -> 1922.4496 | E47: ='Net Yield Build'!M32 -> 1432.512 | F47: ='Net Yield Build'!N32 -> 1572.8875 | G47: ='Net Yield Build'!O32 -> 1743.0424 | H47: ='Net Yield Build'!P32 -> 2073.5194 | I47: ='Net Yield Build'!Q32 -> 1554.186
B48: Credits issued ($mm) | D48: =-D46*D47 -> 0 | E48: =-E46*E47 -> 20.766562 | F48: =-F46*F47 -> 2.1226434 | G48: =-G46*G47 -> 0 | H48: =-H46*H47 -> 0 | I48: =-I46*I47 -> 0
B49: Credits redeemed ($mm) | D49: =0 -> 0 | E49: =SUM($D$48:D48)/$D$40 -> 0 | F49: =SUM($D$48:E48)/$D$40 -> 2.5958203 | G49: =SUM($D$48:F48)/$D$40 -> 2.8611507 | H49: =SUM($D$48:G48)/$D$40 -> 2.8611507 | I49: =SUM($D$48:H48)/$D$40 -> 2.8611507
B50: Redemption cost (pts of ticket revenue) | D50: =-D49/D47 -> 0 | E50: =-E49/E47 -> 0 | F50: =-F49/F47 -> -0.0016503534 | G50: =-G49/G47 -> -0.0016414693 | H50: =-H49/H47 -> -0.0013798524 | I50: =-I49/I47 -> -0.0018409319
B51: Total claim cost (pts of ticket revenue) | D51: =D45+D50 -> 0 | E51: =E45+E50 -> 0 | F51: =F45+F50 -> -0.011177735 | G51: =G45+G50 -> -0.0094785292 | H51: =H45+H50 -> -0.0018888502 | I51: =I45+I50 -> -0.0025176234
B52: Applied in the Net Yield Build (x switch) | D52: =D51*$D$36 -> 0 | E52: =E51*$D$36 -> 0 | F52: =F51*$D$36 -> 0 | G52: =G51*$D$36 -> 0 | H52: =H51*$D$36 -> 0 | I52: =I51*$D$36 -> 0
B53: Memo: 2027 EBITDA cost if switched on ($mm) | D53: =SUMPRODUCT(F51:I51,'Net Yield Build'!N59:Q59) -> -40.846751
B54: Memo: 2027 net yield cost if switched on (pts) | D54: =D53/'Net Yield Build'!U64 -> -0.0052854333
B56: E. Dated checks on the booking shortfall
B57: Sept 30, 2026 advance ticket sales: our forecast ($mm, Nov 4 10-Q) | D57: =Deposits!C70 -> 2940.2197
B58: Supports the thesis if below ($mm) | D58: =Deposits!C72 -> 2970
B59: Thesis 2 wrong if at or above ($mm) | D59: =Deposits!C73 -> 3110
B60: Back-test: share of quarters the indicator called the direction of net yield | D60: =Deposits!F31 -> 0.8
B62: Sources: SEC XBRL (customer deposits); NCLH 8-Ks and 2Q26 call; ncl.com Best Price Guarantee terms; fare panel. Blue on gray = assumptions.

Sheet Fleet Build
B2: Fleet Build: berths in service by ship and year
B3: Scaling of undisclosed existing-ship berths to the 10-K fleet total (YE2024: 32 ships, ~66,500 berths) | E3: =66500/67220 -> 0.9892889
B4: Berth-years = berths x share of the year in service; dates as decimal years (2026.25 = Apr 1, 2026). Months after 2026 and all post-2027 delivery years are assumptions.
B5: Ship | C5: Brand | D5: Class / status | E5: Berths | F5: In service | G5: Out of service | H5: 2024 | I5: 2025 | J5: 2026 | K5: 2027 | L5: 2028 | M5: 2029 | N5: 2030
B6: Norwegian Aura | C6: Norwegian | D6: Prima Plus; 3,880 berths (10-Q); month assumed | E6: 3880 | F6: 2027.42 | G6: 2099 | H6: =$E6*MAX(0,MIN(H$5+1,$G6)-MAX(H$5,$F6)) -> 0 | I6: =$E6*MAX(0,MIN(I$5+1,$G6)-MAX(I$5,$F6)) -> 0 | J6: =$E6*MAX(0,MIN(J$5+1,$G6)-MAX(J$5,$F6)) -> 0 | K6: =$E6*MAX(0,MIN(K$5+1,$G6)-MAX(K$5,$F6)) -> 2250.4 | L6: =$E6*MAX(0,MIN(L$5+1,$G6)-MAX(L$5,$F6)) -> 3880 | M6: =$E6*MAX(0,MIN(M$5+1,$G6)-MAX(M$5,$F6)) -> 3880 | N6: =$E6*MAX(0,MIN(N$5+1,$G6)-MAX(N$5,$F6)) -> 3880
B7: Norwegian Prima Plus #6 | C7: Norwegian | D7: Prima Plus; 3,880 berths (10-Q); 2028 date assumed | E7: 3880 | F7: 2028.5 | G7: 2099 | H7: =$E7*MAX(0,MIN(H$5+1,$G7)-MAX(H$5,$F7)) -> 0 | I7: =$E7*MAX(0,MIN(I$5+1,$G7)-MAX(I$5,$F7)) -> 0 | J7: =$E7*MAX(0,MIN(J$5+1,$G7)-MAX(J$5,$F7)) -> 0 | K7: =$E7*MAX(0,MIN(K$5+1,$G7)-MAX(K$5,$F7)) -> 0 | L7: =$E7*MAX(0,MIN(L$5+1,$G7)-MAX(L$5,$F7)) -> 1940 | M7: =$E7*MAX(0,MIN(M$5+1,$G7)-MAX(M$5,$F7)) -> 3880 | N7: =$E7*MAX(0,MIN(N$5+1,$G7)-MAX(N$5,$F7)) -> 3880
B8: Norwegian Luna | C8: Norwegian | D8: Prima Plus; 3,565 berths (10-K); delivered Mar 2026 | E8: 3565 | F8: 2026.25 | G8: 2099 | H8: =$E8*MAX(0,MIN(H$5+1,$G8)-MAX(H$5,$F8)) -> 0 | I8: =$E8*MAX(0,MIN(I$5+1,$G8)-MAX(I$5,$F8)) -> 0 | J8: =$E8*MAX(0,MIN(J$5+1,$G8)-MAX(J$5,$F8)) -> 2673.75 | K8: =$E8*MAX(0,MIN(K$5+1,$G8)-MAX(K$5,$F8)) -> 3565 | L8: =$E8*MAX(0,MIN(L$5+1,$G8)-MAX(L$5,$F8)) -> 3565 | M8: =$E8*MAX(0,MIN(M$5+1,$G8)-MAX(M$5,$F8)) -> 3565 | N8: =$E8*MAX(0,MIN(N$5+1,$G8)-MAX(N$5,$F8)) -> 3565
B9: Norwegian Aqua | C9: Norwegian | D9: Prima Plus; 3,550 berths (FY24 10-K); delivered 2025 | E9: 3550 | F9: 2025.25 | G9: 2099 | H9: =$E9*MAX(0,MIN(H$5+1,$G9)-MAX(H$5,$F9)) -> 0 | I9: =$E9*MAX(0,MIN(I$5+1,$G9)-MAX(I$5,$F9)) -> 2662.5 | J9: =$E9*MAX(0,MIN(J$5+1,$G9)-MAX(J$5,$F9)) -> 3550 | K9: =$E9*MAX(0,MIN(K$5+1,$G9)-MAX(K$5,$F9)) -> 3550 | L9: =$E9*MAX(0,MIN(L$5+1,$G9)-MAX(L$5,$F9)) -> 3550 | M9: =$E9*MAX(0,MIN(M$5+1,$G9)-MAX(M$5,$F9)) -> 3550 | N9: =$E9*MAX(0,MIN(N$5+1,$G9)-MAX(N$5,$F9)) -> 3550
B10: Norwegian Viva | C10: Norwegian | D10: Prima | E10: =3099*$E$3 -> 3065.8063 | F10: 2000 | G10: 2099 | H10: =$E10*MAX(0,MIN(H$5+1,$G10)-MAX(H$5,$F10)) -> 3065.8063 | I10: =$E10*MAX(0,MIN(I$5+1,$G10)-MAX(I$5,$F10)) -> 3065.8063 | J10: =$E10*MAX(0,MIN(J$5+1,$G10)-MAX(J$5,$F10)) -> 3065.8063 | K10: =$E10*MAX(0,MIN(K$5+1,$G10)-MAX(K$5,$F10)) -> 3065.8063 | L10: =$E10*MAX(0,MIN(L$5+1,$G10)-MAX(L$5,$F10)) -> 3065.8063 | M10: =$E10*MAX(0,MIN(M$5+1,$G10)-MAX(M$5,$F10)) -> 3065.8063 | N10: =$E10*MAX(0,MIN(N$5+1,$G10)-MAX(N$5,$F10)) -> 3065.8063
B11: Norwegian Prima | C11: Norwegian | D11: Prima | E11: =3099*$E$3 -> 3065.8063 | F11: 2000 | G11: 2099 | H11: =$E11*MAX(0,MIN(H$5+1,$G11)-MAX(H$5,$F11)) -> 3065.8063 | I11: =$E11*MAX(0,MIN(I$5+1,$G11)-MAX(I$5,$F11)) -> 3065.8063 | J11: =$E11*MAX(0,MIN(J$5+1,$G11)-MAX(J$5,$F11)) -> 3065.8063 | K11: =$E11*MAX(0,MIN(K$5+1,$G11)-MAX(K$5,$F11)) -> 3065.8063 | L11: =$E11*MAX(0,MIN(L$5+1,$G11)-MAX(L$5,$F11)) -> 3065.8063 | M11: =$E11*MAX(0,MIN(M$5+1,$G11)-MAX(M$5,$F11)) -> 3065.8063 | N11: =$E11*MAX(0,MIN(N$5+1,$G11)-MAX(N$5,$F11)) -> 3065.8063
B12: Norwegian new class #1 | C12: Norwegian | D12: 5,000 berths (10-Q); 2030 date assumed | E12: 5000 | F12: 2030.5 | G12: 2099 | H12: =$E12*MAX(0,MIN(H$5+1,$G12)-MAX(H$5,$F12)) -> 0 | I12: =$E12*MAX(0,MIN(I$5+1,$G12)-MAX(I$5,$F12)) -> 0 | J12: =$E12*MAX(0,MIN(J$5+1,$G12)-MAX(J$5,$F12)) -> 0 | K12: =$E12*MAX(0,MIN(K$5+1,$G12)-MAX(K$5,$F12)) -> 0 | L12: =$E12*MAX(0,MIN(L$5+1,$G12)-MAX(L$5,$F12)) -> 0 | M12: =$E12*MAX(0,MIN(M$5+1,$G12)-MAX(M$5,$F12)) -> 0 | N12: =$E12*MAX(0,MIN(N$5+1,$G12)-MAX(N$5,$F12)) -> 2500
B13: Norwegian Encore | C13: Norwegian | D13: Breakaway Plus | E13: =3998*$E$3 -> 3955.177 | F13: 2000 | G13: 2099 | H13: =$E13*MAX(0,MIN(H$5+1,$G13)-MAX(H$5,$F13)) -> 3955.177 | I13: =$E13*MAX(0,MIN(I$5+1,$G13)-MAX(I$5,$F13)) -> 3955.177 | J13: =$E13*MAX(0,MIN(J$5+1,$G13)-MAX(J$5,$F13)) -> 3955.177 | K13: =$E13*MAX(0,MIN(K$5+1,$G13)-MAX(K$5,$F13)) -> 3955.177 | L13: =$E13*MAX(0,MIN(L$5+1,$G13)-MAX(L$5,$F13)) -> 3955.177 | M13: =$E13*MAX(0,MIN(M$5+1,$G13)-MAX(M$5,$F13)) -> 3955.177 | N13: =$E13*MAX(0,MIN(N$5+1,$G13)-MAX(N$5,$F13)) -> 3955.177
B14: Norwegian Bliss | C14: Norwegian | D14: Breakaway Plus | E14: =4004*$E$3 -> 3961.1128 | F14: 2000 | G14: 2099 | H14: =$E14*MAX(0,MIN(H$5+1,$G14)-MAX(H$5,$F14)) -> 3961.1128 | I14: =$E14*MAX(0,MIN(I$5+1,$G14)-MAX(I$5,$F14)) -> 3961.1128 | J14: =$E14*MAX(0,MIN(J$5+1,$G14)-MAX(J$5,$F14)) -> 3961.1128 | K14: =$E14*MAX(0,MIN(K$5+1,$G14)-MAX(K$5,$F14)) -> 3961.1128 | L14: =$E14*MAX(0,MIN(L$5+1,$G14)-MAX(L$5,$F14)) -> 3961.1128 | M14: =$E14*MAX(0,MIN(M$5+1,$G14)-MAX(M$5,$F14)) -> 3961.1128 | N14: =$E14*MAX(0,MIN(N$5+1,$G14)-MAX(N$5,$F14)) -> 3961.1128
B15: Norwegian Joy | C15: Norwegian | D15: Breakaway Plus | E15: =3804*$E$3 -> 3763.255 | F15: 2000 | G15: 2099 | H15: =$E15*MAX(0,MIN(H$5+1,$G15)-MAX(H$5,$F15)) -> 3763.255 | I15: =$E15*MAX(0,MIN(I$5+1,$G15)-MAX(I$5,$F15)) -> 3763.255 | J15: =$E15*MAX(0,MIN(J$5+1,$G15)-MAX(J$5,$F15)) -> 3763.255 | K15: =$E15*MAX(0,MIN(K$5+1,$G15)-MAX(K$5,$F15)) -> 3763.255 | L15: =$E15*MAX(0,MIN(L$5+1,$G15)-MAX(L$5,$F15)) -> 3763.255 | M15: =$E15*MAX(0,MIN(M$5+1,$G15)-MAX(M$5,$F15)) -> 3763.255 | N15: =$E15*MAX(0,MIN(N$5+1,$G15)-MAX(N$5,$F15)) -> 3763.255
B16: Norwegian Escape | C16: Norwegian | D16: Breakaway Plus | E16: =4266*$E$3 -> 4220.3065 | F16: 2000 | G16: 2099 | H16: =$E16*MAX(0,MIN(H$5+1,$G16)-MAX(H$5,$F16)) -> 4220.3065 | I16: =$E16*MAX(0,MIN(I$5+1,$G16)-MAX(I$5,$F16)) -> 4220.3065 | J16: =$E16*MAX(0,MIN(J$5+1,$G16)-MAX(J$5,$F16)) -> 4220.3065 | K16: =$E16*MAX(0,MIN(K$5+1,$G16)-MAX(K$5,$F16)) -> 4220.3065 | L16: =$E16*MAX(0,MIN(L$5+1,$G16)-MAX(L$5,$F16)) -> 4220.3065 | M16: =$E16*MAX(0,MIN(M$5+1,$G16)-MAX(M$5,$F16)) -> 4220.3065 | N16: =$E16*MAX(0,MIN(N$5+1,$G16)-MAX(N$5,$F16)) -> 4220.3065
B17: Norwegian Getaway | C17: Norwegian | D17: Breakaway | E17: =3963*$E$3 -> 3920.5519 | F17: 2000 | G17: 2099 | H17: =$E17*MAX(0,MIN(H$5+1,$G17)-MAX(H$5,$F17)) -> 3920.5519 | I17: =$E17*MAX(0,MIN(I$5+1,$G17)-MAX(I$5,$F17)) -> 3920.5519 | J17: =$E17*MAX(0,MIN(J$5+1,$G17)-MAX(J$5,$F17)) -> 3920.5519 | K17: =$E17*MAX(0,MIN(K$5+1,$G17)-MAX(K$5,$F17)) -> 3920.5519 | L17: =$E17*MAX(0,MIN(L$5+1,$G17)-MAX(L$5,$F17)) -> 3920.5519 | M17: =$E17*MAX(0,MIN(M$5+1,$G17)-MAX(M$5,$F17)) -> 3920.5519 | N17: =$E17*MAX(0,MIN(N$5+1,$G17)-MAX(N$5,$F17)) -> 3920.5519
B18: Norwegian Breakaway | C18: Norwegian | D18: Breakaway | E18: =3963*$E$3 -> 3920.5519 | F18: 2000 | G18: 2099 | H18: =$E18*MAX(0,MIN(H$5+1,$G18)-MAX(H$5,$F18)) -> 3920.5519 | I18: =$E18*MAX(0,MIN(I$5+1,$G18)-MAX(I$5,$F18)) -> 3920.5519 | J18: =$E18*MAX(0,MIN(J$5+1,$G18)-MAX(J$5,$F18)) -> 3920.5519 | K18: =$E18*MAX(0,MIN(K$5+1,$G18)-MAX(K$5,$F18)) -> 3920.5519 | L18: =$E18*MAX(0,MIN(L$5+1,$G18)-MAX(L$5,$F18)) -> 3920.5519 | M18: =$E18*MAX(0,MIN(M$5+1,$G18)-MAX(M$5,$F18)) -> 3920.5519 | N18: =$E18*MAX(0,MIN(N$5+1,$G18)-MAX(N$5,$F18)) -> 3920.5519
B19: Norwegian Epic | C19: Norwegian | D19: Epic | E19: =4100*$E$3 -> 4056.0845 | F19: 2000 | G19: 2099 | H19: =$E19*MAX(0,MIN(H$5+1,$G19)-MAX(H$5,$F19)) -> 4056.0845 | I19: =$E19*MAX(0,MIN(I$5+1,$G19)-MAX(I$5,$F19)) -> 4056.0845 | J19: =$E19*MAX(0,MIN(J$5+1,$G19)-MAX(J$5,$F19)) -> 4056.0845 | K19: =$E19*MAX(0,MIN(K$5+1,$G19)-MAX(K$5,$F19)) -> 4056.0845 | L19: =$E19*MAX(0,MIN(L$5+1,$G19)-MAX(L$5,$F19)) -> 4056.0845 | M19: =$E19*MAX(0,MIN(M$5+1,$G19)-MAX(M$5,$F19)) -> 4056.0845 | N19: =$E19*MAX(0,MIN(N$5+1,$G19)-MAX(N$5,$F19)) -> 4056.0845
B20: Norwegian Gem | C20: Norwegian | D20: Jewel | E20: =2394*$E$3 -> 2368.3576 | F20: 2000 | G20: 2099 | H20: =$E20*MAX(0,MIN(H$5+1,$G20)-MAX(H$5,$F20)) -> 2368.3576 | I20: =$E20*MAX(0,MIN(I$5+1,$G20)-MAX(I$5,$F20)) -> 2368.3576 | J20: =$E20*MAX(0,MIN(J$5+1,$G20)-MAX(J$5,$F20)) -> 2368.3576 | K20: =$E20*MAX(0,MIN(K$5+1,$G20)-MAX(K$5,$F20)) -> 2368.3576 | L20: =$E20*MAX(0,MIN(L$5+1,$G20)-MAX(L$5,$F20)) -> 2368.3576 | M20: =$E20*MAX(0,MIN(M$5+1,$G20)-MAX(M$5,$F20)) -> 2368.3576 | N20: =$E20*MAX(0,MIN(N$5+1,$G20)-MAX(N$5,$F20)) -> 2368.3576
B21: Norwegian Jade | C21: Norwegian | D21: Jewel | E21: =2402*$E$3 -> 2376.2719 | F21: 2000 | G21: 2099 | H21: =$E21*MAX(0,MIN(H$5+1,$G21)-MAX(H$5,$F21)) -> 2376.2719 | I21: =$E21*MAX(0,MIN(I$5+1,$G21)-MAX(I$5,$F21)) -> 2376.2719 | J21: =$E21*MAX(0,MIN(J$5+1,$G21)-MAX(J$5,$F21)) -> 2376.2719 | K21: =$E21*MAX(0,MIN(K$5+1,$G21)-MAX(K$5,$F21)) -> 2376.2719 | L21: =$E21*MAX(0,MIN(L$5+1,$G21)-MAX(L$5,$F21)) -> 2376.2719 | M21: =$E21*MAX(0,MIN(M$5+1,$G21)-MAX(M$5,$F21)) -> 2376.2719 | N21: =$E21*MAX(0,MIN(N$5+1,$G21)-MAX(N$5,$F21)) -> 2376.2719
B22: Norwegian Pearl | C22: Norwegian | D22: Jewel | E22: =2394*$E$3 -> 2368.3576 | F22: 2000 | G22: 2099 | H22: =$E22*MAX(0,MIN(H$5+1,$G22)-MAX(H$5,$F22)) -> 2368.3576 | I22: =$E22*MAX(0,MIN(I$5+1,$G22)-MAX(I$5,$F22)) -> 2368.3576 | J22: =$E22*MAX(0,MIN(J$5+1,$G22)-MAX(J$5,$F22)) -> 2368.3576 | K22: =$E22*MAX(0,MIN(K$5+1,$G22)-MAX(K$5,$F22)) -> 2368.3576 | L22: =$E22*MAX(0,MIN(L$5+1,$G22)-MAX(L$5,$F22)) -> 2368.3576 | M22: =$E22*MAX(0,MIN(M$5+1,$G22)-MAX(M$5,$F22)) -> 2368.3576 | N22: =$E22*MAX(0,MIN(N$5+1,$G22)-MAX(N$5,$F22)) -> 2368.3576
B23: Norwegian Jewel | C23: Norwegian | D23: Jewel | E23: =2376*$E$3 -> 2350.5504 | F23: 2000 | G23: 2099 | H23: =$E23*MAX(0,MIN(H$5+1,$G23)-MAX(H$5,$F23)) -> 2350.5504 | I23: =$E23*MAX(0,MIN(I$5+1,$G23)-MAX(I$5,$F23)) -> 2350.5504 | J23: =$E23*MAX(0,MIN(J$5+1,$G23)-MAX(J$5,$F23)) -> 2350.5504 | K23: =$E23*MAX(0,MIN(K$5+1,$G23)-MAX(K$5,$F23)) -> 2350.5504 | L23: =$E23*MAX(0,MIN(L$5+1,$G23)-MAX(L$5,$F23)) -> 2350.5504 | M23: =$E23*MAX(0,MIN(M$5+1,$G23)-MAX(M$5,$F23)) -> 2350.5504 | N23: =$E23*MAX(0,MIN(N$5+1,$G23)-MAX(N$5,$F23)) -> 2350.5504
B24: Pride of America | C24: Norwegian | D24: Hawaii (U.S.-flag) | E24: =2186*$E$3 -> 2162.5855 | F24: 2000 | G24: 2099 | H24: =$E24*MAX(0,MIN(H$5+1,$G24)-MAX(H$5,$F24)) -> 2162.5855 | I24: =$E24*MAX(0,MIN(I$5+1,$G24)-MAX(I$5,$F24)) -> 2162.5855 | J24: =$E24*MAX(0,MIN(J$5+1,$G24)-MAX(J$5,$F24)) -> 2162.5855 | K24: =$E24*MAX(0,MIN(K$5+1,$G24)-MAX(K$5,$F24)) -> 2162.5855 | L24: =$E24*MAX(0,MIN(L$5+1,$G24)-MAX(L$5,$F24)) -> 2162.5855 | M24: =$E24*MAX(0,MIN(M$5+1,$G24)-MAX(M$5,$F24)) -> 2162.5855 | N24: =$E24*MAX(0,MIN(N$5+1,$G24)-MAX(N$5,$F24)) -> 2162.5855
B25: Norwegian Dawn | C25: Norwegian | D25: Dawn | E25: =2340*$E$3 -> 2314.936 | F25: 2000 | G25: 2099 | H25: =$E25*MAX(0,MIN(H$5+1,$G25)-MAX(H$5,$F25)) -> 2314.936 | I25: =$E25*MAX(0,MIN(I$5+1,$G25)-MAX(I$5,$F25)) -> 2314.936 | J25: =$E25*MAX(0,MIN(J$5+1,$G25)-MAX(J$5,$F25)) -> 2314.936 | K25: =$E25*MAX(0,MIN(K$5+1,$G25)-MAX(K$5,$F25)) -> 2314.936 | L25: =$E25*MAX(0,MIN(L$5+1,$G25)-MAX(L$5,$F25)) -> 2314.936 | M25: =$E25*MAX(0,MIN(M$5+1,$G25)-MAX(M$5,$F25)) -> 2314.936 | N25: =$E25*MAX(0,MIN(N$5+1,$G25)-MAX(N$5,$F25)) -> 2314.936
B26: Norwegian Star | C26: Norwegian | D26: Dawn | E26: =2348*$E$3 -> 2322.8503 | F26: 2000 | G26: 2099 | H26: =$E26*MAX(0,MIN(H$5+1,$G26)-MAX(H$5,$F26)) -> 2322.8503 | I26: =$E26*MAX(0,MIN(I$5+1,$G26)-MAX(I$5,$F26)) -> 2322.8503 | J26: =$E26*MAX(0,MIN(J$5+1,$G26)-MAX(J$5,$F26)) -> 2322.8503 | K26: =$E26*MAX(0,MIN(K$5+1,$G26)-MAX(K$5,$F26)) -> 2322.8503 | L26: =$E26*MAX(0,MIN(L$5+1,$G26)-MAX(L$5,$F26)) -> 2322.8503 | M26: =$E26*MAX(0,MIN(M$5+1,$G26)-MAX(M$5,$F26)) -> 2322.8503 | N26: =$E26*MAX(0,MIN(N$5+1,$G26)-MAX(N$5,$F26)) -> 2322.8503
B27: Norwegian Sun | C27: Norwegian | D27: Bareboat charter out, late 2027 (10-Q) | E27: 1936 | F27: 2000 | G27: 2027.83 | H27: =$E27*MAX(0,MIN(H$5+1,$G27)-MAX(H$5,$F27)) -> 1936 | I27: =$E27*MAX(0,MIN(I$5+1,$G27)-MAX(I$5,$F27)) -> 1936 | J27: =$E27*MAX(0,MIN(J$5+1,$G27)-MAX(J$5,$F27)) -> 1936 | K27: =$E27*MAX(0,MIN(K$5+1,$G27)-MAX(K$5,$F27)) -> 1606.88 | L27: =$E27*MAX(0,MIN(L$5+1,$G27)-MAX(L$5,$F27)) -> 0 | M27: =$E27*MAX(0,MIN(M$5+1,$G27)-MAX(M$5,$F27)) -> 0 | N27: =$E27*MAX(0,MIN(N$5+1,$G27)-MAX(N$5,$F27)) -> 0
B28: Norwegian Sky | C28: Norwegian | D28: Bareboat charter out, late 2026 (10-Q) | E28: 2004 | F28: 2000 | G28: 2026.83 | H28: =$E28*MAX(0,MIN(H$5+1,$G28)-MAX(H$5,$F28)) -> 2004 | I28: =$E28*MAX(0,MIN(I$5+1,$G28)-MAX(I$5,$F28)) -> 2004 | J28: =$E28*MAX(0,MIN(J$5+1,$G28)-MAX(J$5,$F28)) -> 1663.32 | K28: =$E28*MAX(0,MIN(K$5+1,$G28)-MAX(K$5,$F28)) -> 0 | L28: =$E28*MAX(0,MIN(L$5+1,$G28)-MAX(L$5,$F28)) -> 0 | M28: =$E28*MAX(0,MIN(M$5+1,$G28)-MAX(M$5,$F28)) -> 0 | N28: =$E28*MAX(0,MIN(N$5+1,$G28)-MAX(N$5,$F28)) -> 0
B29: Norwegian Spirit | C29: Norwegian | D29: Spirit | E29: =1972*$E$3 -> 1950.8777 | F29: 2000 | G29: 2099 | H29: =$E29*MAX(0,MIN(H$5+1,$G29)-MAX(H$5,$F29)) -> 1950.8777 | I29: =$E29*MAX(0,MIN(I$5+1,$G29)-MAX(I$5,$F29)) -> 1950.8777 | J29: =$E29*MAX(0,MIN(J$5+1,$G29)-MAX(J$5,$F29)) -> 1950.8777 | K29: =$E29*MAX(0,MIN(K$5+1,$G29)-MAX(K$5,$F29)) -> 1950.8777 | L29: =$E29*MAX(0,MIN(L$5+1,$G29)-MAX(L$5,$F29)) -> 1950.8777 | M29: =$E29*MAX(0,MIN(M$5+1,$G29)-MAX(M$5,$F29)) -> 1950.8777 | N29: =$E29*MAX(0,MIN(N$5+1,$G29)-MAX(N$5,$F29)) -> 1950.8777
B30: Oceania Sonata | C30: Oceania | D30: Sonata; 1,390 berths (10-Q); month assumed | E30: 1390 | F30: 2027.58 | G30: 2099 | H30: =$E30*MAX(0,MIN(H$5+1,$G30)-MAX(H$5,$F30)) -> 0 | I30: =$E30*MAX(0,MIN(I$5+1,$G30)-MAX(I$5,$F30)) -> 0 | J30: =$E30*MAX(0,MIN(J$5+1,$G30)-MAX(J$5,$F30)) -> 0 | K30: =$E30*MAX(0,MIN(K$5+1,$G30)-MAX(K$5,$F30)) -> 583.8 | L30: =$E30*MAX(0,MIN(L$5+1,$G30)-MAX(L$5,$F30)) -> 1390 | M30: =$E30*MAX(0,MIN(M$5+1,$G30)-MAX(M$5,$F30)) -> 1390 | N30: =$E30*MAX(0,MIN(N$5+1,$G30)-MAX(N$5,$F30)) -> 1390
B31: Oceania Sonata class #2 | C31: Oceania | D31: Sonata; 1,390 berths (10-Q); 2029 date assumed | E31: 1390 | F31: 2029.5 | G31: 2099 | H31: =$E31*MAX(0,MIN(H$5+1,$G31)-MAX(H$5,$F31)) -> 0 | I31: =$E31*MAX(0,MIN(I$5+1,$G31)-MAX(I$5,$F31)) -> 0 | J31: =$E31*MAX(0,MIN(J$5+1,$G31)-MAX(J$5,$F31)) -> 0 | K31: =$E31*MAX(0,MIN(K$5+1,$G31)-MAX(K$5,$F31)) -> 0 | L31: =$E31*MAX(0,MIN(L$5+1,$G31)-MAX(L$5,$F31)) -> 0 | M31: =$E31*MAX(0,MIN(M$5+1,$G31)-MAX(M$5,$F31)) -> 695 | N31: =$E31*MAX(0,MIN(N$5+1,$G31)-MAX(N$5,$F31)) -> 1390
B32: Oceania Allura | C32: Oceania | D32: Allura; 1,200 berths (FY24 10-K); delivered 2025 | E32: 1200 | F32: 2025.55 | G32: 2099 | H32: =$E32*MAX(0,MIN(H$5+1,$G32)-MAX(H$5,$F32)) -> 0 | I32: =$E32*MAX(0,MIN(I$5+1,$G32)-MAX(I$5,$F32)) -> 540 | J32: =$E32*MAX(0,MIN(J$5+1,$G32)-MAX(J$5,$F32)) -> 1200 | K32: =$E32*MAX(0,MIN(K$5+1,$G32)-MAX(K$5,$F32)) -> 1200 | L32: =$E32*MAX(0,MIN(L$5+1,$G32)-MAX(L$5,$F32)) -> 1200 | M32: =$E32*MAX(0,MIN(M$5+1,$G32)-MAX(M$5,$F32)) -> 1200 | N32: =$E32*MAX(0,MIN(N$5+1,$G32)-MAX(N$5,$F32)) -> 1200
B33: Oceania Vista | C33: Oceania | D33: Allura | E33: =1200*$E$3 -> 1187.1467 | F33: 2000 | G33: 2099 | H33: =$E33*MAX(0,MIN(H$5+1,$G33)-MAX(H$5,$F33)) -> 1187.1467 | I33: =$E33*MAX(0,MIN(I$5+1,$G33)-MAX(I$5,$F33)) -> 1187.1467 | J33: =$E33*MAX(0,MIN(J$5+1,$G33)-MAX(J$5,$F33)) -> 1187.1467 | K33: =$E33*MAX(0,MIN(K$5+1,$G33)-MAX(K$5,$F33)) -> 1187.1467 | L33: =$E33*MAX(0,MIN(L$5+1,$G33)-MAX(L$5,$F33)) -> 1187.1467 | M33: =$E33*MAX(0,MIN(M$5+1,$G33)-MAX(M$5,$F33)) -> 1187.1467 | N33: =$E33*MAX(0,MIN(N$5+1,$G33)-MAX(N$5,$F33)) -> 1187.1467
B34: Oceania Riviera | C34: Oceania | D34: Marina | E34: =1250*$E$3 -> 1236.6111 | F34: 2000 | G34: 2099 | H34: =$E34*MAX(0,MIN(H$5+1,$G34)-MAX(H$5,$F34)) -> 1236.6111 | I34: =$E34*MAX(0,MIN(I$5+1,$G34)-MAX(I$5,$F34)) -> 1236.6111 | J34: =$E34*MAX(0,MIN(J$5+1,$G34)-MAX(J$5,$F34)) -> 1236.6111 | K34: =$E34*MAX(0,MIN(K$5+1,$G34)-MAX(K$5,$F34)) -> 1236.6111 | L34: =$E34*MAX(0,MIN(L$5+1,$G34)-MAX(L$5,$F34)) -> 1236.6111 | M34: =$E34*MAX(0,MIN(M$5+1,$G34)-MAX(M$5,$F34)) -> 1236.6111 | N34: =$E34*MAX(0,MIN(N$5+1,$G34)-MAX(N$5,$F34)) -> 1236.6111
B35: Oceania Marina | C35: Oceania | D35: Marina | E35: =1250*$E$3 -> 1236.6111 | F35: 2000 | G35: 2099 | H35: =$E35*MAX(0,MIN(H$5+1,$G35)-MAX(H$5,$F35)) -> 1236.6111 | I35: =$E35*MAX(0,MIN(I$5+1,$G35)-MAX(I$5,$F35)) -> 1236.6111 | J35: =$E35*MAX(0,MIN(J$5+1,$G35)-MAX(J$5,$F35)) -> 1236.6111 | K35: =$E35*MAX(0,MIN(K$5+1,$G35)-MAX(K$5,$F35)) -> 1236.6111 | L35: =$E35*MAX(0,MIN(L$5+1,$G35)-MAX(L$5,$F35)) -> 1236.6111 | M35: =$E35*MAX(0,MIN(M$5+1,$G35)-MAX(M$5,$F35)) -> 1236.6111 | N35: =$E35*MAX(0,MIN(N$5+1,$G35)-MAX(N$5,$F35)) -> 1236.6111
B36: Oceania Sirena | C36: Oceania | D36: Sold 3Q26, chartered back (10-Q) | E36: 684 | F36: 2000 | G36: 2099 | H36: =$E36*MAX(0,MIN(H$5+1,$G36)-MAX(H$5,$F36)) -> 684 | I36: =$E36*MAX(0,MIN(I$5+1,$G36)-MAX(I$5,$F36)) -> 684 | J36: =$E36*MAX(0,MIN(J$5+1,$G36)-MAX(J$5,$F36)) -> 684 | K36: =$E36*MAX(0,MIN(K$5+1,$G36)-MAX(K$5,$F36)) -> 684 | L36: =$E36*MAX(0,MIN(L$5+1,$G36)-MAX(L$5,$F36)) -> 684 | M36: =$E36*MAX(0,MIN(M$5+1,$G36)-MAX(M$5,$F36)) -> 684 | N36: =$E36*MAX(0,MIN(N$5+1,$G36)-MAX(N$5,$F36)) -> 684
B37: Oceania Nautica | C37: Oceania | D37: R-class | E37: =684*$E$3 -> 676.67361 | F37: 2000 | G37: 2099 | H37: =$E37*MAX(0,MIN(H$5+1,$G37)-MAX(H$5,$F37)) -> 676.67361 | I37: =$E37*MAX(0,MIN(I$5+1,$G37)-MAX(I$5,$F37)) -> 676.67361 | J37: =$E37*MAX(0,MIN(J$5+1,$G37)-MAX(J$5,$F37)) -> 676.67361 | K37: =$E37*MAX(0,MIN(K$5+1,$G37)-MAX(K$5,$F37)) -> 676.67361 | L37: =$E37*MAX(0,MIN(L$5+1,$G37)-MAX(L$5,$F37)) -> 676.67361 | M37: =$E37*MAX(0,MIN(M$5+1,$G37)-MAX(M$5,$F37)) -> 676.67361 | N37: =$E37*MAX(0,MIN(N$5+1,$G37)-MAX(N$5,$F37)) -> 676.67361
B38: Oceania Regatta | C38: Oceania | D38: R-class | E38: =684*$E$3 -> 676.67361 | F38: 2000 | G38: 2099 | H38: =$E38*MAX(0,MIN(H$5+1,$G38)-MAX(H$5,$F38)) -> 676.67361 | I38: =$E38*MAX(0,MIN(I$5+1,$G38)-MAX(I$5,$F38)) -> 676.67361 | J38: =$E38*MAX(0,MIN(J$5+1,$G38)-MAX(J$5,$F38)) -> 676.67361 | K38: =$E38*MAX(0,MIN(K$5+1,$G38)-MAX(K$5,$F38)) -> 676.67361 | L38: =$E38*MAX(0,MIN(L$5+1,$G38)-MAX(L$5,$F38)) -> 676.67361 | M38: =$E38*MAX(0,MIN(M$5+1,$G38)-MAX(M$5,$F38)) -> 676.67361 | N38: =$E38*MAX(0,MIN(N$5+1,$G38)-MAX(N$5,$F38)) -> 676.67361
B39: Oceania Insignia | C39: Oceania | D39: R-class | E39: =684*$E$3 -> 676.67361 | F39: 2000 | G39: 2099 | H39: =$E39*MAX(0,MIN(H$5+1,$G39)-MAX(H$5,$F39)) -> 676.67361 | I39: =$E39*MAX(0,MIN(I$5+1,$G39)-MAX(I$5,$F39)) -> 676.67361 | J39: =$E39*MAX(0,MIN(J$5+1,$G39)-MAX(J$5,$F39)) -> 676.67361 | K39: =$E39*MAX(0,MIN(K$5+1,$G39)-MAX(K$5,$F39)) -> 676.67361 | L39: =$E39*MAX(0,MIN(L$5+1,$G39)-MAX(L$5,$F39)) -> 676.67361 | M39: =$E39*MAX(0,MIN(M$5+1,$G39)-MAX(M$5,$F39)) -> 676.67361 | N39: =$E39*MAX(0,MIN(N$5+1,$G39)-MAX(N$5,$F39)) -> 676.67361
B40: Seven Seas Prestige | C40: Regent | D40: Prestige; 822 berths (10-Q); month assumed | E40: 822 | F40: 2026.96 | G40: 2099 | H40: =$E40*MAX(0,MIN(H$5+1,$G40)-MAX(H$5,$F40)) -> 0 | I40: =$E40*MAX(0,MIN(I$5+1,$G40)-MAX(I$5,$F40)) -> 0 | J40: =$E40*MAX(0,MIN(J$5+1,$G40)-MAX(J$5,$F40)) -> 32.88 | K40: =$E40*MAX(0,MIN(K$5+1,$G40)-MAX(K$5,$F40)) -> 822 | L40: =$E40*MAX(0,MIN(L$5+1,$G40)-MAX(L$5,$F40)) -> 822 | M40: =$E40*MAX(0,MIN(M$5+1,$G40)-MAX(M$5,$F40)) -> 822 | N40: =$E40*MAX(0,MIN(N$5+1,$G40)-MAX(N$5,$F40)) -> 822
B41: Regent Prestige class #2 | C41: Regent | D41: Prestige; 822 berths (10-Q); 2029 per FY24 10-K, assumed | E41: 822 | F41: 2029.5 | G41: 2099 | H41: =$E41*MAX(0,MIN(H$5+1,$G41)-MAX(H$5,$F41)) -> 0 | I41: =$E41*MAX(0,MIN(I$5+1,$G41)-MAX(I$5,$F41)) -> 0 | J41: =$E41*MAX(0,MIN(J$5+1,$G41)-MAX(J$5,$F41)) -> 0 | K41: =$E41*MAX(0,MIN(K$5+1,$G41)-MAX(K$5,$F41)) -> 0 | L41: =$E41*MAX(0,MIN(L$5+1,$G41)-MAX(L$5,$F41)) -> 0 | M41: =$E41*MAX(0,MIN(M$5+1,$G41)-MAX(M$5,$F41)) -> 411 | N41: =$E41*MAX(0,MIN(N$5+1,$G41)-MAX(N$5,$F41)) -> 822
B42: Seven Seas Grandeur | C42: Regent | D42: Explorer | E42: =746*$E$3 -> 738.00952 | F42: 2000 | G42: 2099 | H42: =$E42*MAX(0,MIN(H$5+1,$G42)-MAX(H$5,$F42)) -> 738.00952 | I42: =$E42*MAX(0,MIN(I$5+1,$G42)-MAX(I$5,$F42)) -> 738.00952 | J42: =$E42*MAX(0,MIN(J$5+1,$G42)-MAX(J$5,$F42)) -> 738.00952 | K42: =$E42*MAX(0,MIN(K$5+1,$G42)-MAX(K$5,$F42)) -> 738.00952 | L42: =$E42*MAX(0,MIN(L$5+1,$G42)-MAX(L$5,$F42)) -> 738.00952 | M42: =$E42*MAX(0,MIN(M$5+1,$G42)-MAX(M$5,$F42)) -> 738.00952 | N42: =$E42*MAX(0,MIN(N$5+1,$G42)-MAX(N$5,$F42)) -> 738.00952
B43: Seven Seas Splendor | C43: Regent | D43: Explorer | E43: =750*$E$3 -> 741.96668 | F43: 2000 | G43: 2099 | H43: =$E43*MAX(0,MIN(H$5+1,$G43)-MAX(H$5,$F43)) -> 741.96668 | I43: =$E43*MAX(0,MIN(I$5+1,$G43)-MAX(I$5,$F43)) -> 741.96668 | J43: =$E43*MAX(0,MIN(J$5+1,$G43)-MAX(J$5,$F43)) -> 741.96668 | K43: =$E43*MAX(0,MIN(K$5+1,$G43)-MAX(K$5,$F43)) -> 741.96668 | L43: =$E43*MAX(0,MIN(L$5+1,$G43)-MAX(L$5,$F43)) -> 741.96668 | M43: =$E43*MAX(0,MIN(M$5+1,$G43)-MAX(M$5,$F43)) -> 741.96668 | N43: =$E43*MAX(0,MIN(N$5+1,$G43)-MAX(N$5,$F43)) -> 741.96668
B44: Seven Seas Explorer | C44: Regent | D44: Explorer | E44: =750*$E$3 -> 741.96668 | F44: 2000 | G44: 2099 | H44: =$E44*MAX(0,MIN(H$5+1,$G44)-MAX(H$5,$F44)) -> 741.96668 | I44: =$E44*MAX(0,MIN(I$5+1,$G44)-MAX(I$5,$F44)) -> 741.96668 | J44: =$E44*MAX(0,MIN(J$5+1,$G44)-MAX(J$5,$F44)) -> 741.96668 | K44: =$E44*MAX(0,MIN(K$5+1,$G44)-MAX(K$5,$F44)) -> 741.96668 | L44: =$E44*MAX(0,MIN(L$5+1,$G44)-MAX(L$5,$F44)) -> 741.96668 | M44: =$E44*MAX(0,MIN(M$5+1,$G44)-MAX(M$5,$F44)) -> 741.96668 | N44: =$E44*MAX(0,MIN(N$5+1,$G44)-MAX(N$5,$F44)) -> 741.96668
B45: Seven Seas Voyager | C45: Regent | D45: Voyager | E45: =700*$E$3 -> 692.50223 | F45: 2000 | G45: 2099 | H45: =$E45*MAX(0,MIN(H$5+1,$G45)-MAX(H$5,$F45)) -> 692.50223 | I45: =$E45*MAX(0,MIN(I$5+1,$G45)-MAX(I$5,$F45)) -> 692.50223 | J45: =$E45*MAX(0,MIN(J$5+1,$G45)-MAX(J$5,$F45)) -> 692.50223 | K45: =$E45*MAX(0,MIN(K$5+1,$G45)-MAX(K$5,$F45)) -> 692.50223 | L45: =$E45*MAX(0,MIN(L$5+1,$G45)-MAX(L$5,$F45)) -> 692.50223 | M45: =$E45*MAX(0,MIN(M$5+1,$G45)-MAX(M$5,$F45)) -> 692.50223 | N45: =$E45*MAX(0,MIN(N$5+1,$G45)-MAX(N$5,$F45)) -> 692.50223
B46: Seven Seas Mariner | C46: Regent | D46: Mariner | E46: =700*$E$3 -> 692.50223 | F46: 2000 | G46: 2099 | H46: =$E46*MAX(0,MIN(H$5+1,$G46)-MAX(H$5,$F46)) -> 692.50223 | I46: =$E46*MAX(0,MIN(I$5+1,$G46)-MAX(I$5,$F46)) -> 692.50223 | J46: =$E46*MAX(0,MIN(J$5+1,$G46)-MAX(J$5,$F46)) -> 692.50223 | K46: =$E46*MAX(0,MIN(K$5+1,$G46)-MAX(K$5,$F46)) -> 692.50223 | L46: =$E46*MAX(0,MIN(L$5+1,$G46)-MAX(L$5,$F46)) -> 692.50223 | M46: =$E46*MAX(0,MIN(M$5+1,$G46)-MAX(M$5,$F46)) -> 692.50223 | N46: =$E46*MAX(0,MIN(N$5+1,$G46)-MAX(N$5,$F46)) -> 692.50223
B47: Seven Seas Navigator | C47: Regent | D47: Bareboat charter out, late 2027 (10-Q) | E47: 490 | F47: 2000 | G47: 2027.83 | H47: =$E47*MAX(0,MIN(H$5+1,$G47)-MAX(H$5,$F47)) -> 490 | I47: =$E47*MAX(0,MIN(I$5+1,$G47)-MAX(I$5,$F47)) -> 490 | J47: =$E47*MAX(0,MIN(J$5+1,$G47)-MAX(J$5,$F47)) -> 490 | K47: =$E47*MAX(0,MIN(K$5+1,$G47)-MAX(K$5,$F47)) -> 406.7 | L47: =$E47*MAX(0,MIN(L$5+1,$G47)-MAX(L$5,$F47)) -> 0 | M47: =$E47*MAX(0,MIN(M$5+1,$G47)-MAX(M$5,$F47)) -> 0 | N47: =$E47*MAX(0,MIN(N$5+1,$G47)-MAX(N$5,$F47)) -> 0
B49: Berth-years by brand
B50: Norwegian | H50: =SUM(H6:H29) -> 56083.439 | I50: =SUM(I6:I29) -> 58745.939 | J50: =SUM(J6:J29) -> 61966.509 | K50: =SUM(K6:K29) -> 63115.719 | L50: =SUM(L6:L29) -> 65078.439 | M50: =SUM(M6:M29) -> 67018.439 | N50: =SUM(N6:N29) -> 69518.439
B51: Oceania | H51: =SUM(H30:H39) -> 6374.3898 | I51: =SUM(I30:I39) -> 6914.3898 | J51: =SUM(J30:J39) -> 7574.3898 | K51: =SUM(K30:K39) -> 8158.1898 | L51: =SUM(L30:L39) -> 8964.3898 | M51: =SUM(M30:M39) -> 9659.3898 | N51: =SUM(N30:N39) -> 10354.39
B52: Regent | H52: =SUM(H40:H47) -> 4096.9473 | I52: =SUM(I40:I47) -> 4096.9473 | J52: =SUM(J40:J47) -> 4129.8273 | K52: =SUM(K40:K47) -> 4835.6473 | L52: =SUM(L40:L47) -> 4428.9473 | M52: =SUM(M40:M47) -> 4839.9473 | N52: =SUM(N40:N47) -> 5250.9473
B53: Total berth-years | H53: =SUM(H50:H52) -> 66554.777 | I53: =SUM(I50:I52) -> 69757.277 | J53: =SUM(J50:J52) -> 73670.727 | K53: =SUM(K50:K52) -> 76109.557 | L53: =SUM(L50:L52) -> 78471.777 | M53: =SUM(M50:M52) -> 81517.777 | N53: =SUM(N50:N52) -> 85123.777
B54: Prima-class share of Norwegian berth-years (newest ships) | H54: =SUM(H6:H11)/H50 -> 0.10933018 | I54: =SUM(I6:I11)/I50 -> 0.14969737 | J54: =SUM(J6:J11)/J50 -> 0.19938775 | K54: =SUM(K6:K11)/K50 -> 0.24553333 | L54: =SUM(L6:L11)/L50 -> 0.29297895 | M54: =SUM(M6:M11)/M50 -> 0.31344527 | N54: =SUM(N6:N11)/N50 -> 0.30217325
B56: Capacity days: calibration to reported and guided figures
B57: Capacity days, reported / guided (M) | H57: ='Quarterly (A)'!L29 -> 23.4454 | I57: ='Quarterly (A)'!M29 -> 24.4336 | J57: =Consensus!C34 -> 26.25
B58: Capacity days per berth-year (drydocks, repositioning) | H58: =H57*1000000/H53 -> 352.27224 | I58: =I57*1000000/I53 -> 350.26597 | J58: =J57*1000000/J53 -> 356.3152 | K58: =$J$58 -> 356.3152 | L58: =$J$58 -> 356.3152 | M58: =$J$58 -> 356.3152 | N58: =$J$58 -> 356.3152
B59: Fleet-implied capacity days (M) | H59: =H53*H58/1000000 -> 23.4454 | I59: =I53*I58/1000000 -> 24.4336 | J59: =J53*J58/1000000 -> 26.25 | K59: =K53*K58/1000000 -> 27.118992 | L59: =L53*L58/1000000 -> 27.960687 | M59: =M53*M58/1000000 -> 29.046023 | N59: =N53*N58/1000000 -> 30.330896
B60: Capacity growth y/y | I60: =I59/H59-1 -> 0.042148993 | J60: =J59/I59-1 -> 0.074340253 | K60: =K59/J59-1 -> 0.033104465 | L60: =L59/K59-1 -> 0.031037101 | M60: =M59/L59-1 -> 0.038816504 | N60: =N59/M59-1 -> 0.04423575
B61: Net Yield Build capacity days (M) | J61: ='Net Yield Build'!T94 -> 26.249873 | K61: ='Net Yield Build'!U94 -> 27.121933
B62: Net Yield Build less fleet-implied (M) | J62: =J61-J59 -> -0.000126508 | K62: =K61-K59 -> 0.0029409039
B63: Fleet berths reported: YE2024 (10-K) / YE2025 (10-K) / Jun 30, 2026 (10-Q) | H63: 66500 | I63: 71400 | J63: 75000
B64: Model berths in service at the same dates | H64: =SUMPRODUCT(($F$6:$F$47<=2025)*($G$6:$G$47>2025)*$E$6:$E$47)-SUMPRODUCT(($F$6:$F$47>2024.99)*($F$6:$F$47<=2025)*$E$6:$E$47) -> 66554.777 | I64: =SUMPRODUCT(($F$6:$F$47<=2026)*($G$6:$G$47>2026)*$E$6:$E$47) -> 71304.777 | J64: =SUMPRODUCT(($F$6:$F$47<=2026.5)*($G$6:$G$47>2026.5)*$E$6:$E$47) -> 74869.777
B66: Source: NCLH 10-K FY2024 and FY2025 (fleet lists, fleet berth totals, class berths), 2Q26 10-Q (orderbook, charters, Sirena sale). Per-ship berths of existing ships are not disclosed: approximate, scaled to the 10-K total. Delivery months and post-2027 delivery years are assumptions.

Sheet Fleet Qtr Build
B2: Fleet Qtr Build: capacity days by ship and quarter (bottom-up quarterly capacity growth)
B3: One row per ship per quarter (rows 21-524). Capacity days = berths x years in service during the quarter x capacity days per berth-year (Fleet Build K58). Delivery and exit dates come from Fleet Build. 2027 y/y growth (row 12) feeds the Net Yield Build; 3Q-4Q26 stay on company guidance.
B5: Quarter | D5: 1Q25 | E5: 2Q25 | F5: 3Q25 | G5: 4Q25 | H5: 1Q26 | I5: 2Q26 | J5: 3Q26 | K5: 4Q26 | L5: 1Q27 | M5: 2Q27 | N5: 3Q27 | O5: 4Q27
B6: Quarter start (year) | D6: 2025 | E6: 2025.25 | F6: 2025.5 | G6: 2025.75 | H6: 2026 | I6: 2026.25 | J6: 2026.5 | K6: 2026.75 | L6: 2027 | M6: 2027.25 | N6: 2027.5 | O6: 2027.75
B7: Capacity days, total (M) | D7: =SUMIFS($K$21:$K$524,$D$21:$D$524,D$5) -> 5.9286197 | E7: =SUMIFS($K$21:$K$524,$D$21:$D$524,E$5) -> 6.2448494 | F7: =SUMIFS($K$21:$K$524,$D$21:$D$524,F$5) -> 6.3303651 | G7: =SUMIFS($K$21:$K$524,$D$21:$D$524,G$5) -> 6.351744 | H7: =SUMIFS($K$21:$K$524,$D$21:$D$524,H$5) -> 6.351744 | I7: =SUMIFS($K$21:$K$524,$D$21:$D$524,I$5) -> 6.6693099 | J7: =SUMIFS($K$21:$K$524,$D$21:$D$524,J$5) -> 6.6693099 | K7: =SUMIFS($K$21:$K$524,$D$21:$D$524,K$5) -> 6.5596361 | ... O7: =SUMIFS($K$21:$K$524,$D$21:$D$524,O$5) -> 6.8865126
B8: Norwegian (M) | D8: =SUMIFS($K$21:$K$524,$D$21:$D$524,D$5,$C$21:$C$524,"Norwegian") -> 4.9958455 | E8: =SUMIFS($K$21:$K$524,$D$21:$D$524,E$5,$C$21:$C$524,"Norwegian") -> 5.3120753 | F8: =SUMIFS($K$21:$K$524,$D$21:$D$524,F$5,$C$21:$C$524,"Norwegian") -> 5.3120753 | G8: =SUMIFS($K$21:$K$524,$D$21:$D$524,G$5,$C$21:$C$524,"Norwegian") -> 5.3120753 | H8: =SUMIFS($K$21:$K$524,$D$21:$D$524,H$5,$C$21:$C$524,"Norwegian") -> 5.3120753 | I8: =SUMIFS($K$21:$K$524,$D$21:$D$524,I$5,$C$21:$C$524,"Norwegian") -> 5.6296412 | J8: =SUMIFS($K$21:$K$524,$D$21:$D$524,J$5,$C$21:$C$524,"Norwegian") -> 5.6296412 | K8: =SUMIFS($K$21:$K$524,$D$21:$D$524,K$5,$C$21:$C$524,"Norwegian") -> 5.5082518 | ... O8: =SUMIFS($K$21:$K$524,$D$21:$D$524,O$5,$C$21:$C$524,"Norwegian") -> 5.6794826
B9: Oceania (M) | D9: =SUMIFS($K$21:$K$524,$D$21:$D$524,D$5,$C$21:$C$524,"Oceania") -> 0.567823 | E9: =SUMIFS($K$21:$K$524,$D$21:$D$524,E$5,$C$21:$C$524,"Oceania") -> 0.567823 | F9: =SUMIFS($K$21:$K$524,$D$21:$D$524,F$5,$C$21:$C$524,"Oceania") -> 0.65333865 | G9: =SUMIFS($K$21:$K$524,$D$21:$D$524,G$5,$C$21:$C$524,"Oceania") -> 0.67471756 | H9: =SUMIFS($K$21:$K$524,$D$21:$D$524,H$5,$C$21:$C$524,"Oceania") -> 0.67471756 | I9: =SUMIFS($K$21:$K$524,$D$21:$D$524,I$5,$C$21:$C$524,"Oceania") -> 0.67471756 | J9: =SUMIFS($K$21:$K$524,$D$21:$D$524,J$5,$C$21:$C$524,"Oceania") -> 0.67471756 | K9: =SUMIFS($K$21:$K$524,$D$21:$D$524,K$5,$C$21:$C$524,"Oceania") -> 0.67471756 | ... O9: =SUMIFS($K$21:$K$524,$D$21:$D$524,O$5,$C$21:$C$524,"Oceania") -> 0.79853709
B10: Regent (M) | D10: =SUMIFS($K$21:$K$524,$D$21:$D$524,D$5,$C$21:$C$524,"Regent") -> 0.36495116 | E10: =SUMIFS($K$21:$K$524,$D$21:$D$524,E$5,$C$21:$C$524,"Regent") -> 0.36495116 | F10: =SUMIFS($K$21:$K$524,$D$21:$D$524,F$5,$C$21:$C$524,"Regent") -> 0.36495116 | G10: =SUMIFS($K$21:$K$524,$D$21:$D$524,G$5,$C$21:$C$524,"Regent") -> 0.36495116 | H10: =SUMIFS($K$21:$K$524,$D$21:$D$524,H$5,$C$21:$C$524,"Regent") -> 0.36495116 | I10: =SUMIFS($K$21:$K$524,$D$21:$D$524,I$5,$C$21:$C$524,"Regent") -> 0.36495116 | J10: =SUMIFS($K$21:$K$524,$D$21:$D$524,J$5,$C$21:$C$524,"Regent") -> 0.36495116 | K10: =SUMIFS($K$21:$K$524,$D$21:$D$524,K$5,$C$21:$C$524,"Regent") -> 0.3766668 | ... O10: =SUMIFS($K$21:$K$524,$D$21:$D$524,O$5,$C$21:$C$524,"Regent") -> 0.40849288
B11: Luxury (Oceania + Regent) share of capacity | D11: =(D9+D10)/D7 -> 0.15733412 | E11: =(E9+E10)/E7 -> 0.14936696 | F11: =(F9+F10)/F7 -> 0.16085799 | G11: =(G9+G10)/G7 -> 0.1636824 | H11: =(H9+H10)/H7 -> 0.1636824 | I11: =(I9+I10)/I7 -> 0.1558885 | J11: =(J9+J10)/J7 -> 0.1558885 | K11: =(K9+K10)/K7 -> 0.1602809 | ... O11: =(O9+O10)/O7 -> 0.17527449
B12: Capacity growth y/y | H12: =H7/D7-1 -> 0.071369784 | I12: =I7/E7-1 -> 0.067969691 | J12: =J7/F7-1 -> 0.0535427 | K12: =K7/G7-1 -> 0.032729925 | L12: =L7/H7-1 -> 0.033419921 | M12: =M7/I7-1 -> 0.00079604886 | N12: =N7/J7-1 -> 0.04866049 | O12: =O7/K7-1 -> 0.04983149
B13: Reported capacity days (M), for reference | D13: ='Quarterly (A)'!E29 -> 5.7006 | E13: ='Quarterly (A)'!F29 -> 6.0523 | F13: ='Quarterly (A)'!G29 -> 6.4176 | G13: ='Quarterly (A)'!H29 -> 6.2631 | H13: ='Quarterly (A)'!I29 -> 6.393 | I13: ='Quarterly (A)'!J29 -> 6.5897
B15: Fleet-implied 2027 capacity days (M) vs. Net Yield Build | D15: =SUM(L7:O7) -> 27.118992 | E15: ='Net Yield Build'!U94 -> 27.121933 | F15: The quarterly build uses the 2026-27 days-per-berth-year, so only y/y growth (not levels) feeds the model.
B20: Ship | C20: Brand | D20: Quarter | E20: Q start | F20: Q end | G20: Berths | H20: In service | I20: Out of service | J20: Years in service in quarter | K20: Capacity days (M)
B21: ='Fleet Build'!B6 -> Norwegian Aura | C21: ='Fleet Build'!C6 -> Norwegian | D21: 1Q25 | E21: =D$6 -> 2025 | F21: =E21+0.25 -> 2025.25 | G21: ='Fleet Build'!E6 -> 3880 | H21: ='Fleet Build'!F6 -> 2027.42 | I21: ='Fleet Build'!G6 -> 2099 | J21: =MAX(0,MIN(F21,I21)-MAX(E21,H21)) -> 0 | K21: =G21*J21*'Fleet Build'!$K$58/1000000 -> 0
B22: ='Fleet Build'!B6 -> Norwegian Aura | C22: ='Fleet Build'!C6 -> Norwegian | D22: 2Q25 | E22: =E$6 -> 2025.25 | F22: =E22+0.25 -> 2025.5 | G22: ='Fleet Build'!E6 -> 3880 | H22: ='Fleet Build'!F6 -> 2027.42 | I22: ='Fleet Build'!G6 -> 2099 | J22: =MAX(0,MIN(F22,I22)-MAX(E22,H22)) -> 0 | K22: =G22*J22*'Fleet Build'!$K$58/1000000 -> 0
B23: ='Fleet Build'!B6 -> Norwegian Aura | C23: ='Fleet Build'!C6 -> Norwegian | D23: 3Q25 | E23: =F$6 -> 2025.5 | F23: =E23+0.25 -> 2025.75 | G23: ='Fleet Build'!E6 -> 3880 | H23: ='Fleet Build'!F6 -> 2027.42 | I23: ='Fleet Build'!G6 -> 2099 | J23: =MAX(0,MIN(F23,I23)-MAX(E23,H23)) -> 0 | K23: =G23*J23*'Fleet Build'!$K$58/1000000 -> 0
B24: ='Fleet Build'!B6 -> Norwegian Aura | C24: ='Fleet Build'!C6 -> Norwegian | D24: 4Q25 | E24: =G$6 -> 2025.75 | F24: =E24+0.25 -> 2026 | G24: ='Fleet Build'!E6 -> 3880 | H24: ='Fleet Build'!F6 -> 2027.42 | I24: ='Fleet Build'!G6 -> 2099 | J24: =MAX(0,MIN(F24,I24)-MAX(E24,H24)) -> 0 | K24: =G24*J24*'Fleet Build'!$K$58/1000000 -> 0
B25: ='Fleet Build'!B6 -> Norwegian Aura | C25: ='Fleet Build'!C6 -> Norwegian | D25: 1Q26 | E25: =H$6 -> 2026 | F25: =E25+0.25 -> 2026.25 | G25: ='Fleet Build'!E6 -> 3880 | H25: ='Fleet Build'!F6 -> 2027.42 | I25: ='Fleet Build'!G6 -> 2099 | J25: =MAX(0,MIN(F25,I25)-MAX(E25,H25)) -> 0 | K25: =G25*J25*'Fleet Build'!$K$58/1000000 -> 0
B26: ='Fleet Build'!B6 -> Norwegian Aura | C26: ='Fleet Build'!C6 -> Norwegian | D26: 2Q26 | E26: =I$6 -> 2026.25 | F26: =E26+0.25 -> 2026.5 | G26: ='Fleet Build'!E6 -> 3880 | H26: ='Fleet Build'!F6 -> 2027.42 | I26: ='Fleet Build'!G6 -> 2099 | J26: =MAX(0,MIN(F26,I26)-MAX(E26,H26)) -> 0 | K26: =G26*J26*'Fleet Build'!$K$58/1000000 -> 0
B27: ='Fleet Build'!B6 -> Norwegian Aura | C27: ='Fleet Build'!C6 -> Norwegian | D27: 3Q26 | E27: =J$6 -> 2026.5 | F27: =E27+0.25 -> 2026.75 | G27: ='Fleet Build'!E6 -> 3880 | H27: ='Fleet Build'!F6 -> 2027.42 | I27: ='Fleet Build'!G6 -> 2099 | J27: =MAX(0,MIN(F27,I27)-MAX(E27,H27)) -> 0 | K27: =G27*J27*'Fleet Build'!$K$58/1000000 -> 0
B28: ='Fleet Build'!B6 -> Norwegian Aura | C28: ='Fleet Build'!C6 -> Norwegian | D28: 4Q26 | E28: =K$6 -> 2026.75 | F28: =E28+0.25 -> 2027 | G28: ='Fleet Build'!E6 -> 3880 | H28: ='Fleet Build'!F6 -> 2027.42 | I28: ='Fleet Build'!G6 -> 2099 | J28: =MAX(0,MIN(F28,I28)-MAX(E28,H28)) -> 0 | K28: =G28*J28*'Fleet Build'!$K$58/1000000 -> 0
B29: ='Fleet Build'!B6 -> Norwegian Aura | C29: ='Fleet Build'!C6 -> Norwegian | D29: 1Q27 | E29: =L$6 -> 2027 | F29: =E29+0.25 -> 2027.25 | G29: ='Fleet Build'!E6 -> 3880 | H29: ='Fleet Build'!F6 -> 2027.42 | I29: ='Fleet Build'!G6 -> 2099 | J29: =MAX(0,MIN(F29,I29)-MAX(E29,H29)) -> 0 | K29: =G29*J29*'Fleet Build'!$K$58/1000000 -> 0
B30: ='Fleet Build'!B6 -> Norwegian Aura | C30: ='Fleet Build'!C6 -> Norwegian | D30: 2Q27 | E30: =M$6 -> 2027.25 | F30: =E30+0.25 -> 2027.5 | G30: ='Fleet Build'!E6 -> 3880 | H30: ='Fleet Build'!F6 -> 2027.42 | I30: ='Fleet Build'!G6 -> 2099 | J30: =MAX(0,MIN(F30,I30)-MAX(E30,H30)) -> 0.08 | K30: =G30*J30*'Fleet Build'!$K$58/1000000 -> 0.11060024
B31: ='Fleet Build'!B6 -> Norwegian Aura | C31: ='Fleet Build'!C6 -> Norwegian | D31: 3Q27 | E31: =N$6 -> 2027.5 | F31: =E31+0.25 -> 2027.75 | G31: ='Fleet Build'!E6 -> 3880 | H31: ='Fleet Build'!F6 -> 2027.42 | I31: ='Fleet Build'!G6 -> 2099 | J31: =MAX(0,MIN(F31,I31)-MAX(E31,H31)) -> 0.25 | K31: =G31*J31*'Fleet Build'!$K$58/1000000 -> 0.34562575
B32: ='Fleet Build'!B6 -> Norwegian Aura | C32: ='Fleet Build'!C6 -> Norwegian | D32: 4Q27 | E32: =O$6 -> 2027.75 | F32: =E32+0.25 -> 2028 | G32: ='Fleet Build'!E6 -> 3880 | H32: ='Fleet Build'!F6 -> 2027.42 | I32: ='Fleet Build'!G6 -> 2099 | J32: =MAX(0,MIN(F32,I32)-MAX(E32,H32)) -> 0.25 | K32: =G32*J32*'Fleet Build'!$K$58/1000000 -> 0.34562575
B33: ='Fleet Build'!B7 -> Norwegian Prima Plus #6 | C33: ='Fleet Build'!C7 -> Norwegian | D33: 1Q25 | E33: =D$6 -> 2025 | F33: =E33+0.25 -> 2025.25 | G33: ='Fleet Build'!E7 -> 3880 | H33: ='Fleet Build'!F7 -> 2028.5 | I33: ='Fleet Build'!G7 -> 2099 | J33: =MAX(0,MIN(F33,I33)-MAX(E33,H33)) -> 0 | K33: =G33*J33*'Fleet Build'!$K$58/1000000 -> 0
B34: ='Fleet Build'!B7 -> Norwegian Prima Plus #6 | C34: ='Fleet Build'!C7 -> Norwegian | D34: 2Q25 | E34: =E$6 -> 2025.25 | F34: =E34+0.25 -> 2025.5 | G34: ='Fleet Build'!E7 -> 3880 | H34: ='Fleet Build'!F7 -> 2028.5 | I34: ='Fleet Build'!G7 -> 2099 | J34: =MAX(0,MIN(F34,I34)-MAX(E34,H34)) -> 0 | K34: =G34*J34*'Fleet Build'!$K$58/1000000 -> 0
B35: ='Fleet Build'!B7 -> Norwegian Prima Plus #6 | C35: ='Fleet Build'!C7 -> Norwegian | D35: 3Q25 | E35: =F$6 -> 2025.5 | F35: =E35+0.25 -> 2025.75 | G35: ='Fleet Build'!E7 -> 3880 | H35: ='Fleet Build'!F7 -> 2028.5 | I35: ='Fleet Build'!G7 -> 2099 | J35: =MAX(0,MIN(F35,I35)-MAX(E35,H35)) -> 0 | K35: =G35*J35*'Fleet Build'!$K$58/1000000 -> 0
B36: ='Fleet Build'!B7 -> Norwegian Prima Plus #6 | C36: ='Fleet Build'!C7 -> Norwegian | D36: 4Q25 | E36: =G$6 -> 2025.75 | F36: =E36+0.25 -> 2026 | G36: ='Fleet Build'!E7 -> 3880 | H36: ='Fleet Build'!F7 -> 2028.5 | I36: ='Fleet Build'!G7 -> 2099 | J36: =MAX(0,MIN(F36,I36)-MAX(E36,H36)) -> 0 | K36: =G36*J36*'Fleet Build'!$K$58/1000000 -> 0
B37: ='Fleet Build'!B7 -> Norwegian Prima Plus #6 | C37: ='Fleet Build'!C7 -> Norwegian | D37: 1Q26 | E37: =H$6 -> 2026 | F37: =E37+0.25 -> 2026.25 | G37: ='Fleet Build'!E7 -> 3880 | H37: ='Fleet Build'!F7 -> 2028.5 | I37: ='Fleet Build'!G7 -> 2099 | J37: =MAX(0,MIN(F37,I37)-MAX(E37,H37)) -> 0 | K37: =G37*J37*'Fleet Build'!$K$58/1000000 -> 0
B38: ='Fleet Build'!B7 -> Norwegian Prima Plus #6 | C38: ='Fleet Build'!C7 -> Norwegian | D38: 2Q26 | E38: =I$6 -> 2026.25 | F38: =E38+0.25 -> 2026.5 | G38: ='Fleet Build'!E7 -> 3880 | H38: ='Fleet Build'!F7 -> 2028.5 | I38: ='Fleet Build'!G7 -> 2099 | J38: =MAX(0,MIN(F38,I38)-MAX(E38,H38)) -> 0 | K38: =G38*J38*'Fleet Build'!$K$58/1000000 -> 0
B39: ='Fleet Build'!B7 -> Norwegian Prima Plus #6 | C39: ='Fleet Build'!C7 -> Norwegian | D39: 3Q26 | E39: =J$6 -> 2026.5 | F39: =E39+0.25 -> 2026.75 | G39: ='Fleet Build'!E7 -> 3880 | H39: ='Fleet Build'!F7 -> 2028.5 | I39: ='Fleet Build'!G7 -> 2099 | J39: =MAX(0,MIN(F39,I39)-MAX(E39,H39)) -> 0 | K39: =G39*J39*'Fleet Build'!$K$58/1000000 -> 0
B40: ='Fleet Build'!B7 -> Norwegian Prima Plus #6 | C40: ='Fleet Build'!C7 -> Norwegian | D40: 4Q26 | E40: =K$6 -> 2026.75 | F40: =E40+0.25 -> 2027 | G40: ='Fleet Build'!E7 -> 3880 | H40: ='Fleet Build'!F7 -> 2028.5 | I40: ='Fleet Build'!G7 -> 2099 | J40: =MAX(0,MIN(F40,I40)-MAX(E40,H40)) -> 0 | K40: =G40*J40*'Fleet Build'!$K$58/1000000 -> 0
B41: ='Fleet Build'!B7 -> Norwegian Prima Plus #6 | C41: ='Fleet Build'!C7 -> Norwegian | D41: 1Q27 | E41: =L$6 -> 2027 | F41: =E41+0.25 -> 2027.25 | G41: ='Fleet Build'!E7 -> 3880 | H41: ='Fleet Build'!F7 -> 2028.5 | I41: ='Fleet Build'!G7 -> 2099 | J41: =MAX(0,MIN(F41,I41)-MAX(E41,H41)) -> 0 | K41: =G41*J41*'Fleet Build'!$K$58/1000000 -> 0
B42: ='Fleet Build'!B7 -> Norwegian Prima Plus #6 | C42: ='Fleet Build'!C7 -> Norwegian | D42: 2Q27 | E42: =M$6 -> 2027.25 | F42: =E42+0.25 -> 2027.5 | G42: ='Fleet Build'!E7 -> 3880 | H42: ='Fleet Build'!F7 -> 2028.5 | I42: ='Fleet Build'!G7 -> 2099 | J42: =MAX(0,MIN(F42,I42)-MAX(E42,H42)) -> 0 | K42: =G42*J42*'Fleet Build'!$K$58/1000000 -> 0
B43: ='Fleet Build'!B7 -> Norwegian Prima Plus #6 | C43: ='Fleet Build'!C7 -> Norwegian | D43: 3Q27 | E43: =N$6 -> 2027.5 | F43: =E43+0.25 -> 2027.75 | G43: ='Fleet Build'!E7 -> 3880 | H43: ='Fleet Build'!F7 -> 2028.5 | I43: ='Fleet Build'!G7 -> 2099 | J43: =MAX(0,MIN(F43,I43)-MAX(E43,H43)) -> 0 | K43: =G43*J43*'Fleet Build'!$K$58/1000000 -> 0
B44: ='Fleet Build'!B7 -> Norwegian Prima Plus #6 | C44: ='Fleet Build'!C7 -> Norwegian | D44: 4Q27 | E44: =O$6 -> 2027.75 | F44: =E44+0.25 -> 2028 | G44: ='Fleet Build'!E7 -> 3880 | H44: ='Fleet Build'!F7 -> 2028.5 | I44: ='Fleet Build'!G7 -> 2099 | J44: =MAX(0,MIN(F44,I44)-MAX(E44,H44)) -> 0 | K44: =G44*J44*'Fleet Build'!$K$58/1000000 -> 0
B45: ='Fleet Build'!B8 -> Norwegian Luna | C45: ='Fleet Build'!C8 -> Norwegian | D45: 1Q25 | E45: =D$6 -> 2025 | F45: =E45+0.25 -> 2025.25 | G45: ='Fleet Build'!E8 -> 3565 | H45: ='Fleet Build'!F8 -> 2026.25 | I45: ='Fleet Build'!G8 -> 2099 | J45: =MAX(0,MIN(F45,I45)-MAX(E45,H45)) -> 0 | K45: =G45*J45*'Fleet Build'!$K$58/1000000 -> 0
B46: ='Fleet Build'!B8 -> Norwegian Luna | C46: ='Fleet Build'!C8 -> Norwegian | D46: 2Q25 | E46: =E$6 -> 2025.25 | F46: =E46+0.25 -> 2025.5 | G46: ='Fleet Build'!E8 -> 3565 | H46: ='Fleet Build'!F8 -> 2026.25 | I46: ='Fleet Build'!G8 -> 2099 | J46: =MAX(0,MIN(F46,I46)-MAX(E46,H46)) -> 0 | K46: =G46*J46*'Fleet Build'!$K$58/1000000 -> 0
B47: ='Fleet Build'!B8 -> Norwegian Luna | C47: ='Fleet Build'!C8 -> Norwegian | D47: 3Q25 | E47: =F$6 -> 2025.5 | F47: =E47+0.25 -> 2025.75 | G47: ='Fleet Build'!E8 -> 3565 | H47: ='Fleet Build'!F8 -> 2026.25 | I47: ='Fleet Build'!G8 -> 2099 | J47: =MAX(0,MIN(F47,I47)-MAX(E47,H47)) -> 0 | K47: =G47*J47*'Fleet Build'!$K$58/1000000 -> 0
B48: ='Fleet Build'!B8 -> Norwegian Luna | C48: ='Fleet Build'!C8 -> Norwegian | D48: 4Q25 | E48: =G$6 -> 2025.75 | F48: =E48+0.25 -> 2026 | G48: ='Fleet Build'!E8 -> 3565 | H48: ='Fleet Build'!F8 -> 2026.25 | I48: ='Fleet Build'!G8 -> 2099 | J48: =MAX(0,MIN(F48,I48)-MAX(E48,H48)) -> 0 | K48: =G48*J48*'Fleet Build'!$K$58/1000000 -> 0
B49: ='Fleet Build'!B8 -> Norwegian Luna | C49: ='Fleet Build'!C8 -> Norwegian | D49: 1Q26 | E49: =H$6 -> 2026 | F49: =E49+0.25 -> 2026.25 | G49: ='Fleet Build'!E8 -> 3565 | H49: ='Fleet Build'!F8 -> 2026.25 | I49: ='Fleet Build'!G8 -> 2099 | J49: =MAX(0,MIN(F49,I49)-MAX(E49,H49)) -> 0 | K49: =G49*J49*'Fleet Build'!$K$58/1000000 -> 0
B50: ='Fleet Build'!B8 -> Norwegian Luna | C50: ='Fleet Build'!C8 -> Norwegian | D50: 2Q26 | E50: =I$6 -> 2026.25 | F50: =E50+0.25 -> 2026.5 | G50: ='Fleet Build'!E8 -> 3565 | H50: ='Fleet Build'!F8 -> 2026.25 | I50: ='Fleet Build'!G8 -> 2099 | J50: =MAX(0,MIN(F50,I50)-MAX(E50,H50)) -> 0.25 | K50: =G50*J50*'Fleet Build'!$K$58/1000000 -> 0.31756593
B51: ='Fleet Build'!B8 -> Norwegian Luna | C51: ='Fleet Build'!C8 -> Norwegian | D51: 3Q26 | E51: =J$6 -> 2026.5 | F51: =E51+0.25 -> 2026.75 | G51: ='Fleet Build'!E8 -> 3565 | H51: ='Fleet Build'!F8 -> 2026.25 | I51: ='Fleet Build'!G8 -> 2099 | J51: =MAX(0,MIN(F51,I51)-MAX(E51,H51)) -> 0.25 | K51: =G51*J51*'Fleet Build'!$K$58/1000000 -> 0.31756593
B52: ='Fleet Build'!B8 -> Norwegian Luna | C52: ='Fleet Build'!C8 -> Norwegian | D52: 4Q26 | E52: =K$6 -> 2026.75 | F52: =E52+0.25 -> 2027 | G52: ='Fleet Build'!E8 -> 3565 | H52: ='Fleet Build'!F8 -> 2026.25 | I52: ='Fleet Build'!G8 -> 2099 | J52: =MAX(0,MIN(F52,I52)-MAX(E52,H52)) -> 0.25 | K52: =G52*J52*'Fleet Build'!$K$58/1000000 -> 0.31756593
B53: ='Fleet Build'!B8 -> Norwegian Luna | C53: ='Fleet Build'!C8 -> Norwegian | D53: 1Q27 | E53: =L$6 -> 2027 | F53: =E53+0.25 -> 2027.25 | G53: ='Fleet Build'!E8 -> 3565 | H53: ='Fleet Build'!F8 -> 2026.25 | I53: ='Fleet Build'!G8 -> 2099 | J53: =MAX(0,MIN(F53,I53)-MAX(E53,H53)) -> 0.25 | K53: =G53*J53*'Fleet Build'!$K$58/1000000 -> 0.31756593
B54: ='Fleet Build'!B8 -> Norwegian Luna | C54: ='Fleet Build'!C8 -> Norwegian | D54: 2Q27 | E54: =M$6 -> 2027.25 | F54: =E54+0.25 -> 2027.5 | G54: ='Fleet Build'!E8 -> 3565 | H54: ='Fleet Build'!F8 -> 2026.25 | I54: ='Fleet Build'!G8 -> 2099 | J54: =MAX(0,MIN(F54,I54)-MAX(E54,H54)) -> 0.25 | K54: =G54*J54*'Fleet Build'!$K$58/1000000 -> 0.31756593
B55: ='Fleet Build'!B8 -> Norwegian Luna | C55: ='Fleet Build'!C8 -> Norwegian | D55: 3Q27 | E55: =N$6 -> 2027.5 | F55: =E55+0.25 -> 2027.75 | G55: ='Fleet Build'!E8 -> 3565 | H55: ='Fleet Build'!F8 -> 2026.25 | I55: ='Fleet Build'!G8 -> 2099 | J55: =MAX(0,MIN(F55,I55)-MAX(E55,H55)) -> 0.25 | K55: =G55*J55*'Fleet Build'!$K$58/1000000 -> 0.31756593
B56: ='Fleet Build'!B8 -> Norwegian Luna | C56: ='Fleet Build'!C8 -> Norwegian | D56: 4Q27 | E56: =O$6 -> 2027.75 | F56: =E56+0.25 -> 2028 | G56: ='Fleet Build'!E8 -> 3565 | H56: ='Fleet Build'!F8 -> 2026.25 | I56: ='Fleet Build'!G8 -> 2099 | J56: =MAX(0,MIN(F56,I56)-MAX(E56,H56)) -> 0.25 | K56: =G56*J56*'Fleet Build'!$K$58/1000000 -> 0.31756593
B57: ='Fleet Build'!B9 -> Norwegian Aqua | C57: ='Fleet Build'!C9 -> Norwegian | D57: 1Q25 | E57: =D$6 -> 2025 | F57: =E57+0.25 -> 2025.25 | G57: ='Fleet Build'!E9 -> 3550 | H57: ='Fleet Build'!F9 -> 2025.25 | I57: ='Fleet Build'!G9 -> 2099 | J57: =MAX(0,MIN(F57,I57)-MAX(E57,H57)) -> 0 | K57: =G57*J57*'Fleet Build'!$K$58/1000000 -> 0
B58: ='Fleet Build'!B9 -> Norwegian Aqua | C58: ='Fleet Build'!C9 -> Norwegian | D58: 2Q25 | E58: =E$6 -> 2025.25 | F58: =E58+0.25 -> 2025.5 | G58: ='Fleet Build'!E9 -> 3550 | H58: ='Fleet Build'!F9 -> 2025.25 | I58: ='Fleet Build'!G9 -> 2099 | J58: =MAX(0,MIN(F58,I58)-MAX(E58,H58)) -> 0.25 | K58: =G58*J58*'Fleet Build'!$K$58/1000000 -> 0.31622974
B59: ='Fleet Build'!B9 -> Norwegian Aqua | C59: ='Fleet Build'!C9 -> Norwegian | D59: 3Q25 | E59: =F$6 -> 2025.5 | F59: =E59+0.25 -> 2025.75 | G59: ='Fleet Build'!E9 -> 3550 | H59: ='Fleet Build'!F9 -> 2025.25 | I59: ='Fleet Build'!G9 -> 2099 | J59: =MAX(0,MIN(F59,I59)-MAX(E59,H59)) -> 0.25 | K59: =G59*J59*'Fleet Build'!$K$58/1000000 -> 0.31622974
B60: ='Fleet Build'!B9 -> Norwegian Aqua | C60: ='Fleet Build'!C9 -> Norwegian | D60: 4Q25 | E60: =G$6 -> 2025.75 | F60: =E60+0.25 -> 2026 | G60: ='Fleet Build'!E9 -> 3550 | H60: ='Fleet Build'!F9 -> 2025.25 | I60: ='Fleet Build'!G9 -> 2099 | J60: =MAX(0,MIN(F60,I60)-MAX(E60,H60)) -> 0.25 | K60: =G60*J60*'Fleet Build'!$K$58/1000000 -> 0.31622974
B61: ='Fleet Build'!B9 -> Norwegian Aqua | C61: ='Fleet Build'!C9 -> Norwegian | D61: 1Q26 | E61: =H$6 -> 2026 | F61: =E61+0.25 -> 2026.25 | G61: ='Fleet Build'!E9 -> 3550 | H61: ='Fleet Build'!F9 -> 2025.25 | I61: ='Fleet Build'!G9 -> 2099 | J61: =MAX(0,MIN(F61,I61)-MAX(E61,H61)) -> 0.25 | K61: =G61*J61*'Fleet Build'!$K$58/1000000 -> 0.31622974
B62: ='Fleet Build'!B9 -> Norwegian Aqua | C62: ='Fleet Build'!C9 -> Norwegian | D62: 2Q26 | E62: =I$6 -> 2026.25 | F62: =E62+0.25 -> 2026.5 | G62: ='Fleet Build'!E9 -> 3550 | H62: ='Fleet Build'!F9 -> 2025.25 | I62: ='Fleet Build'!G9 -> 2099 | J62: =MAX(0,MIN(F62,I62)-MAX(E62,H62)) -> 0.25 | K62: =G62*J62*'Fleet Build'!$K$58/1000000 -> 0.31622974
B63: ='Fleet Build'!B9 -> Norwegian Aqua | C63: ='Fleet Build'!C9 -> Norwegian | D63: 3Q26 | E63: =J$6 -> 2026.5 | F63: =E63+0.25 -> 2026.75 | G63: ='Fleet Build'!E9 -> 3550 | H63: ='Fleet Build'!F9 -> 2025.25 | I63: ='Fleet Build'!G9 -> 2099 | J63: =MAX(0,MIN(F63,I63)-MAX(E63,H63)) -> 0.25 | K63: =G63*J63*'Fleet Build'!$K$58/1000000 -> 0.31622974
B64: ='Fleet Build'!B9 -> Norwegian Aqua | C64: ='Fleet Build'!C9 -> Norwegian | D64: 4Q26 | E64: =K$6 -> 2026.75 | F64: =E64+0.25 -> 2027 | G64: ='Fleet Build'!E9 -> 3550 | H64: ='Fleet Build'!F9 -> 2025.25 | I64: ='Fleet Build'!G9 -> 2099 | J64: =MAX(0,MIN(F64,I64)-MAX(E64,H64)) -> 0.25 | K64: =G64*J64*'Fleet Build'!$K$58/1000000 -> 0.31622974
B65: ='Fleet Build'!B9 -> Norwegian Aqua | C65: ='Fleet Build'!C9 -> Norwegian | D65: 1Q27 | E65: =L$6 -> 2027 | F65: =E65+0.25 -> 2027.25 | G65: ='Fleet Build'!E9 -> 3550 | H65: ='Fleet Build'!F9 -> 2025.25 | I65: ='Fleet Build'!G9 -> 2099 | J65: =MAX(0,MIN(F65,I65)-MAX(E65,H65)) -> 0.25 | K65: =G65*J65*'Fleet Build'!$K$58/1000000 -> 0.31622974
B66: ='Fleet Build'!B9 -> Norwegian Aqua | C66: ='Fleet Build'!C9 -> Norwegian | D66: 2Q27 | E66: =M$6 -> 2027.25 | F66: =E66+0.25 -> 2027.5 | G66: ='Fleet Build'!E9 -> 3550 | H66: ='Fleet Build'!F9 -> 2025.25 | I66: ='Fleet Build'!G9 -> 2099 | J66: =MAX(0,MIN(F66,I66)-MAX(E66,H66)) -> 0.25 | K66: =G66*J66*'Fleet Build'!$K$58/1000000 -> 0.31622974
B67: ='Fleet Build'!B9 -> Norwegian Aqua | C67: ='Fleet Build'!C9 -> Norwegian | D67: 3Q27 | E67: =N$6 -> 2027.5 | F67: =E67+0.25 -> 2027.75 | G67: ='Fleet Build'!E9 -> 3550 | H67: ='Fleet Build'!F9 -> 2025.25 | I67: ='Fleet Build'!G9 -> 2099 | J67: =MAX(0,MIN(F67,I67)-MAX(E67,H67)) -> 0.25 | K67: =G67*J67*'Fleet Build'!$K$58/1000000 -> 0.31622974
B68: ='Fleet Build'!B9 -> Norwegian Aqua | C68: ='Fleet Build'!C9 -> Norwegian | D68: 4Q27 | E68: =O$6 -> 2027.75 | F68: =E68+0.25 -> 2028 | G68: ='Fleet Build'!E9 -> 3550 | H68: ='Fleet Build'!F9 -> 2025.25 | I68: ='Fleet Build'!G9 -> 2099 | J68: =MAX(0,MIN(F68,I68)-MAX(E68,H68)) -> 0.25 | K68: =G68*J68*'Fleet Build'!$K$58/1000000 -> 0.31622974
B69: ='Fleet Build'!B10 -> Norwegian Viva | C69: ='Fleet Build'!C10 -> Norwegian | D69: 1Q25 | E69: =D$6 -> 2025 | F69: =E69+0.25 -> 2025.25 | G69: ='Fleet Build'!E10 -> 3065.8063 | H69: ='Fleet Build'!F10 -> 2000 | I69: ='Fleet Build'!G10 -> 2099 | J69: =MAX(0,MIN(F69,I69)-MAX(E69,H69)) -> 0.25 | K69: =G69*J69*'Fleet Build'!$K$58/1000000 -> 0.27309835
B70: ='Fleet Build'!B10 -> Norwegian Viva | C70: ='Fleet Build'!C10 -> Norwegian | D70: 2Q25 | E70: =E$6 -> 2025.25 | F70: =E70+0.25 -> 2025.5 | G70: ='Fleet Build'!E10 -> 3065.8063 | H70: ='Fleet Build'!F10 -> 2000 | I70: ='Fleet Build'!G10 -> 2099 | J70: =MAX(0,MIN(F70,I70)-MAX(E70,H70)) -> 0.25 | K70: =G70*J70*'Fleet Build'!$K$58/1000000 -> 0.27309835
B71: ='Fleet Build'!B10 -> Norwegian Viva | C71: ='Fleet Build'!C10 -> Norwegian | D71: 3Q25 | E71: =F$6 -> 2025.5 | F71: =E71+0.25 -> 2025.75 | G71: ='Fleet Build'!E10 -> 3065.8063 | H71: ='Fleet Build'!F10 -> 2000 | I71: ='Fleet Build'!G10 -> 2099 | J71: =MAX(0,MIN(F71,I71)-MAX(E71,H71)) -> 0.25 | K71: =G71*J71*'Fleet Build'!$K$58/1000000 -> 0.27309835
B72: ='Fleet Build'!B10 -> Norwegian Viva | C72: ='Fleet Build'!C10 -> Norwegian | D72: 4Q25 | E72: =G$6 -> 2025.75 | F72: =E72+0.25 -> 2026 | G72: ='Fleet Build'!E10 -> 3065.8063 | H72: ='Fleet Build'!F10 -> 2000 | I72: ='Fleet Build'!G10 -> 2099 | J72: =MAX(0,MIN(F72,I72)-MAX(E72,H72)) -> 0.25 | K72: =G72*J72*'Fleet Build'!$K$58/1000000 -> 0.27309835
B73: ='Fleet Build'!B10 -> Norwegian Viva | C73: ='Fleet Build'!C10 -> Norwegian | D73: 1Q26 | E73: =H$6 -> 2026 | F73: =E73+0.25 -> 2026.25 | G73: ='Fleet Build'!E10 -> 3065.8063 | H73: ='Fleet Build'!F10 -> 2000 | I73: ='Fleet Build'!G10 -> 2099 | J73: =MAX(0,MIN(F73,I73)-MAX(E73,H73)) -> 0.25 | K73: =G73*J73*'Fleet Build'!$K$58/1000000 -> 0.27309835
B74: ='Fleet Build'!B10 -> Norwegian Viva | C74: ='Fleet Build'!C10 -> Norwegian | D74: 2Q26 | E74: =I$6 -> 2026.25 | F74: =E74+0.25 -> 2026.5 | G74: ='Fleet Build'!E10 -> 3065.8063 | H74: ='Fleet Build'!F10 -> 2000 | I74: ='Fleet Build'!G10 -> 2099 | J74: =MAX(0,MIN(F74,I74)-MAX(E74,H74)) -> 0.25 | K74: =G74*J74*'Fleet Build'!$K$58/1000000 -> 0.27309835
B75: ='Fleet Build'!B10 -> Norwegian Viva | C75: ='Fleet Build'!C10 -> Norwegian | D75: 3Q26 | E75: =J$6 -> 2026.5 | F75: =E75+0.25 -> 2026.75 | G75: ='Fleet Build'!E10 -> 3065.8063 | H75: ='Fleet Build'!F10 -> 2000 | I75: ='Fleet Build'!G10 -> 2099 | J75: =MAX(0,MIN(F75,I75)-MAX(E75,H75)) -> 0.25 | K75: =G75*J75*'Fleet Build'!$K$58/1000000 -> 0.27309835
B76: ='Fleet Build'!B10 -> Norwegian Viva | C76: ='Fleet Build'!C10 -> Norwegian | D76: 4Q26 | E76: =K$6 -> 2026.75 | F76: =E76+0.25 -> 2027 | G76: ='Fleet Build'!E10 -> 3065.8063 | H76: ='Fleet Build'!F10 -> 2000 | I76: ='Fleet Build'!G10 -> 2099 | J76: =MAX(0,MIN(F76,I76)-MAX(E76,H76)) -> 0.25 | K76: =G76*J76*'Fleet Build'!$K$58/1000000 -> 0.27309835
B77: ='Fleet Build'!B10 -> Norwegian Viva | C77: ='Fleet Build'!C10 -> Norwegian | D77: 1Q27 | E77: =L$6 -> 2027 | F77: =E77+0.25 -> 2027.25 | G77: ='Fleet Build'!E10 -> 3065.8063 | H77: ='Fleet Build'!F10 -> 2000 | I77: ='Fleet Build'!G10 -> 2099 | J77: =MAX(0,MIN(F77,I77)-MAX(E77,H77)) -> 0.25 | K77: =G77*J77*'Fleet Build'!$K$58/1000000 -> 0.27309835
B78: ='Fleet Build'!B10 -> Norwegian Viva | C78: ='Fleet Build'!C10 -> Norwegian | D78: 2Q27 | E78: =M$6 -> 2027.25 | F78: =E78+0.25 -> 2027.5 | G78: ='Fleet Build'!E10 -> 3065.8063 | H78: ='Fleet Build'!F10 -> 2000 | I78: ='Fleet Build'!G10 -> 2099 | J78: =MAX(0,MIN(F78,I78)-MAX(E78,H78)) -> 0.25 | K78: =G78*J78*'Fleet Build'!$K$58/1000000 -> 0.27309835
B79: ='Fleet Build'!B10 -> Norwegian Viva | C79: ='Fleet Build'!C10 -> Norwegian | D79: 3Q27 | E79: =N$6 -> 2027.5 | F79: =E79+0.25 -> 2027.75 | G79: ='Fleet Build'!E10 -> 3065.8063 | H79: ='Fleet Build'!F10 -> 2000 | I79: ='Fleet Build'!G10 -> 2099 | J79: =MAX(0,MIN(F79,I79)-MAX(E79,H79)) -> 0.25 | K79: =G79*J79*'Fleet Build'!$K$58/1000000 -> 0.27309835
B80: ='Fleet Build'!B10 -> Norwegian Viva | C80: ='Fleet Build'!C10 -> Norwegian | D80: 4Q27 | E80: =O$6 -> 2027.75 | F80: =E80+0.25 -> 2028 | G80: ='Fleet Build'!E10 -> 3065.8063 | H80: ='Fleet Build'!F10 -> 2000 | I80: ='Fleet Build'!G10 -> 2099 | J80: =MAX(0,MIN(F80,I80)-MAX(E80,H80)) -> 0.25 | K80: =G80*J80*'Fleet Build'!$K$58/1000000 -> 0.27309835
B81: ='Fleet Build'!B11 -> Norwegian Prima | C81: ='Fleet Build'!C11 -> Norwegian | D81: 1Q25 | E81: =D$6 -> 2025 | F81: =E81+0.25 -> 2025.25 | G81: ='Fleet Build'!E11 -> 3065.8063 | H81: ='Fleet Build'!F11 -> 2000 | I81: ='Fleet Build'!G11 -> 2099 | J81: =MAX(0,MIN(F81,I81)-MAX(E81,H81)) -> 0.25 | K81: =G81*J81*'Fleet Build'!$K$58/1000000 -> 0.27309835
B82: ='Fleet Build'!B11 -> Norwegian Prima | C82: ='Fleet Build'!C11 -> Norwegian | D82: 2Q25 | E82: =E$6 -> 2025.25 | F82: =E82+0.25 -> 2025.5 | G82: ='Fleet Build'!E11 -> 3065.8063 | H82: ='Fleet Build'!F11 -> 2000 | I82: ='Fleet Build'!G11 -> 2099 | J82: =MAX(0,MIN(F82,I82)-MAX(E82,H82)) -> 0.25 | K82: =G82*J82*'Fleet Build'!$K$58/1000000 -> 0.27309835
B83: ='Fleet Build'!B11 -> Norwegian Prima | C83: ='Fleet Build'!C11 -> Norwegian | D83: 3Q25 | E83: =F$6 -> 2025.5 | F83: =E83+0.25 -> 2025.75 | G83: ='Fleet Build'!E11 -> 3065.8063 | H83: ='Fleet Build'!F11 -> 2000 | I83: ='Fleet Build'!G11 -> 2099 | J83: =MAX(0,MIN(F83,I83)-MAX(E83,H83)) -> 0.25 | K83: =G83*J83*'Fleet Build'!$K$58/1000000 -> 0.27309835
B84: ='Fleet Build'!B11 -> Norwegian Prima | C84: ='Fleet Build'!C11 -> Norwegian | D84: 4Q25 | E84: =G$6 -> 2025.75 | F84: =E84+0.25 -> 2026 | G84: ='Fleet Build'!E11 -> 3065.8063 | H84: ='Fleet Build'!F11 -> 2000 | I84: ='Fleet Build'!G11 -> 2099 | J84: =MAX(0,MIN(F84,I84)-MAX(E84,H84)) -> 0.25 | K84: =G84*J84*'Fleet Build'!$K$58/1000000 -> 0.27309835
B85: ='Fleet Build'!B11 -> Norwegian Prima | C85: ='Fleet Build'!C11 -> Norwegian | D85: 1Q26 | E85: =H$6 -> 2026 | F85: =E85+0.25 -> 2026.25 | G85: ='Fleet Build'!E11 -> 3065.8063 | H85: ='Fleet Build'!F11 -> 2000 | I85: ='Fleet Build'!G11 -> 2099 | J85: =MAX(0,MIN(F85,I85)-MAX(E85,H85)) -> 0.25 | K85: =G85*J85*'Fleet Build'!$K$58/1000000 -> 0.27309835
B86: ='Fleet Build'!B11 -> Norwegian Prima | C86: ='Fleet Build'!C11 -> Norwegian | D86: 2Q26 | E86: =I$6 -> 2026.25 | F86: =E86+0.25 -> 2026.5 | G86: ='Fleet Build'!E11 -> 3065.8063 | H86: ='Fleet Build'!F11 -> 2000 | I86: ='Fleet Build'!G11 -> 2099 | J86: =MAX(0,MIN(F86,I86)-MAX(E86,H86)) -> 0.25 | K86: =G86*J86*'Fleet Build'!$K$58/1000000 -> 0.27309835
B87: ='Fleet Build'!B11 -> Norwegian Prima | C87: ='Fleet Build'!C11 -> Norwegian | D87: 3Q26 | E87: =J$6 -> 2026.5 | F87: =E87+0.25 -> 2026.75 | G87: ='Fleet Build'!E11 -> 3065.8063 | H87: ='Fleet Build'!F11 -> 2000 | I87: ='Fleet Build'!G11 -> 2099 | J87: =MAX(0,MIN(F87,I87)-MAX(E87,H87)) -> 0.25 | K87: =G87*J87*'Fleet Build'!$K$58/1000000 -> 0.27309835
B88: ='Fleet Build'!B11 -> Norwegian Prima | C88: ='Fleet Build'!C11 -> Norwegian | D88: 4Q26 | E88: =K$6 -> 2026.75 | F88: =E88+0.25 -> 2027 | G88: ='Fleet Build'!E11 -> 3065.8063 | H88: ='Fleet Build'!F11 -> 2000 | I88: ='Fleet Build'!G11 -> 2099 | J88: =MAX(0,MIN(F88,I88)-MAX(E88,H88)) -> 0.25 | K88: =G88*J88*'Fleet Build'!$K$58/1000000 -> 0.27309835
B89: ='Fleet Build'!B11 -> Norwegian Prima | C89: ='Fleet Build'!C11 -> Norwegian | D89: 1Q27 | E89: =L$6 -> 2027 | F89: =E89+0.25 -> 2027.25 | G89: ='Fleet Build'!E11 -> 3065.8063 | H89: ='Fleet Build'!F11 -> 2000 | I89: ='Fleet Build'!G11 -> 2099 | J89: =MAX(0,MIN(F89,I89)-MAX(E89,H89)) -> 0.25 | K89: =G89*J89*'Fleet Build'!$K$58/1000000 -> 0.27309835
B90: ='Fleet Build'!B11 -> Norwegian Prima | C90: ='Fleet Build'!C11 -> Norwegian | D90: 2Q27 | E90: =M$6 -> 2027.25 | F90: =E90+0.25 -> 2027.5 | G90: ='Fleet Build'!E11 -> 3065.8063 | H90: ='Fleet Build'!F11 -> 2000 | I90: ='Fleet Build'!G11 -> 2099 | J90: =MAX(0,MIN(F90,I90)-MAX(E90,H90)) -> 0.25 | K90: =G90*J90*'Fleet Build'!$K$58/1000000 -> 0.27309835
B91: ='Fleet Build'!B11 -> Norwegian Prima | C91: ='Fleet Build'!C11 -> Norwegian | D91: 3Q27 | E91: =N$6 -> 2027.5 | F91: =E91+0.25 -> 2027.75 | G91: ='Fleet Build'!E11 -> 3065.8063 | H91: ='Fleet Build'!F11 -> 2000 | I91: ='Fleet Build'!G11 -> 2099 | J91: =MAX(0,MIN(F91,I91)-MAX(E91,H91)) -> 0.25 | K91: =G91*J91*'Fleet Build'!$K$58/1000000 -> 0.27309835
B92: ='Fleet Build'!B11 -> Norwegian Prima | C92: ='Fleet Build'!C11 -> Norwegian | D92: 4Q27 | E92: =O$6 -> 2027.75 | F92: =E92+0.25 -> 2028 | G92: ='Fleet Build'!E11 -> 3065.8063 | H92: ='Fleet Build'!F11 -> 2000 | I92: ='Fleet Build'!G11 -> 2099 | J92: =MAX(0,MIN(F92,I92)-MAX(E92,H92)) -> 0.25 | K92: =G92*J92*'Fleet Build'!$K$58/1000000 -> 0.27309835
B93: ='Fleet Build'!B12 -> Norwegian new class #1 | C93: ='Fleet Build'!C12 -> Norwegian | D93: 1Q25 | E93: =D$6 -> 2025 | F93: =E93+0.25 -> 2025.25 | G93: ='Fleet Build'!E12 -> 5000 | H93: ='Fleet Build'!F12 -> 2030.5 | I93: ='Fleet Build'!G12 -> 2099 | J93: =MAX(0,MIN(F93,I93)-MAX(E93,H93)) -> 0 | K93: =G93*J93*'Fleet Build'!$K$58/1000000 -> 0
B94: ='Fleet Build'!B12 -> Norwegian new class #1 | C94: ='Fleet Build'!C12 -> Norwegian | D94: 2Q25 | E94: =E$6 -> 2025.25 | F94: =E94+0.25 -> 2025.5 | G94: ='Fleet Build'!E12 -> 5000 | H94: ='Fleet Build'!F12 -> 2030.5 | I94: ='Fleet Build'!G12 -> 2099 | J94: =MAX(0,MIN(F94,I94)-MAX(E94,H94)) -> 0 | K94: =G94*J94*'Fleet Build'!$K$58/1000000 -> 0
B95: ='Fleet Build'!B12 -> Norwegian new class #1 | C95: ='Fleet Build'!C12 -> Norwegian | D95: 3Q25 | E95: =F$6 -> 2025.5 | F95: =E95+0.25 -> 2025.75 | G95: ='Fleet Build'!E12 -> 5000 | H95: ='Fleet Build'!F12 -> 2030.5 | I95: ='Fleet Build'!G12 -> 2099 | J95: =MAX(0,MIN(F95,I95)-MAX(E95,H95)) -> 0 | K95: =G95*J95*'Fleet Build'!$K$58/1000000 -> 0
B96: ='Fleet Build'!B12 -> Norwegian new class #1 | C96: ='Fleet Build'!C12 -> Norwegian | D96: 4Q25 | E96: =G$6 -> 2025.75 | F96: =E96+0.25 -> 2026 | G96: ='Fleet Build'!E12 -> 5000 | H96: ='Fleet Build'!F12 -> 2030.5 | I96: ='Fleet Build'!G12 -> 2099 | J96: =MAX(0,MIN(F96,I96)-MAX(E96,H96)) -> 0 | K96: =G96*J96*'Fleet Build'!$K$58/1000000 -> 0
B97: ='Fleet Build'!B12 -> Norwegian new class #1 | C97: ='Fleet Build'!C12 -> Norwegian | D97: 1Q26 | E97: =H$6 -> 2026 | F97: =E97+0.25 -> 2026.25 | G97: ='Fleet Build'!E12 -> 5000 | H97: ='Fleet Build'!F12 -> 2030.5 | I97: ='Fleet Build'!G12 -> 2099 | J97: =MAX(0,MIN(F97,I97)-MAX(E97,H97)) -> 0 | K97: =G97*J97*'Fleet Build'!$K$58/1000000 -> 0
B98: ='Fleet Build'!B12 -> Norwegian new class #1 | C98: ='Fleet Build'!C12 -> Norwegian | D98: 2Q26 | E98: =I$6 -> 2026.25 | F98: =E98+0.25 -> 2026.5 | G98: ='Fleet Build'!E12 -> 5000 | H98: ='Fleet Build'!F12 -> 2030.5 | I98: ='Fleet Build'!G12 -> 2099 | J98: =MAX(0,MIN(F98,I98)-MAX(E98,H98)) -> 0 | K98: =G98*J98*'Fleet Build'!$K$58/1000000 -> 0
B99: ='Fleet Build'!B12 -> Norwegian new class #1 | C99: ='Fleet Build'!C12 -> Norwegian | D99: 3Q26 | E99: =J$6 -> 2026.5 | F99: =E99+0.25 -> 2026.75 | G99: ='Fleet Build'!E12 -> 5000 | H99: ='Fleet Build'!F12 -> 2030.5 | I99: ='Fleet Build'!G12 -> 2099 | J99: =MAX(0,MIN(F99,I99)-MAX(E99,H99)) -> 0 | K99: =G99*J99*'Fleet Build'!$K$58/1000000 -> 0
B100: ='Fleet Build'!B12 -> Norwegian new class #1 | C100: ='Fleet Build'!C12 -> Norwegian | D100: 4Q26 | E100: =K$6 -> 2026.75 | F100: =E100+0.25 -> 2027 | G100: ='Fleet Build'!E12 -> 5000 | H100: ='Fleet Build'!F12 -> 2030.5 | I100: ='Fleet Build'!G12 -> 2099 | J100: =MAX(0,MIN(F100,I100)-MAX(E100,H100)) -> 0 | K100: =G100*J100*'Fleet Build'!$K$58/1000000 -> 0
B101: ='Fleet Build'!B12 -> Norwegian new class #1 | C101: ='Fleet Build'!C12 -> Norwegian | D101: 1Q27 | E101: =L$6 -> 2027 | F101: =E101+0.25 -> 2027.25 | G101: ='Fleet Build'!E12 -> 5000 | H101: ='Fleet Build'!F12 -> 2030.5 | I101: ='Fleet Build'!G12 -> 2099 | J101: =MAX(0,MIN(F101,I101)-MAX(E101,H101)) -> 0 | K101: =G101*J101*'Fleet Build'!$K$58/1000000 -> 0
B102: ='Fleet Build'!B12 -> Norwegian new class #1 | C102: ='Fleet Build'!C12 -> Norwegian | D102: 2Q27 | E102: =M$6 -> 2027.25 | F102: =E102+0.25 -> 2027.5 | G102: ='Fleet Build'!E12 -> 5000 | H102: ='Fleet Build'!F12 -> 2030.5 | I102: ='Fleet Build'!G12 -> 2099 | J102: =MAX(0,MIN(F102,I102)-MAX(E102,H102)) -> 0 | K102: =G102*J102*'Fleet Build'!$K$58/1000000 -> 0
B103: ='Fleet Build'!B12 -> Norwegian new class #1 | C103: ='Fleet Build'!C12 -> Norwegian | D103: 3Q27 | E103: =N$6 -> 2027.5 | F103: =E103+0.25 -> 2027.75 | G103: ='Fleet Build'!E12 -> 5000 | H103: ='Fleet Build'!F12 -> 2030.5 | I103: ='Fleet Build'!G12 -> 2099 | J103: =MAX(0,MIN(F103,I103)-MAX(E103,H103)) -> 0 | K103: =G103*J103*'Fleet Build'!$K$58/1000000 -> 0
B104: ='Fleet Build'!B12 -> Norwegian new class #1 | C104: ='Fleet Build'!C12 -> Norwegian | D104: 4Q27 | E104: =O$6 -> 2027.75 | F104: =E104+0.25 -> 2028 | G104: ='Fleet Build'!E12 -> 5000 | H104: ='Fleet Build'!F12 -> 2030.5 | I104: ='Fleet Build'!G12 -> 2099 | J104: =MAX(0,MIN(F104,I104)-MAX(E104,H104)) -> 0 | K104: =G104*J104*'Fleet Build'!$K$58/1000000 -> 0
B105: ='Fleet Build'!B13 -> Norwegian Encore | C105: ='Fleet Build'!C13 -> Norwegian | D105: 1Q25 | E105: =D$6 -> 2025 | F105: =E105+0.25 -> 2025.25 | G105: ='Fleet Build'!E13 -> 3955.177 | H105: ='Fleet Build'!F13 -> 2000 | I105: ='Fleet Build'!G13 -> 2099 | J105: =MAX(0,MIN(F105,I105)-MAX(E105,H105)) -> 0.25 | K105: =G105*J105*'Fleet Build'!$K$58/1000000 -> 0.35232243
B106: ='Fleet Build'!B13 -> Norwegian Encore | C106: ='Fleet Build'!C13 -> Norwegian | D106: 2Q25 | E106: =E$6 -> 2025.25 | F106: =E106+0.25 -> 2025.5 | G106: ='Fleet Build'!E13 -> 3955.177 | H106: ='Fleet Build'!F13 -> 2000 | I106: ='Fleet Build'!G13 -> 2099 | J106: =MAX(0,MIN(F106,I106)-MAX(E106,H106)) -> 0.25 | K106: =G106*J106*'Fleet Build'!$K$58/1000000 -> 0.35232243
B107: ='Fleet Build'!B13 -> Norwegian Encore | C107: ='Fleet Build'!C13 -> Norwegian | D107: 3Q25 | E107: =F$6 -> 2025.5 | F107: =E107+0.25 -> 2025.75 | G107: ='Fleet Build'!E13 -> 3955.177 | H107: ='Fleet Build'!F13 -> 2000 | I107: ='Fleet Build'!G13 -> 2099 | J107: =MAX(0,MIN(F107,I107)-MAX(E107,H107)) -> 0.25 | K107: =G107*J107*'Fleet Build'!$K$58/1000000 -> 0.35232243
...

Sheet Consensus
B2: Public consensus, ratings and company guidance (as of Oct 2, 2026)
B4: Annual consensus
C5: FY2026E | D5: FY2027E | E5: FY2028E | F5: Estimates (FY27) | G5: Low (FY27) | H5: High (FY27)
B6: Revenue ($mm), Yahoo Finance | C6: 10030 | D6: 10570 | F6: 23 | G6: 10260 | H6: 11490
B7: Adjusted EPS, Yahoo Finance | C7: 1.54 | D7: 1.67 | E7: 1.75 | F7: 26 | G7: 1.22 | H7: 1.95
B8: Adjusted EPS, Nasdaq / Zacks | C8: 1.36 | D8: 1.46 | E8: 1.75 | F8: 7 | G8: 0.91 | H8: 1.99
B10: Quarterly consensus EPS (Nasdaq / Zacks)
C11: 3Q26 | D11: 4Q26 | E11: 1Q27 | F11: 2Q27 | G11: 3Q27 | H11: 4Q27 (implied)
B12: Adjusted EPS | C12: 0.83 | D12: -0.1 | E12: -0.04 | F12: 0.37 | G12: 0.97 | H12: =D8-SUM(E12:G12) -> 0.16
B14: FY2027E consensus EPS trend (Yahoo Finance)
C15: 90 days ago | D15: 60 days ago | E15: 30 days ago | F15: 7 days ago | G15: Current
B16: FY2027E EPS | C16: 2.04 | D16: 1.79 | E16: 1.7 | F16: 1.69 | G16: 1.67
B17: Change in the week after the Sept 30 interest guide | F17: =G16-F16 -> -0.02
B19: Ratings and price targets (Nasdaq)
B20: Date | C20: Buy | D20: Hold | E20: Sell | F20: Average target
B21: Sep 2025 | C21: 11 | D21: 4 | E21: 0 | F21: 24.84
B22: Dec 2025 | C22: 9 | D22: 4 | E22: 0 | F22: 18.57
B23: Mar 2026 | C23: 6 | D23: 8 | E23: 0 | F23: 24.79
B24: Jun 2026 | C24: 9 | D24: 11 | E24: 0 | F24: 18.06
B25: Aug 2026 | C25: 6 | D25: 13 | E25: 0 | F25: 18.53
B26: Sep 2026 | C26: 4 | D26: 15 | E26: 0 | F26: 15.43
B27: Oct 2026 | C27: 4 | D27: 15 | E27: 0 | F27: 18.8
B28: Target range, low / high (Oct 2026) | C28: 13 | D28: 25
B30: Company guidance
B31: FY2026 net yield (constant currency) | C31: -0.05
B32: FY2026 Adjusted EBITDA ($mm) | C32: 2500
B33: FY2026 Adjusted EPS | C33: 1.5
B34: FY2026 capacity days (M) | C34: 26.25
B35: FY2026 occupancy | C35: 1.023
B36: FY2026 D&A ($mm) | C36: 1085
B37: FY2026 net interest ($mm) | C37: 705
B38: FY2026 diluted shares (M) | C38: 464
B39: FY2026 fuel (k metric tons) | C39: 1010
B40: FY2026 fuel price per ton, net of hedges ($) | C40: 780
B41: 3Q26 net yield (cc); beat pre-announced Sept 30 | C41: -0.089
B42: 4Q26 implied net yield (CFO, 2Q26 call) | C42: -0.065
... B47: 3Q26 NCC ex fuel per capacity day, y/y (guide) | C47: -0.009
B49: Street-implied FY2027 EBITDA
C50: Yahoo EPS, pre-guide interest | D50: Zacks EPS, guided interest
B51: Consensus FY27 EPS | C51: =D7 -> 1.67 | D51: =D8 -> 1.46
B52: Diluted shares (M) | C52: 466 | D52: 466
B53: Implied adjusted net income ($mm) | C53: =C51*C52 -> 778.22 | D53: =D51*D52 -> 680.36
B54: (+) D&A ($mm) | C54: 1150 | D54: 1150
B55: (+) Net interest ($mm) | C55: 750 | D55: =C43 -> 870
B56: (+) Tax ($mm) | C56: 15 | D56: 15
B57: Street-implied FY2027 Adjusted EBITDA ($mm) | C57: =C53+C54+C55+C56 -> 2693.22 | D57: =D53+D54+D55+D56 -> 2715.36
B58: Consensus FY27 EPS adjusted for the Sept 30 interest guide (Yahoo) | C58: =C51-(C43-C55)/C52 -> 1.4124893
B60: Decoding the average price target
B61: Average target | C61: =F27 -> 18.8
B62: Diluted shares (M) | C62: 466
B63: Implied equity value ($mm) | C63: =C61*C62 -> 8760.8
B64: (+) Net debt at YE2026E ($mm) | C64: =DCF!F22 -> 15800
B65: Implied enterprise value ($mm) | C65: =C63+C64 -> 24560.8
B66: Market EV / FY2027E EBITDA | C66: =DCF!F25 -> 8.4325861
B67: FY2027E EBITDA the average target requires ($mm) | C67: =C65/C66 -> 2912.6059
B69: Source: Yahoo Finance (Analysis); Nasdaq (Zacks earnings forecast, analyst ratings); NCLH 8-Ks (Mar 2, Jul 30, Sep 30, 2026) and 2Q26 call.

Sheet Filings>>>

Sheet Quarterly (A)
B2: NCLH historical financials (as reported, 8-K earnings releases) | D2: Q4'24A | E2: Q1'25A | F2: Q2'25A | G2: Q3'25A | H2: Q4'25A | I2: Q1'26A | J2: Q2'26A | L2: FY2024A | M2: FY2025A
B3: $mm; capacity and passenger days in millions
B5: Passenger ticket revenue | D5: 1408.734 | E5: 1418.684 | F5: 1708.985 | G5: =M5-E5-F5-H5 -> 2049.959 | H5: 1510.039 | I5: 1542.321 | J5: 1729.838 | L5: 6415.545 | M5: 6687.667
B6: Onboard and other revenue | D6: 700.632 | E6: 708.869 | F6: 808.512 | G6: =M6-E6-F6-H6 -> 888.183 | H6: 734.361 | I6: 788.9 | J6: 910.706 | L6: 3064.106 | M6: 3139.925
B7: Total revenue | D7: =D5+D6 -> 2109.366 | E7: =E5+E6 -> 2127.553 | F7: =F5+F6 -> 2517.497 | G7: =G5+G6 -> 2938.142 | H7: =H5+H6 -> 2244.4 | I7: =I5+I6 -> 2331.221 | J7: =J5+J6 -> 2640.544 | L7: =L5+L6 -> 9479.651 | M7: =M5+M6 -> 9827.592
B8: Commissions, transportation and other | D8: 415.58 | E8: 395.343 | F8: 487.835 | G8: =M8-E8-F8-H8 -> 521.981 | H8: 376.845 | I8: 397.605 | J8: 484.668 | L8: 1917.443 | M8: 1782.004
B9: Onboard and other expense | D9: 146.057 | E9: 138.858 | F9: 187.684 | G9: =M9-E9-F9-H9 -> 222.002 | H9: 140.18 | I9: 151.868 | J9: 191.446 | L9: 661.553 | M9: 688.724
B10: Payroll and related | D10: 332.429 | E10: 334.504 | F10: 346.133 | G10: =M10-E10-F10-H10 -> 355.396 | H10: 367.023 | I10: 380.216 | J10: 394.573 | L10: 1344.718 | M10: 1403.056
B11: Fuel | D11: 160.418 | E11: 175.014 | F11: 157.377 | G11: =M11-E11-F11-H11 -> 175.913 | H11: 167.583 | I11: 168.926 | J11: 219.384 | L11: 698.05 | M11: 675.887
B12: Food | D12: 73.142 | E12: 75.588 | F12: 81.323 | G12: =M12-E12-F12-H12 -> 81.866 | H12: 76.683 | I12: 80.682 | J12: 87.322 | L12: 312.992 | M12: 315.46
B13: Other cruise operating expense | D13: 179.953 | E13: 184.631 | F13: 196.495 | G13: =M13-E13-F13-H13 -> 197.701 | H13: 195.205 | I13: 198.584 | J13: 209.415 | L13: 753.94 | M13: 774.032
